Workbook

Sheet May 2
A1: DAILY SALES REPORT
A2: 45414
A3: ITEMS | B3: RETAIL PRICE | C3: PCS SOLD | D3: SALES | E3: DISCOUNTED PRICE | F3: PCS SOLD | G3: SALES | H3: SPECIAL DISC. PRICE | I3: PCS SOLD | J3: SALES | K3: TOTALQTY SOLD | L3: PRODUCTION PRICE | M3: 12% Vat | N3: 10% Mark Up | O3: PROFIT
A4: NAPOLIZ
A5: Backpack Bag | B5: 1750 | D5: =B5*C5 -> 0 | E5: 1600 | G5: =E5*F5 -> 0 | H5: 1400 | J5: =H5*I5 -> 0 | K5: =C5+F5+I5 -> 0 | L5: 840 | M5: 100.8 | N5: 84 | O5: =((B5-L5)*C5)+((E5-L5)*F5)+((H5-L5)*I5) -> 0
A6: Black Tote Bag (Phased Out) | B6: 280 | D6: =B6*C6 -> 0 | G6: =E6*F6 -> 0 | J6: =H6*I6 -> 0 | K6: =C6+F6+I6 -> 0 | L6: 230 | O6: =((B6-L6)*C6)+((E6-L6)*F6)+((H6-L6)*I6) -> 0
A7: Double Canopy | B7: 639 | D7: =B7*C7 -> 0 | E7: 575 | G7: =E7*F7 -> 0 | H7: 500 | J7: =H7*I7 -> 0 | K7: =C7+F7+I7 -> 0 | L7: 330 | M7: 39.6 | N7: 33 | O7: =((B7-L7)*C7)+((E7-L7)*F7)+((H7-L7)*I7) -> 0
A8: Laptop Bag | B8: 1450 | D8: =B8*C8 -> 0 | E8: 1400 | G8: =E8*F8 -> 0 | H8: 1250 | J8: =H8*I8 -> 0 | K8: =C8+F8+I8 -> 0 | L8: 840 | M8: 100.8 | N8: 84 | O8: =((B8-L8)*C8)+((E8-L8)*F8)+((H8-L8)*I8) -> 0
A9: Script Santo Tomas with Tiger Back (B) | B9: 480 | D9: =B9*C9 -> 0 | E9: 460 | G9: =E9*F9 -> 0 | H9: 450 | J9: =H9*I9 -> 0 | K9: =C9+F9+I9 -> 0 | L9: 360 | M9: 43.2 | N9: 36 | O9: =((B9-L9)*C9)+((E9-L9)*F9)+((H9-L9)*I9) -> 0
A10: Side Tiger Hoodie | B10: 1480 | D10: =B10*C10 -> 0 | E10: 1400 | G10: =E10*F10 -> 0 | H10: 1375 | J10: =H10*I10 -> 0 | K10: =C10+F10+I10 -> 0 | L10: 1125 | M10: 135 | N10: 112.5 | O10: =((B10-L10)*C10)+((E10-L10)*F10)+((H10-L10)*I10) -> 0
A11: Sling Bag | B11: 330 | C11: 94 | D11: =B11*C11 -> 31020 | E11: 320 | G11: =E11*F11 -> 0 | H11: 300 | J11: =H11*I11 -> 0 | K11: =C11+F11+I11 -> 94 | L11: 260 | M11: 31.2 | N11: 26 | O11: =((B11-L11)*C11)+((E11-L11)*F11)+((H11-L11)*I11) -> 6580
A12: Front Tiger Hoodie | B12: 1440 | D12: =B12*C12 -> 0 | E12: 1400 | G12: =E12*F12 -> 0 | H12: 1375 | J12: =H12*I12 -> 0 | K12: =C12+F12+I12 -> 0 | L12: 1125 | M12: 135 | N12: 112.5 | O12: =((B12-L12)*C12)+((E12-L12)*F12)+((H12-L12)*I12) -> 0
A13: University of Santo Tomas (B) | B13: 450 | C13: 4 | D13: =B13*C13 -> 1800 | E13: 440 | G13: =E13*F13 -> 0 | H13: 425 | J13: =H13*I13 -> 0 | K13: =C13+F13+I13 -> 4 | L13: 360 | M13: 43.2 | N13: 36 | O13: =((B13-L13)*C13)+((E13-L13)*F13)+((H13-L13)*I13) -> 360
A14: UST Tiger Front and Back Graphic (W) | B14: 500 | D14: =B14*C14 -> 0 | E14: 480 | G14: =E14*F14 -> 0 | H14: 450 | J14: =H14*I14 -> 0 | K14: =C14+F14+I14 -> 0 | L14: 360 | M14: 43.2 | N14: 36 | O14: =((B14-L14)*C14)+((E14-L14)*F14)+((H14-L14)*I14) -> 0
A15: White Tote Bag | B15: 260 | C15: 181 | D15: =B15*C15 -> 47060 | E15: 250 | G15: =E15*F15 -> 0 | H15: 240 | J15: =H15*I15 -> 0 | K15: =C15+F15+I15 -> 181 | L15: 200 | M15: 24 | N15: 20 | O15: =((B15-L15)*C15)+((E15-L15)*F15)+((H15-L15)*I15) -> 10860
A16: Wind Breaker | B16: 1650 | C16: 2 | D16: =B16*C16 -> 3300 | E16: 1600 | G16: =E16*F16 -> 0 | H16: 1500 | J16: =H16*I16 -> 0 | K16: =C16+F16+I16 -> 2 | L16: 1125 | M16: 135 | N16: 112.5 | O16: =((B16-L16)*C16)+((E16-L16)*F16)+((H16-L16)*I16) -> 1050
C17: TOTAL | D17: =SUM(D5:D16) -> 83180 | F17: TOTAL | G17: =SUM(G5:G16) -> 0 | I17: TOTAL | J17: =SUM(J5:J16) -> 0 | L17: TOTAL | O17: =SUM(O5:O16) -> 18850
A18: JYL | B18: RETAIL PRICE | C18: PCS SOLD | D18: SALES | E18: DISCOUNTED PRICE | F18: PCS SOLD | G18: SALES | H18: SPECIAL DISC. PRICE | I18: PCS SOLD | J18: SALES | K18: TOTALQTY SOLD | L18: PRODUCTION PRICE | O18: PROFIT
A19: GT Shirt | B19: 375 | D19: =B19*C19 -> 0 | E19: 350 | G19: =E19*F19 -> 0 | H19: 325 | J19: =H19*I19 -> 0 | K19: =C19+F19+I19 -> 0 | L19: 250 | M19: 30 | N19: 25 | O19: =((B19-L19)*C19)+((E19-L19)*F19)+((H19-L19)*I19) -> 0
A20: Jacket | B20: 1900 | C20: 3 | D20: =B20*C20 -> 5700 | E20: 1700 | G20: =E20*F20 -> 0 | H20: 1500 | J20: =H20*I20 -> 0 | K20: =C20+F20+I20 -> 3 | L20: 1200 | M20: 144 | N20: 120 | O20: =((B20-L20)*C20)+((E20-L20)*F20)+((H20-L20)*I20) -> 2100
A21: Poloshirt 123456 | B21: 860 | C21: 5 | D21: =B21*C21 -> 4300 | E21: 800 | G21: =E21*F21 -> 0 | H21: 750 | J21: =H21*I21 -> 0 | K21: =C21+F21+I21 -> 5 | L21: 600 | M21: 72 | N21: 60 | O21: =((B21-L21)*C21)+((E21-L21)*F21)+((H21-L21)*I21) -> 1300
A22: VB Jersey w/ sig. (Phased Out) | B22: 2800 | D22: =B22*C22 -> 0 | G22: =E22*F22 -> 0 | J22: =H22*I22 -> 0 | K22: =C22+F22+I22 -> 0 | L22: 800 | M22: 96 | N22: 80 | O22: =((B22-L22)*C22)+((E22-L22)*F22)+((H22-L22)*I22) -> 0
A23: VB Jersey w/o sig. | B23: 2000 | D23: =B23*C23 -> 0 | E23: 1800 | G23: =E23*F23 -> 0 | H23: 1500 | J23: =H23*I23 -> 0 | K23: =C23+F23+I23 -> 0 | L23: 800 | O23: =((B23-L23)*C23)+((E23-L23)*F23)+((H23-L23)*I23) -> 0
A24: VB Jersey w/o sig. | B24: 1500 | C24: 3 | D24: =B24*C24 -> 4500 | E24: 1400 | G24: =E24*F24 -> 0 | H24: 1300 | J24: =H24*I24 -> 0 | K24: =C24+F24+I24 -> 3 | L24: 800 | O24: =((B24-L24)*C24)+((E24-L24)*F24)+((H24-L24)*I24) -> 2100
A25: VB Jersey w/o sig. | B25: 1000 | D25: =B25*C25 -> 0 | E25: 980 | G25: =E25*F25 -> 0 | H25: 950 | J25: =H25*I25 -> 0 | K25: =C25+F25+I25 -> 0 | L25: 800 | O25: =((B25-L25)*C25)+((E25-L25)*F25)+((H25-L25)*I25) -> 0
A26: VB Jersey with sig. (Phased Out) | B26: 1500 | D26: =B26*C26 -> 0 | G26: =E26*F26 -> 0 | J26: =H26*I26 -> 0 | K26: =C26+F26+I26 -> 0 | L26: 800 | O26: =((B26-L26)*C26)+((E26-L26)*F26)+((H26-L26)*I26) -> 0
C27: TOTAL | D27: =SUM(D19:D26) -> 14500 | F27: TOTAL | G27: =SUM(G19:G26) -> 0 | I27: TOTAL | J27: =SUM(J19:J26) -> 0 | L27: TOTAL | O27: =SUM(O19:O26) -> 5500
A28: JUC | B28: RETAIL PRICE | C28: PCS SOLD | D28: SALES | E28: DISCOUNTED PRICE | F28: PCS SOLD | G28: SALES | H28: SPECIAL DISC. PRICE | I28: PCS SOLD | J28: SALES | K28: TOTALQTY SOLD | L28: PRODUCTION PRICE | O28: PROFIT
A29: UST OAT Hoodie Jacket | B29: 1450 | C29: 1 | D29: =B29*C29 -> 1450 | E29: 1400 | G29: =E29*F29 -> 0 | H29: 1300 | J29: =H29*I29 -> 0 | K29: =C29+F29+I29 -> 1 | L29: 1000 | M29: 120 | N29: 100 | O29: =((B29-L29)*C29)+((E29-L29)*F29)+((H29-L29)*I29) -> 450
A30: UST OAT T-Shirt | B30: 375 | D30: =B30*C30 -> 0 | E30: 360 | G30: =E30*F30 -> 0 | H30: 340 | J30: =H30*I30 -> 0 | K30: =C30+F30+I30 -> 0 | L30: 280 | M30: 33.6 | N30: 28 | O30: =((B30-L30)*C30)+((E30-L30)*F30)+((H30-L30)*I30) -> 0
A31: UST T-Shirt Sports | B31: 430 | C31: 9 | D31: =B31*C31 -> 3870 | E31: 400 | G31: =E31*F31 -> 0 | H31: 350 | J31: =H31*I31 -> 0 | K31: =C31+F31+I31 -> 9 | L31: 260 | M31: 31.2 | N31: 26 | O31: =((B31-L31)*C31)+((E31-L31)*F31)+((H31-L31)*I31) -> 1530
A32: UST T-Shirt Tiger Pattern | B32: 450 | C32: 2 | D32: =B32*C32 -> 900 | E32: 430 | G32: =E32*F32 -> 0 | H32: 400 | J32: =H32*I32 -> 0 | K32: =C32+F32+I32 -> 2 | L32: 330 | M32: 39.6 | N32: 33 | O32: =((B32-L32)*C32)+((E32-L32)*F32)+((H32-L32)*I32) -> 240
A33: UST Happy Tiger | B33: 450 | D33: =B33*C33 -> 0 | E33: 400 | G33: =E33*F33 -> 0 | H33: 375 | J33: =H33*I33 -> 0 | K33: =C33+F33+I33 -> 0 | L33: 280 | M33: 33.6 | N33: 28 | O33: =((B33-L33)*C33)+((E33-L33)*F33)+((H33-L33)*I33) -> 0
A34: OAT Tote Bag (Phased Out) | B34: 220 | D34: =B34*C34 -> 0 | G34: =E34*F34 -> 0 | J34: =H34*I34 -> 0 | K34: =C34+F34+I34 -> 0 | L34: 120 | O34: =((B34-L34)*C34)+((E34-L34)*F34)+((H34-L34)*I34) -> 0
C35: TOTAL | D35: =SUM(D31:D34) -> 4770 | F35: TOTAL | G35: =SUM(G31:G34) -> 0 | I35: TOTAL | J35: =SUM(J31:J34) -> 0 | L35: TOTAL | O35: =SUM(O29:O34) -> 2220
A36: USTORE | B36: RETAIL PRICE | C36: PCS SOLD | D36: SALES | E36: DISCOUNTED PRICE | F36: PCS SOLD | G36: SALES | H36: SPECIAL DISC. PRICE | I36: PCS SOLD | J36: SALES | K36: TOTALQTY SOLD | L36: PRODUCTION PRICE | O36: PROFIT
A37: Auto Umbrella | B37: 250 | D37: =B37*C37 -> 0 | G37: =E37*F37 -> 0 | J37: =H37*I37 -> 0 | K37: =C37+F37+I37 -> 0 | O37: =((B37-L37)*C37)+((E37-L37)*F37)+((H37-L37)*I37) -> 0
A38: Bag | B38: 250 | D38: =B38*C38 -> 0 | G38: =E38*F38 -> 0 | J38: =H38*I38 -> 0 | K38: =C38+F38+I38 -> 0 | O38: =((B38-L38)*C38)+((E38-L38)*F38)+((H38-L38)*I38) -> 0
A39: Eco Bag CGEEE! | B39: 50 | C39: 3 | D39: =B39*C39 -> 150 | E39: 35 | G39: =E39*F39 -> 0 | J39: =H39*I39 -> 0 | K39: =C39+F39+I39 -> 3 | O39: =((B39-L39)*C39)+((E39-L39)*F39)+((H39-L39)*I39) -> 150
A40: Keychain | B40: 150 | C40: 2 | D40: =B40*C40 -> 300 | E40: 120 | G40: =E40*F40 -> 0 | H40: 75 | J40: =H40*I40 -> 0 | K40: =C40+F40+I40 -> 2 | O40: =((B40-L40)*C40)+((E40-L40)*F40)+((H40-L40)*I40) -> 300
A41: Kit Set | B41: 800 | D41: =B41*C41 -> 0 | E41: 750 | G41: =E41*F41 -> 0 | H41: 700 | J41: =H41*I41 -> 0 | K41: =C41+F41+I41 -> 0 | O41: =((B41-L41)*C41)+((E41-L41)*F41)+((H41-L41)*I41) -> 0
A42: Lanyard | B42: 190 | C42: 3 | D42: =B42*C42 -> 570 | E42: 175 | G42: =E42*F42 -> 0 | H42: 150 | J42: =H42*I42 -> 0 | K42: =C42+F42+I42 -> 3 | L42: 117 | M42: 14.04 | N42: 11.7 | O42: =((B42-L42)*C42)+((E42-L42)*F42)+((H42-L42)*I42) -> 219
A43: Lanyard | B43: 180 | D43: =B43*C43 -> 0 | E43: 165 | G43: =E43*F43 -> 0 | H43: 140 | J43: =H43*I43 -> 0 | K43: =C43+F43+I43 -> 0 | L43: 110 | M43: 13.2 | N43: 11 | O43: =((B43-L43)*C43)+((E43-L43)*F43)+((H43-L43)*I43) -> 0
A44: NB | B44: 75 | D44: =B44*C44 -> 0 | G44: =E44*F44 -> 0 | J44: =H44*I44 -> 0 | K44: =C44+F44+I44 -> 0 | O44: =((B44-L44)*C44)+((E44-L44)*F44)+((H44-L44)*I44) -> 0
A45: NB | B45: 100 | C45: 140 | D45: =B45*C45 -> 14000 | E45: 80 | F45: 120 | G45: =E45*F45 -> 9600 | H45: 70 | J45: =H45*I45 -> 0 | K45: =C45+F45+I45 -> 260 | O45: =((B45-L45)*C45)+((E45-L45)*F45)+((H45-L45)*I45) -> 23600
A46: Sash Big | B46: 600 | D46: =B46*C46 -> 0 | E46: 500 | G46: =E46*F46 -> 0 | H46: 400 | J46: =H46*I46 -> 0 | K46: =C46+F46+I46 -> 0 | O46: =((B46-L46)*C46)+((E46-L46)*F46)+((H46-L46)*I46) -> 0
A47: Sash Small | B47: 150 | D47: =B47*C47 -> 0 | E47: 125 | G47: =E47*F47 -> 0 | H47: 100 | J47: =H47*I47 -> 0 | K47: =C47+F47+I47 -> 0 | O47: =((B47-L47)*C47)+((E47-L47)*F47)+((H47-L47)*I47) -> 0
A48: Shabby Hat | B48: 200 | C48: 13 | D48: =B48*C48 -> 2600 | E48: 175 | G48: =E48*F48 -> 0 | H48: 150 | J48: =H48*I48 -> 0 | K48: =C48+F48+I48 -> 13 | O48: =((B48-L48)*C48)+((E48-L48)*F48)+((H48-L48)*I48) -> 2600
A49: Tiger Stuff Toy Small Grad | B49: 250 | C49: 5 | D49: =B49*C49 -> 1250 | E49: 230 | G49: =E49*F49 -> 0 | H49: 200 | J49: =H49*I49 -> 0 | K49: =C49+F49+I49 -> 5 | O49: =((B49-L49)*C49)+((E49-L49)*F49)+((H49-L49)*I49) -> 1250
A50: Tote Bag CGEEE! | B50: 120 | D50: =B50*C50 -> 0 | E50: 100 | G50: =E50*F50 -> 0 | H50: 80 | J50: =H50*I50 -> 0 | K50: =C50+F50+I50 -> 0 | O50: =((B50-L50)*C50)+((E50-L50)*F50)+((H50-L50)*I50) -> 0
A51: Tote Bag Canvas White | B51: 160 | C51: 250 | D51: =B51*C51 -> 40000 | G51: =E51*F51 -> 0 | J51: =H51*I51 -> 0 | K51: =C51+F51+I51 -> 250 | O51: =((B51-L51)*C51)+((E51-L51)*F51)+((H51-L51)*I51) -> 40000
A52: Tote (One For UST) | B52: 300 | C52: 112 | D52: =B52*C52 -> 33600 | E52: 275 | G52: =E52*F52 -> 0 | H52: 250 | J52: =H52*I52 -> 0 | K52: =C52+F52+I52 -> 112 | O52: =((B52-L52)*C52)+((E52-L52)*F52)+((H52-L52)*I52) -> 33600
A53: Tumbler | B53: 150 | C53: 127 | D53: =B53*C53 -> 19050 | G53: =E53*F53 -> 0 | J53: =H53*I53 -> 0 | K53: =C53+F53+I53 -> 127 | O53: =((B53-L53)*C53)+((E53-L53)*F53)+((H53-L53)*I53) -> 19050
A54: Umb. Cane | B54: 500 | D54: =B54*C54 -> 0 | E54: 450 | G54: =E54*F54 -> 0 | H54: 400 | J54: =H54*I54 -> 0 | K54: =C54+F54+I54 -> 0 | O54: =((B54-L54)*C54)+((E54-L54)*F54)+((H54-L54)*I54) -> 0
A55: Umb (One For UST) | B55: 350 | C55: 60 | D55: =B55*C55 -> 21000 | E55: 300 | G55: =E55*F55 -> 0 | H55: 250 | J55: =H55*I55 -> 0 | K55: =C55+F55+I55 -> 60 | O55: =((B55-L55)*C55)+((E55-L55)*F55)+((H55-L55)*I55) -> 21000
A56: Utensil | B56: 250 | C56: 260 | D56: =B56*C56 -> 65000 | E56: 200 | G56: =E56*F56 -> 0 | H56: 180 | J56: =H56*I56 -> 0 | K56: =C56+F56+I56 -> 260
C57: TOTAL | D57: =SUM(D37:D56) -> 197520 | F57: TOTAL | G57: =SUM(G37:G56) -> 9600 | I57: TOTAL | J57: =SUM(J37:J56) -> 0 | L57: TOTAL | O57: =SUM(O37:O56) -> 141769
A58: TET AND DARS | B58: RETAIL PRICE | C58: PCS SOLD | D58: SALES | E58: DISCOUNTED PRICE | F58: PCS SOLD | G58: SALES | H58: SPECIAL DISC. PRICE | I58: PCS SOLD | J58: SALES | K58: TOTALQTY SOLD | L58: PRODUCTION PRICE | O58: PROFIT
A59: Arch | B59: 320 | D59: =B59*C59 -> 0 | E59: 300 | G59: =E59*F59 -> 0 | H59: 300 | J59: =H59*I59 -> 0 | K59: =C59+F59+I59 -> 0 | L59: 240 | M59: 28.8 | N59: 24 | O59: =((B59-L59)*C59)+((E59-L59)*F59)+((H59-L59)*I59) -> 0
A60: Eco Bag | B60: 80 | D60: =B60*C60 -> 0 | E60: 70 | G60: =E60*F60 -> 0 | H60: 60 | J60: =H60*I60 -> 0 | K60: =C60+F60+I60 -> 0 | L60: 60 | O60: =((B60-L60)*C60)+((E60-L60)*F60)+((H60-L60)*I60) -> 0
A61: Eco Bag | B61: 130 | D61: =B61*C61 -> 0 | E61: 120 | G61: =E61*F61 -> 0 | H61: 110 | J61: =H61*I61 -> 0 | K61: =C61+F61+I61 -> 0 | L61: 100 | O61: =((B61-L61)*C61)+((E61-L61)*F61)+((H61-L61)*I61) -> 0
A62: Main Building | B62: 430 | D62: =B62*C62 -> 0 | E62: 430 | G62: =E62*F62 -> 0 | H62: 430 | J62: =H62*I62 -> 0 | K62: =C62+F62+I62 -> 0 | L62: 350 | M62: 42 | N62: 35 | O62: =((B62-L62)*C62)+((E62-L62)*F62)+((H62-L62)*I62) -> 0
A63: Mug | B63: 170 | D63: =B63*C63 -> 0 | E63: 160 | G63: =E63*F63 -> 0 | H63: 150 | J63: =H63*I63 -> 0 | K63: =C63+F63+I63 -> 0 | L63: 125 | M63: 15 | N63: 12.5 | O63: =((B63-L63)*C63)+((E63-L63)*F63)+((H63-L63)*I63) -> 0
A64: Notebook | B64: 220 | D64: =B64*C64 -> 0 | G64: =E64*F64 -> 0 | J64: =H64*I64 -> 0 | K64: =C64+F64+I64 -> 0 | O64: =((B64-L64)*C64)+((E64-L64)*F64)+((H64-L64)*I64) -> 0
A65: Pen | B65: 50 | D65: =B65*C65 -> 0 | G65: =E65*F65 -> 0 | J65: =H65*I65 -> 0 | K65: =C65+F65+I65 -> 0 | L65: 42 | O65: =((B65-L65)*C65)+((E65-L65)*F65)+((H65-L65)*I65) -> 0
A66: Pen | B66: 25 | D66: =B66*C66 -> 0 | G66: =E66*F66 -> 0 | J66: =H66*I66 -> 0 | K66: =C66+F66+I66 -> 0 | L66: 20 | O66: =((B66-L66)*C66)+((E66-L66)*F66)+((H66-L66)*I66) -> 0
A67: Sticker | B67: 115 | D67: =B67*C67 -> 0 | E67: 110 | G67: =E67*F67 -> 0 | H67: 105 | J67: =H67*I67 -> 0 | K67: =C67+F67+I67 -> 0 | L67: 85 | O67: =((B67-L67)*C67)+((E67-L67)*F67)+((H67-L67)*I67) -> 0
A68: Sticker | B68: 20 | D68: =B68*C68 -> 0 | E68: 20 | G68: =E68*F68 -> 0 | H68: 20 | J68: =H68*I68 -> 0 | K68: =C68+F68+I68 -> 0 | L68: 15 | O68: =((B68-L68)*C68)+((E68-L68)*F68)+((H68-L68)*I68) -> 0
A69: Tote | B69: 230 | D69: =B69*C69 -> 0 | G69: =E69*F69 -> 0 | J69: =H69*I69 -> 0 | K69: =C69+F69+I69 -> 0 | O69: =((B69-L69)*C69)+((E69-L69)*F69)+((H69-L69)*I69) -> 0
C70: TOTAL | D70: =SUM(D59:D69) -> 0 | F70: TOTAL | G70: =SUM(G59:G69) -> 0 | I70: TOTAL | J70: =SUM(J59:J69) -> 0 | L70: TOTAL | O70: =SUM(O59:O69) -> 0
A71: BLAZE | B71: RETAIL PRICE | C71: PCS SOLD | D71: SALES | E71: DISCOUNTED PRICE | F71: PCS SOLD | G71: SALES | H71: SPECIAL DISC. PRICE | I71: PCS SOLD | J71: SALES | K71: TOTALQTY SOLD | L71: PRODUCTION PRICE | O71: PROFIT
A72: Crew Neck Shirt | B72: 475 | D72: =B72*C72 -> 0 | E72: 450 | G72: =E72*F72 -> 0 | H72: 430 | J72: =H72*I72 -> 0 | K72: =C72+F72+I72 -> 0 | L72: 350 | M72: 42 | N72: 35 | O72: =((B72-L72)*C72)+((E72-L72)*F72)+((H72-L72)*I72) -> 0
A73: Polo Shirt | B73: 800 | D73: =B73*C73 -> 0 | E73: 750 | F73: 4 | G73: =E73*F73 -> 3000 | H73: 700 | J73: =H73*I73 -> 0 | K73: =C73+F73+I73 -> 4 | L73: 550 | M73: 66 | N73: 55 | O73: =((B73-L73)*C73)+((E73-L73)*F73)+((H73-L73)*I73) -> 800
A74: Socks | B74: 375 | D74: =B74*C74 -> 0 | E74: 350 | G74: =E74*F74 -> 0 | H74: 325 | J74: =H74*I74 -> 0 | K74: =C74+F74+I74 -> 0 | L74: 250 | M74: 30 | N74: 25 | O74: =((B74-L74)*C74)+((E74-L74)*F74)+((H74-L74)*I74) -> 0
A75: socks set of 3 | B75: 950 | D75: =B75*C75 -> 0 | E75: 900 | G75: =E75*F75 -> 0 | H75: 800 | J75: =H75*I75 -> 0 | K75: =C75+F75+I75 -> 0 | L75: 750 | M75: 90 | N75: 75 | O75: =((B75-L75)*C75)+((E75-L75)*F75)+((H75-L75)*I75) -> 0
C76: TOTAL | D76: =SUM(D72:D75) -> 0 | F76: TOTAL | G76: =SUM(G72:G75) -> 3000 | I76: TOTAL | J76: =SUM(J72:J75) -> 0 | L76: TOTAL | O76: =SUM(O72:O75) -> 800
A77: MITSUI | B77: RETAIL PRICE | C77: PCS SOLD | D77: SALES | E77: DISCOUNTED PRICE | F77: PCS SOLD | G77: SALES | H77: SPECIAL DISC. PRICE | I77: PCS SOLD | J77: SALES | K77: TOTALQTY SOLD | L77: PRODUCTION PRICE | O77: PROFIT
A78: Stylus pen | B78: 45 | D78: =B78*C78 -> 0 | E78: 40 | G78: =E78*F78 -> 0 | H78: 25 | J78: =H78*I78 -> 0 | K78: =C78+F78+I78 -> 0 | L78: 17.36 | M78: 2.08 | N78: 1.74 | O78: =((B78-L78)*C78)+((E78-L78)*F78)+((H78-L78)*I78) -> 0
A79: Retractable | B79: 25 | D79: =B79*C79 -> 0 | E79: 15 | G79: =E79*F79 -> 0 | H79: 20 | J79: =H79*I79 -> 0 | K79: =C79+F79+I79 -> 0 | L79: 10.08 | M79: 1.21 | N79: 1.01 | O79: =((B79-L79)*C79)+((E79-L79)*F79)+((H79-L79)*I79) -> 0
C80: TOTAL | D80: =SUM(D78+D79) -> 0 | F80: TOTAL | G80: =SUM(G78+G79) -> 0 | I80: TOTAL | J80: =SUM(J78+J79) -> 0 | L80: TOTAL | O80: =SUM(O78) -> 0
A81: CENTRAL SEMINARY | B81: RETAIL PRICE | C81: PCS SOLD | D81: SALES | E81: DISCOUNTED PRICE | F81: PCS SOLD | G81: SALES | H81: SPECIAL DISC. PRICE | I81: PCS SOLD | J81: SALES | K81: TOTALQTY SOLD | L81: PRODUCTION PRICE | O81: PROFIT
A82: Subli. Shirt | B82: 550 | C82: 16 | D82: =B82*C82 -> 8800 | G82: =E82*F82 -> 0 | J82: =H82*I82 -> 0 | K82: =C82+F82+I82 -> 16 | L82: 500 | O82: =D82-L82 -> 8300
C83: GRAND TOTAL | D83: =D17+D27+D35+D57+D70+D76+D80+D82 -> 308770 | F83: GRAND TOTAL | G83: =G17+G27+G35+G57+G70+G76+G80+G82 -> 12600 | I83: GRAND TOTAL | J83: =J17+J27+J35+J57+J70+J76+J80+J82 -> 0 | L83: GRAND TOTAL | O83: =O17+O27+O35+O57+O70+O76+O80+O82 -> 177439
C84: TOTAL SALE | E84: =D83+G83+J83 -> 321370 | J84: TOTAL PROFIT | O84: =O83 -> 177439
B85: CASH BREAKDOWN
B86: BILLS | D86: PCS | G86: AMOUNT | J86: REFERENCE NUMBER | N86: AMOUNT
B87: 1000 | D87: 15 | G87: =D87*B87 -> 15000 | N87: 1400
B88: 500 | D88: 3 | G88: =B88*D88 -> 1500 | N88: 700
B89: 200 | G89: =D89*B89 -> 0 | N89: 2020
B90: 100 | G90: =B90*D90 -> 0 | N90: 880
B91: 50 | G91: =D91*B91 -> 0 | N91: 1710
B92: 20 | G92: =B92*D92 -> 0 | N92: 250
B93: COINS | D93: PCS | G93: AMOUNT | N93: 1300
B94: 20 | G94: =D94*B94 -> 0 | N94: 1500
B95: 10 | G95: =B95*D95 -> 0 | N95: 750
B96: 5 | G96: =D96*B96 -> 0
B97: 1 | G97: =B97*D97 -> 0
E98: CASH | G98: =SUM(G87:G97) -> 16500 | J98: TOTAL | N98: =SUM(N87:N97) -> 10510
E99: GCASH | G99: =N98 -> 10510
E100: CASH REQ | G100: 295400
...

Sheet May 3
A1: DAILY SALES REPORT
A2: 45415
A3: ITEMS | B3: RETAIL PRICE | C3: PCS SOLD | D3: SALES | E3: DISCOUNTED PRICE | F3: PCS SOLD | G3: SALES | H3: SPECIAL DISC. PRICE | I3: PCS SOLD | J3: SALES | K3: TOTAL SALES | L3: TOTALQTY SOLD | M3: PRODUCTION PRICE | N3: 12% Vat | O3: 10% Mark Up | P3: PROFIT
A4: NAPOLIZ
A5: Backpack Bag | B5: 1750 | D5: =B5*C5 -> 0 | E5: 1600 | G5: =E5*F5 -> 0 | H5: 1400 | J5: =H5*I5 -> 0 | K5: =D5+G5+J5 -> 0 | L5: =C5+F5+I5 -> 0 | M5: 840 | N5: 100.8 | O5: 84 | P5: =((B5-M5)*C5)+((E5-M5)*F5)+((H5-M5)*I5) -> 0
A6: Black Tote Bag (Phased Out) | B6: 280 | D6: =B6*C6 -> 0 | G6: =E6*F6 -> 0 | J6: =H6*I6 -> 0 | K6: =D6+G6+J6 -> 0 | L6: =C6+F6+I6 -> 0 | M6: 230 | P6: =((B6-M6)*C6)+((E6-M6)*F6)+((H6-M6)*I6) -> 0
A7: Double Canopy | B7: 639 | D7: =B7*C7 -> 0 | E7: 575 | G7: =E7*F7 -> 0 | H7: 500 | J7: =H7*I7 -> 0 | K7: =D7+G7+J7 -> 0 | L7: =C7+F7+I7 -> 0 | M7: 330 | N7: 39.6 | O7: 33 | P7: =((B7-M7)*C7)+((E7-M7)*F7)+((H7-M7)*I7) -> 0
A8: Laptop Bag | B8: 1450 | D8: =B8*C8 -> 0 | E8: 1400 | G8: =E8*F8 -> 0 | H8: 1250 | J8: =H8*I8 -> 0 | K8: =D8+G8+J8 -> 0 | L8: =C8+F8+I8 -> 0 | M8: 840 | N8: 100.8 | O8: 84 | P8: =((B8-M8)*C8)+((E8-M8)*F8)+((H8-M8)*I8) -> 0
A9: Script Santo Tomas with Tiger Back (B) | B9: 480 | D9: =B9*C9 -> 0 | E9: 460 | G9: =E9*F9 -> 0 | H9: 450 | J9: =H9*I9 -> 0 | K9: =D9+G9+J9 -> 0 | L9: =C9+F9+I9 -> 0 | M9: 360 | N9: 43.2 | O9: 36 | P9: =((B9-M9)*C9)+((E9-M9)*F9)+((H9-M9)*I9) -> 0
A10: Side Tiger Hoodie | B10: 1480 | C10: 1 | D10: =B10*C10 -> 1480 | E10: 1400 | G10: =E10*F10 -> 0 | H10: 1375 | J10: =H10*I10 -> 0 | K10: =D10+G10+J10 -> 1480 | L10: =C10+F10+I10 -> 1 | M10: 1125 | N10: 135 | O10: 112.5 | P10: =((B10-M10)*C10)+((E10-M10)*F10)+((H10-M10)*I10) -> 355
A11: Sling Bag | B11: 330 | D11: =B11*C11 -> 0 | E11: 320 | G11: =E11*F11 -> 0 | H11: 300 | J11: =H11*I11 -> 0 | K11: =D11+G11+J11 -> 0 | L11: =C11+F11+I11 -> 0 | M11: 260 | N11: 31.2 | O11: 26 | P11: =((B11-M11)*C11)+((E11-M11)*F11)+((H11-M11)*I11) -> 0
A12: Front Tiger Hoodie | B12: 1440 | D12: =B12*C12 -> 0 | E12: 1400 | G12: =E12*F12 -> 0 | H12: 1375 | J12: =H12*I12 -> 0 | K12: =D12+G12+J12 -> 0 | L12: =C12+F12+I12 -> 0 | M12: 1125 | N12: 135 | O12: 112.5 | P12: =((B12-M12)*C12)+((E12-M12)*F12)+((H12-M12)*I12) -> 0
A13: University of Santo Tomas (B) | B13: 450 | C13: 7 | D13: =B13*C13 -> 3150 | E13: 440 | G13: =E13*F13 -> 0 | H13: 425 | I13: 8 | J13: =H13*I13 -> 3400 | K13: =D13+G13+J13 -> 6550 | L13: =C13+F13+I13 -> 15 | M13: 360 | N13: 43.2 | O13: 36 | P13: =((B13-M13)*C13)+((E13-M13)*F13)+((H13-M13)*I13) -> 1150
A14: UST Tiger Front and Back Graphic (W) | B14: 500 | C14: 2 | D14: =B14*C14 -> 1000 | E14: 480 | G14: =E14*F14 -> 0 | H14: 450 | J14: =H14*I14 -> 0 | K14: =D14+G14+J14 -> 1000 | L14: =C14+F14+I14 -> 2 | M14: 360 | N14: 43.2 | O14: 36 | P14: =((B14-M14)*C14)+((E14-M14)*F14)+((H14-M14)*I14) -> 280
A15: White Tote Bag | B15: 260 | C15: 3 | D15: =B15*C15 -> 780 | E15: 250 | G15: =E15*F15 -> 0 | H15: 240 | J15: =H15*I15 -> 0 | K15: =D15+G15+J15 -> 780 | L15: =C15+F15+I15 -> 3 | M15: 200 | N15: 24 | O15: 20 | P15: =((B15-M15)*C15)+((E15-M15)*F15)+((H15-M15)*I15) -> 180
A16: Wind Breaker | B16: 1650 | D16: =B16*C16 -> 0 | E16: 1600 | G16: =E16*F16 -> 0 | H16: 1500 | I16: 3 | J16: =H16*I16 -> 4500 | K16: =D16+G16+J16 -> 4500 | L16: =C16+F16+I16 -> 3 | M16: 1125 | N16: 135 | O16: 112.5 | P16: =((B16-M16)*C16)+((E16-M16)*F16)+((H16-M16)*I16) -> 1125
C17: TOTAL | D17: =SUM(D5:D16) -> 6410 | F17: TOTAL | G17: =SUM(G5:G16) -> 0 | I17: TOTAL | J17: =SUM(J5:J16) -> 7900 | K17: =D17+G17+J17 -> 14310 | M17: TOTAL | P17: =SUM(P5:P16) -> 3090
A18: JYL | B18: RETAIL PRICE | C18: PCS SOLD | D18: SALES | E18: DISCOUNTED PRICE | F18: PCS SOLD | G18: SALES | H18: SPECIAL DISC. PRICE | I18: PCS SOLD | J18: SALES | K18: TOTAL SALES | L18: TOTALQTY SOLD | M18: PRODUCTION PRICE | N18: 12% Vat | O18: 10% Mark Up | P18: PROFIT
A19: GT Shirt | B19: 375 | D19: =B19*C19 -> 0 | E19: 350 | G19: =E19*F19 -> 0 | H19: 325 | J19: =H19*I19 -> 0 | K19: =D19+G19+J19 -> 0 | L19: =C19+F19+I19 -> 0 | M19: 250 | N19: 30 | O19: 25 | P19: =((B19-M19)*C19)+((E19-M19)*F19)+((H19-M19)*I19) -> 0
A20: Jacket | B20: 1900 | D20: =B20*C20 -> 0 | E20: 1700 | G20: =E20*F20 -> 0 | H20: 1500 | J20: =H20*I20 -> 0 | K20: =D20+G20+J20 -> 0 | L20: =C20+F20+I20 -> 0 | M20: 1200 | N20: 144 | O20: 120 | P20: =((B20-M20)*C20)+((E20-M20)*F20)+((H20-M20)*I20) -> 0
A21: Poloshirt 123456 | B21: 860 | C21: 1 | D21: =B21*C21 -> 860 | E21: 800 | G21: =E21*F21 -> 0 | H21: 750 | J21: =H21*I21 -> 0 | K21: =D21+G21+J21 -> 860 | L21: =C21+F21+I21 -> 1 | M21: 600 | N21: 72 | O21: 60 | P21: =((B21-M21)*C21)+((E21-M21)*F21)+((H21-M21)*I21) -> 260
A22: VB Jersey w/ sig. (Phased Out) | B22: 2800 | D22: =B22*C22 -> 0 | G22: =E22*F22 -> 0 | J22: =H22*I22 -> 0 | K22: =D22+G22+J22 -> 0 | L22: =C22+F22+I22 -> 0 | M22: 800 | N22: 96 | O22: 80 | P22: =((B22-M22)*C22)+((E22-M22)*F22)+((H22-M22)*I22) -> 0
A23: VB Jersey w/o sig. | B23: 2000 | D23: =B23*C23 -> 0 | E23: 1800 | G23: =E23*F23 -> 0 | H23: 1500 | J23: =H23*I23 -> 0 | K23: =D23+G23+J23 -> 0 | L23: =C23+F23+I23 -> 0 | M23: 800 | P23: =((B23-M23)*C23)+((E23-M23)*F23)+((H23-M23)*I23) -> 0
A24: VB Jersey w/o sig. | B24: 1500 | D24: =B24*C24 -> 0 | E24: 1400 | G24: =E24*F24 -> 0 | H24: 1300 | J24: =H24*I24 -> 0 | K24: =D24+G24+J24 -> 0 | L24: =C24+F24+I24 -> 0 | M24: 800 | P24: =((B24-M24)*C24)+((E24-M24)*F24)+((H24-M24)*I24) -> 0
A25: VB Jersey w/o sig. | B25: 1000 | D25: =B25*C25 -> 0 | E25: 980 | G25: =E25*F25 -> 0 | H25: 950 | J25: =H25*I25 -> 0 | K25: =D25+G25+J25 -> 0 | L25: =C25+F25+I25 -> 0 | M25: 800 | P25: =((B25-M25)*C25)+((E25-M25)*F25)+((H25-M25)*I25) -> 0
A26: VB Jersey with sig. (Phased Out) | B26: 1500 | D26: =B26*C26 -> 0 | G26: =E26*F26 -> 0 | J26: =H26*I26 -> 0 | K26: =D26+G26+J26 -> 0 | L26: =C26+F26+I26 -> 0 | M26: 800 | P26: =((B26-M26)*C26)+((E26-M26)*F26)+((H26-M26)*I26) -> 0
C27: TOTAL | D27: =SUM(D19:D26) -> 860 | F27: TOTAL | G27: =SUM(G19:G26) -> 0 | I27: TOTAL | J27: =SUM(J19:J26) -> 0 | K27: =D27+G27+J27 -> 860 | M27: TOTAL | P27: =SUM(P19:P26) -> 260
A28: JUC | B28: RETAIL PRICE | C28: PCS SOLD | D28: SALES | E28: DISCOUNTED PRICE | F28: PCS SOLD | G28: SALES | H28: SPECIAL DISC. PRICE | I28: PCS SOLD | J28: SALES | K28: TOTAL SALES | L28: TOTALQTY SOLD | M28: PRODUCTION PRICE | N28: 12% Vat | O28: 10% Mark Up | P28: PROFIT
A29: UST OAT Hoodie Jacket | B29: 1450 | D29: =B29*C29 -> 0 | E29: 1400 | G29: =E29*F29 -> 0 | H29: 1300 | J29: =H29*I29 -> 0 | K29: =D29+G29+J29 -> 0 | L29: =C29+F29+I29 -> 0 | M29: 1000 | N29: 120 | O29: 100 | P29: =((B29-M29)*C29)+((E29-M29)*F29)+((H29-M29)*I29) -> 0
A30: UST OAT MUG | B30: 150 | D30: =B30*C30 -> 0 | E30: 140 | G30: =E30*F30 -> 0 | H30: 135 | J30: =H30*I30 -> 0 | K30: =D30+G30+J30 -> 0 | L30: =C30+F30+I30 -> 0 | M30: 100 | N30: 12 | O30: 10 | P30: =((B30-M30)*C30)+((E30-M30)*F30)+((H30-M30)*I30) -> 0
A31: UST OAT T-Shirt | B31: 375 | D31: =B31*C31 -> 0 | E31: 360 | G31: =E31*F31 -> 0 | H31: 340 | J31: =H31*I31 -> 0 | K31: =D31+G31+J31 -> 0 | L31: =C31+F31+I31 -> 0 | M31: 280 | N31: 33.6 | O31: 28 | P31: =((B31-M31)*C31)+((E31-M31)*F31)+((H31-M31)*I31) -> 0
A32: UST T-Shirt Sports | B32: 430 | C32: 10 | D32: =B32*C32 -> 4300 | E32: 400 | G32: =E32*F32 -> 0 | H32: 350 | J32: =H32*I32 -> 0 | K32: =D32+G32+J32 -> 4300 | L32: =C32+F32+I32 -> 10 | M32: 260 | N32: 31.2 | O32: 26 | P32: =((B32-M32)*C32)+((E32-M32)*F32)+((H32-M32)*I32) -> 1700
A33: UST T-Shirt Tiger Pattern | B33: 450 | D33: =B33*C33 -> 0 | E33: 430 | G33: =E33*F33 -> 0 | H33: 400 | J33: =H33*I33 -> 0 | K33: =D33+G33+J33 -> 0 | L33: =C33+F33+I33 -> 0 | M33: 330 | N33: 39.6 | O33: 33 | P33: =((B33-M33)*C33)+((E33-M33)*F33)+((H33-M33)*I33) -> 0
A34: UST Happy Tiger | B34: 450 | D34: =B34*C34 -> 0 | E34: 400 | G34: =E34*F34 -> 0 | H34: 375 | J34: =H34*I34 -> 0 | K34: =D34+G34+J34 -> 0 | L34: =C34+F34+I34 -> 0 | M34: 280 | N34: 33.6 | O34: 28 | P34: =((B34-M34)*C34)+((E34-M34)*F34)+((H34-M34)*I34) -> 0
A35: OAT Tote Bag (Phased Out) | B35: 220 | D35: =B35*C35 -> 0 | G35: =E35*F35 -> 0 | J35: =H35*I35 -> 0 | K35: =D35+G35+J35 -> 0 | L35: =C35+F35+I35 -> 0 | M35: 120 | P35: =((B35-M35)*C35)+((E35-M35)*F35)+((H35-M35)*I35) -> 0
C36: TOTAL | D36: =SUM(D29:D35) -> 4300 | F36: TOTAL | G36: =SUM(G29:G35) -> 0 | I36: TOTAL | J36: =SUM(J29:J35) -> 0 | K36: =D36+G36+J36 -> 4300 | M36: TOTAL | P36: =SUM(P29:P35) -> 1700
A37: USTORE | B37: RETAIL PRICE | C37: PCS SOLD | D37: SALES | E37: DISCOUNTED PRICE | F37: PCS SOLD | G37: SALES | H37: SPECIAL DISC. PRICE | I37: PCS SOLD | J37: SALES | K37: TOTAL SALES | L37: TOTALQTY SOLD | M37: PRODUCTION PRICE | N37: 12% Vat | O37: 10% Mark Up | P37: PROFIT
A38: Auto Umbrella | B38: 250 | D38: =B38*C38 -> 0 | G38: =E38*F38 -> 0 | J38: =H38*I38 -> 0 | K38: =D38+G38+J38 -> 0 | L38: =C38+F38+I38 -> 0 | P38: =((B38-M38)*C38)+((E38-M38)*F38)+((H38-M38)*I38) -> 0
A39: Bag | B39: 250 | D39: =B39*C39 -> 0 | G39: =E39*F39 -> 0 | J39: =H39*I39 -> 0 | K39: =D39+G39+J39 -> 0 | L39: =C39+F39+I39 -> 0 | P39: =((B39-M39)*C39)+((E39-M39)*F39)+((H39-M39)*I39) -> 0
A40: Eco Bag CGEEE! | B40: 50 | D40: =B40*C40 -> 0 | E40: 35 | G40: =E40*F40 -> 0 | J40: =H40*I40 -> 0 | K40: =D40+G40+J40 -> 0 | L40: =C40+F40+I40 -> 0 | P40: =((B40-M40)*C40)+((E40-M40)*F40)+((H40-M40)*I40) -> 0
A41: Keychain | B41: 150 | C41: 3 | D41: =B41*C41 -> 450 | E41: 120 | G41: =E41*F41 -> 0 | H41: 75 | J41: =H41*I41 -> 0 | K41: =D41+G41+J41 -> 450 | L41: =C41+F41+I41 -> 3 | P41: =((B41-M41)*C41)+((E41-M41)*F41)+((H41-M41)*I41) -> 450
A42: Kit Set | B42: 800 | D42: =B42*C42 -> 0 | E42: 750 | G42: =E42*F42 -> 0 | H42: 700 | J42: =H42*I42 -> 0 | K42: =D42+G42+J42 -> 0 | L42: =C42+F42+I42 -> 0 | P42: =((B42-M42)*C42)+((E42-M42)*F42)+((H42-M42)*I42) -> 0
A43: Lanyard | B43: 190 | D43: =B43*C43 -> 0 | E43: 175 | G43: =E43*F43 -> 0 | H43: 150 | J43: =H43*I43 -> 0 | K43: =D43+G43+J43 -> 0 | L43: =C43+F43+I43 -> 0 | M43: 117 | N43: 14.04 | O43: 11.7 | P43: =((B43-M43)*C43)+((E43-M43)*F43)+((H43-M43)*I43) -> 0
A44: Lanyard | B44: 180 | D44: =B44*C44 -> 0 | E44: 165 | G44: =E44*F44 -> 0 | H44: 140 | J44: =H44*I44 -> 0 | K44: =D44+G44+J44 -> 0 | L44: =C44+F44+I44 -> 0 | M44: 110 | N44: 13.2 | O44: 11 | P44: =((B44-M44)*C44)+((E44-M44)*F44)+((H44-M44)*I44) -> 0
A45: NB | B45: 75 | D45: =B45*C45 -> 0 | G45: =E45*F45 -> 0 | J45: =H45*I45 -> 0 | K45: =D45+G45+J45 -> 0 | L45: =C45+F45+I45 -> 0 | P45: =((B45-M45)*C45)+((E45-M45)*F45)+((H45-M45)*I45) -> 0
A46: NB | B46: 100 | C46: 1 | D46: =B46*C46 -> 100 | E46: 80 | G46: =E46*F46 -> 0 | H46: 70 | J46: =H46*I46 -> 0 | K46: =D46+G46+J46 -> 100 | L46: =C46+F46+I46 -> 1 | P46: =((B46-M46)*C46)+((E46-M46)*F46)+((H46-M46)*I46) -> 100
A47: Sash Big | B47: 600 | D47: =B47*C47 -> 0 | E47: 500 | G47: =E47*F47 -> 0 | H47: 400 | J47: =H47*I47 -> 0 | K47: =D47+G47+J47 -> 0 | L47: =C47+F47+I47 -> 0 | P47: =((B47-M47)*C47)+((E47-M47)*F47)+((H47-M47)*I47) -> 0
A48: Sash Small | B48: 150 | C48: 1 | D48: =B48*C48 -> 150 | E48: 125 | G48: =E48*F48 -> 0 | H48: 100 | J48: =H48*I48 -> 0 | K48: =D48+G48+J48 -> 150 | L48: =C48+F48+I48 -> 1 | P48: =((B48-M48)*C48)+((E48-M48)*F48)+((H48-M48)*I48) -> 150
A49: Shabby Hat | B49: 200 | C49: 4 | D49: =B49*C49 -> 800 | E49: 175 | G49: =E49*F49 -> 0 | H49: 150 | J49: =H49*I49 -> 0 | K49: =D49+G49+J49 -> 800 | L49: =C49+F49+I49 -> 4 | P49: =((B49-M49)*C49)+((E49-M49)*F49)+((H49-M49)*I49) -> 800
A50: Tiger Stuff Toy Small Grad | B50: 250 | C50: 26 | D50: =B50*C50 -> 6500 | E50: 230 | G50: =E50*F50 -> 0 | H50: 200 | J50: =H50*I50 -> 0 | K50: =D50+G50+J50 -> 6500 | L50: =C50+F50+I50 -> 26 | P50: =((B50-M50)*C50)+((E50-M50)*F50)+((H50-M50)*I50) -> 6500
A51: Tote Bag CGEEE! | B51: 120 | D51: =B51*C51 -> 0 | E51: 100 | G51: =E51*F51 -> 0 | H51: 80 | J51: =H51*I51 -> 0 | K51: =D51+G51+J51 -> 0 | L51: =C51+F51+I51 -> 0 | P51: =((B51-M51)*C51)+((E51-M51)*F51)+((H51-M51)*I51) -> 0
A52: Tote Bag Canvas White | B52: 160 | C52: 8 | D52: =B52*C52 -> 1280 | G52: =E52*F52 -> 0 | J52: =H52*I52 -> 0 | K52: =D52+G52+J52 -> 1280 | L52: =C52+F52+I52 -> 8 | P52: =((B52-M52)*C52)+((E52-M52)*F52)+((H52-M52)*I52) -> 1280
A53: Tote (One For UST) | B53: 300 | C53: 2 | D53: =B53*C53 -> 600 | E53: 275 | G53: =E53*F53 -> 0 | H53: 250 | J53: =H53*I53 -> 0 | K53: =D53+G53+J53 -> 600 | L53: =C53+F53+I53 -> 2 | P53: =((B53-M53)*C53)+((E53-M53)*F53)+((H53-M53)*I53) -> 600
A54: Tumbler | B54: 150 | C54: 4 | D54: =B54*C54 -> 600 | G54: =E54*F54 -> 0 | J54: =H54*I54 -> 0 | K54: =D54+G54+J54 -> 600 | L54: =C54+F54+I54 -> 4 | P54: =((B54-M54)*C54)+((E54-M54)*F54)+((H54-M54)*I54) -> 600
A55: Umb. Cane | B55: 500 | D55: =B55*C55 -> 0 | E55: 450 | G55: =E55*F55 -> 0 | H55: 400 | J55: =H55*I55 -> 0 | K55: =D55+G55+J55 -> 0 | L55: =C55+F55+I55 -> 0 | P55: =((B55-M55)*C55)+((E55-M55)*F55)+((H55-M55)*I55) -> 0
A56: Umb (One For UST) | B56: 350 | C56: 16 | D56: =B56*C56 -> 5600 | E56: 300 | G56: =E56*F56 -> 0 | H56: 250 | J56: =H56*I56 -> 0 | K56: =D56+G56+J56 -> 5600 | L56: =C56+F56+I56 -> 16 | P56: =((B56-M56)*C56)+((E56-M56)*F56)+((H56-M56)*I56) -> 5600
A57: Utensil | B57: 250 | D57: =B57*C57 -> 0 | E57: 200 | G57: =E57*F57 -> 0 | H57: 180 | J57: =H57*I57 -> 0 | K57: =D57+G57+J57 -> 0 | L57: =C57+F57+I57 -> 0
C58: TOTAL | D58: =SUM(D38:D57) -> 16080 | F58: TOTAL | G58: =SUM(G38:G57) -> 0 | I58: TOTAL | J58: =SUM(J38:J57) -> 0 | K58: =D58+G58+J58 -> 16080 | M58: TOTAL | P58: =SUM(P38:P57) -> 16080
A59: TET AND DARS | B59: RETAIL PRICE | C59: PCS SOLD | D59: SALES | E59: DISCOUNTED PRICE | F59: PCS SOLD | G59: SALES | H59: SPECIAL DISC. PRICE | I59: PCS SOLD | J59: SALES | K59: TOTAL SALES | L59: TOTALQTY SOLD | M59: PRODUCTION PRICE | N59: 12% Vat | O59: 10% Mark Up | P59: PROFIT
A60: Arch | B60: 320 | D60: =B60*C60 -> 0 | E60: 300 | G60: =E60*F60 -> 0 | H60: 300 | J60: =H60*I60 -> 0 | K60: =D60+G60+J60 -> 0 | L60: =C60+F60+I60 -> 0 | M60: 240 | N60: 28.8 | O60: 24 | P60: =((B60-M60)*C60)+((E60-M60)*F60)+((H60-M60)*I60) -> 0
A61: Eco Bag | B61: 80 | D61: =B61*C61 -> 0 | E61: 70 | G61: =E61*F61 -> 0 | H61: 60 | J61: =H61*I61 -> 0 | K61: =D61+G61+J61 -> 0 | L61: =C61+F61+I61 -> 0 | M61: 60 | P61: =((B61-M61)*C61)+((E61-M61)*F61)+((H61-M61)*I61) -> 0
A62: Eco Bag | B62: 130 | D62: =B62*C62 -> 0 | E62: 120 | G62: =E62*F62 -> 0 | H62: 110 | J62: =H62*I62 -> 0 | K62: =D62+G62+J62 -> 0 | L62: =C62+F62+I62 -> 0 | M62: 100 | P62: =((B62-M62)*C62)+((E62-M62)*F62)+((H62-M62)*I62) -> 0
A63: Main Building | B63: 430 | C63: 1 | D63: =B63*C63 -> 430 | E63: 430 | G63: =E63*F63 -> 0 | H63: 430 | J63: =H63*I63 -> 0 | K63: =D63+G63+J63 -> 430 | L63: =C63+F63+I63 -> 1 | M63: 350 | N63: 42 | O63: 35 | P63: =((B63-M63)*C63)+((E63-M63)*F63)+((H63-M63)*I63) -> 80
A64: Mug | B64: 170 | C64: 1 | D64: =B64*C64 -> 170 | E64: 160 | G64: =E64*F64 -> 0 | H64: 150 | J64: =H64*I64 -> 0 | K64: =D64+G64+J64 -> 170 | L64: =C64+F64+I64 -> 1 | M64: 125 | N64: 15 | O64: 12.5 | P64: =((B64-M64)*C64)+((E64-M64)*F64)+((H64-M64)*I64) -> 45
A65: Notebook | B65: 220 | D65: =B65*C65 -> 0 | G65: =E65*F65 -> 0 | J65: =H65*I65 -> 0 | K65: =D65+G65+J65 -> 0 | L65: =C65+F65+I65 -> 0 | P65: =((B65-M65)*C65)+((E65-M65)*F65)+((H65-M65)*I65) -> 0
A66: Pen | B66: 50 | D66: =B66*C66 -> 0 | G66: =E66*F66 -> 0 | J66: =H66*I66 -> 0 | K66: =D66+G66+J66 -> 0 | L66: =C66+F66+I66 -> 0 | M66: 42 | P66: =((B66-M66)*C66)+((E66-M66)*F66)+((H66-M66)*I66) -> 0
A67: Pen | B67: 25 | D67: =B67*C67 -> 0 | G67: =E67*F67 -> 0 | J67: =H67*I67 -> 0 | K67: =D67+G67+J67 -> 0 | L67: =C67+F67+I67 -> 0 | M67: 20 | P67: =((B67-M67)*C67)+((E67-M67)*F67)+((H67-M67)*I67) -> 0
A68: Sticker | B68: 115 | C68: 3 | D68: =B68*C68 -> 345 | E68: 110 | G68: =E68*F68 -> 0 | H68: 105 | J68: =H68*I68 -> 0 | K68: =D68+G68+J68 -> 345 | L68: =C68+F68+I68 -> 3 | M68: 85 | P68: =((B68-M68)*C68)+((E68-M68)*F68)+((H68-M68)*I68) -> 90
A69: Sticker | B69: 20 | D69: =B69*C69 -> 0 | E69: 20 | G69: =E69*F69 -> 0 | H69: 20 | J69: =H69*I69 -> 0 | K69: =D69+G69+J69 -> 0 | L69: =C69+F69+I69 -> 0 | M69: 15 | P69: =((B69-M69)*C69)+((E69-M69)*F69)+((H69-M69)*I69) -> 0
A70: Tote | B70: 230 | D70: =B70*C70 -> 0 | G70: =E70*F70 -> 0 | J70: =H70*I70 -> 0 | K70: =D70+G70+J70 -> 0 | L70: =C70+F70+I70 -> 0 | P70: =((B70-M70)*C70)+((E70-M70)*F70)+((H70-M70)*I70) -> 0
C71: TOTAL | D71: =SUM(D60:D70) -> 945 | F71: TOTAL | G71: =SUM(G60:G70) -> 0 | I71: TOTAL | J71: =SUM(J60:J70) -> 0 | K71: =D71+G71+J71 -> 945 | M71: TOTAL | P71: =SUM(P60:P70) -> 215
A72: BLAZE | B72: RETAIL PRICE | C72: PCS SOLD | D72: SALES | E72: DISCOUNTED PRICE | F72: PCS SOLD | G72: SALES | H72: SPECIAL DISC. PRICE | I72: PCS SOLD | J72: SALES | K72: TOTAL SALES | L72: TOTALQTY SOLD | M72: PRODUCTION PRICE | N72: 12% Vat | O72: 10% Mark Up | P72: PROFIT
A73: Crew Neck Shirt | B73: 475 | D73: =B73*C73 -> 0 | E73: 450 | G73: =E73*F73 -> 0 | H73: 430 | J73: =H73*I73 -> 0 | K73: =D73+G73+J73 -> 0 | L73: =C73+F73+I73 -> 0 | M73: 350 | N73: 42 | O73: 35 | P73: =((B73-M73)*C73)+((E73-M73)*F73)+((H73-M73)*I73) -> 0
A74: Polo Shirt | B74: 800 | D74: =B74*C74 -> 0 | E74: 750 | F74: 2 | G74: =E74*F74 -> 1500 | H74: 700 | J74: =H74*I74 -> 0 | K74: =D74+G74+J74 -> 1500 | L74: =C74+F74+I74 -> 2 | M74: 550 | N74: 66 | O74: 55 | P74: =((B74-M74)*C74)+((E74-M74)*F74)+((H74-M74)*I74) -> 400
A75: Socks | B75: 375 | D75: =B75*C75 -> 0 | E75: 350 | G75: =E75*F75 -> 0 | H75: 325 | J75: =H75*I75 -> 0 | K75: =D75+G75+J75 -> 0 | L75: =C75+F75+I75 -> 0 | M75: 250 | N75: 30 | O75: 25 | P75: =((B75-M75)*C75)+((E75-M75)*F75)+((H75-M75)*I75) -> 0
A76: socks set of 3 | B76: 950 | D76: =B76*C76 -> 0 | E76: 900 | G76: =E76*F76 -> 0 | H76: 800 | J76: =H76*I76 -> 0 | K76: =D76+G76+J76 -> 0 | L76: =C76+F76+I76 -> 0 | M76: 750 | N76: 90 | O76: 75 | P76: =((B76-M76)*C76)+((E76-M76)*F76)+((H76-M76)*I76) -> 0
C77: TOTAL | D77: =SUM(D73:D76) -> 0 | F77: TOTAL | G77: =SUM(G73:G76) -> 1500 | I77: TOTAL | J77: =SUM(J73:J76) -> 0 | K77: =D77+G77+J77 -> 1500 | M77: TOTAL | P77: =SUM(P73:P76) -> 400
A78: VARSITY LIFE STYLE | B78: RETAIL PRICE | C78: PCS SOLD | D78: SALES | E78: DISCOUNTED PRICE | F78: PCS SOLD | G78: SALES | H78: SPECIAL DISC. PRICE | I78: PCS SOLD | J78: SALES | K78: TOTAL SALES | L78: TOTALQTY SOLD | M78: PRODUCTION PRICE | N78: 12% Vat | O78: 10% Mark Up | P78: PROFIT
A79: Baller | B79: 100 | D79: =B79*C79 -> 0 | K79: =D79+G79+J79 -> 0 | L79: =C79+F79+I79 -> 0 | M79: 90
A80: Caps | B80: 800 | D80: =B80*C80 -> 0 | K80: =D80+G80+J80 -> 0 | L80: =C80+F80+I80 -> 0 | M80: 700
A81: Hoodie | B81: 1750 | D81: =B81*C81 -> 0 | K81: =D81+G81+J81 -> 0 | L81: =C81+F81+I81 -> 0 | M81: 1500
A82: Keychain | B82: 100 | D82: =B82*C82 -> 0 | K82: =D82+G82+J82 -> 0 | L82: =C82+F82+I82 -> 0 | M82: 90
A83: Lanyard | B83: 250 | D83: =B83*C83 -> 0 | K83: =D83+G83+J83 -> 0 | L83: =C83+F83+I83 -> 0 | M83: 200
A84: Long Sticker | B84: 100 | D84: =B84*C84 -> 0 | K84: =D84+G84+J84 -> 0 | L84: =C84+F84+I84 -> 0 | M84: 90
A85: Oversized Sweatshirt | B85: 1500 | D85: =B85*C85 -> 0 | K85: =D85+G85+J85 -> 0 | L85: =C85+F85+I85 -> 0 | M85: 1300
A86: Scarves | B86: 400 | D86: =B86*C86 -> 0 | K86: =D86+G86+J86 -> 0 | L86: =C86+F86+I86 -> 0 | M86: 350
A87: Shirts | B87: 700 | D87: =B87*C87 -> 0 | K87: =D87+G87+J87 -> 0 | L87: =C87+F87+I87 -> 0 | M87: 600
A88: Sticker Pack | B88: 150 | D88: =B88*C88 -> 0 | K88: =D88+G88+J88 -> 0 | L88: =C88+F88+I88 -> 0 | M88: 130
A89: Varsity Jacket | B89: 2100 | D89: =B89*C89 -> 0 | K89: =D89+G89+J89 -> 0 | L89: =C89+F89+I89 -> 0 | M89: 1900
C90: TOTAL | D90: =SUM(D79:D89) -> 0 | F90: TOTAL | G90: =SUM(G79:G89) -> 0 | I90: TOTAL | J90: =SUM(J79:J89) -> 0 | K90: =D90+G90+J90 -> 0 | M90: TOTAL | P90: =SUM(P79:P89) -> 0
A91: MITSUI | B91: RETAIL PRICE | C91: PCS SOLD | D91: SALES | E91: DISCOUNTED PRICE | F91: PCS SOLD | G91: SALES | H91: SPECIAL DISC. PRICE | I91: PCS SOLD | J91: SALES | K91: TOTAL SALES | L91: TOTALQTY SOLD | M91: PRODUCTION PRICE | N91: 12% Vat | O91: 10% Mark Up | P91: PROFIT
A92: Stylus pen | B92: 45 | D92: =B92*C92 -> 0 | E92: 40 | G92: =E92*F92 -> 0 | H92: 25 | J92: =H92*I92 -> 0 | K92: =D92+G92+J92 -> 0 | L92: =C92+F92+I92 -> 0 | M92: 17.36 | N92: 2.08 | O92: 1.74 | P92: =((B92-M92)*C92)+((E92-M92)*F92)+((H92-M92)*I92) -> 0
A93: Retractable | B93: 25 | D93: =B93*C93 -> 0 | E93: 15 | G93: =E93*F93 -> 0 | H93: 20 | J93: =H93*I93 -> 0 | K93: =D93+G93+J93 -> 0 | L93: =C93+F93+I93 -> 0 | M93: 10.08 | N93: 1.21 | O93: 1.01 | P93: =((B93-M93)*C93)+((E93-M93)*F93)+((H93-M93)*I93) -> 0
C94: TOTAL | D94: =SUM(D92+D93) -> 0 | F94: TOTAL | G94: =SUM(G92+G93) -> 0 | I94: TOTAL | J94: =SUM(J92+J93) -> 0 | K94: =D94+G94+J94 -> 0 | M94: TOTAL | P94: =SUM(P92) -> 0
A95: CENTRAL SEMINARY | B95: RETAIL PRICE | C95: PCS SOLD | D95: SALES | E95: DISCOUNTED PRICE | F95: PCS SOLD | G95: SALES | H95: SPECIAL DISC. PRICE | I95: PCS SOLD | J95: SALES | K95: TOTAL SALES | L95: TOTALQTY SOLD | M95: PRODUCTION PRICE | N95: 12% Vat | O95: 10% Mark Up | P95: PROFIT
A96: Subli. Shirt | B96: 550 | C96: 4 | D96: =B96*C96 -> 2200 | G96: =E96*F96 -> 0 | J96: =H96*I96 -> 0 | K96: =D96+G96+J96 -> 2200 | L96: =C96+F96+I96 -> 4 | M96: 500 | P96: =((B96-M96)*C96)+((E96-M96)*F96)+((H96-M96)*I96) -> 200
C97: GRAND TOTAL | D97: =D17+D27+D36+D58+D71+D77+D94+D96+D90 -> 30795 | F97: GRAND TOTAL | G97: =G17+G27+G36+G58+G71+G77+G94+G96+G90 -> 1500 | I97: GRAND TOTAL | J97: =J17+J27+J36+J58+J71+J77+J94+J96 -> 7900 | K97: =D97+G97+J97 -> 40195 | M97: GRAND TOTAL | P97: =P17+P27+P36+P58+P71+P77+P94+P96 -> 21945
C98: TOTAL SALE | E98: =K97 -> 40195 | N98: TOTAL PROFIT | P98: =P97 -> 21945
B99: CASH BREAKDOWN
B100: BILLS | D100: PCS | G100: AMOUNT | M100: REFERENCE NUMBER | O100: AMOUNT
...

Sheet May 4
A1: DAILY SALES REPORT
A2: 45415
A3: ITEMS | B3: RETAIL PRICE | C3: PCS SOLD | D3: SALES | E3: DISCOUNTED PRICE | F3: PCS SOLD | G3: SALES | H3: SPECIAL DISC. PRICE | I3: PCS SOLD | J3: SALES | K3: TOTAL SALES | L3: TOTALQTY SOLD | M3: PRODUCTION PRICE | N3: 12% Vat | O3: 10% Mark Up | P3: PROFIT
A4: NAPOLIZ
A5: Backpack Bag | B5: 1750 | D5: =B5*C5 -> 0 | E5: 1600 | G5: =E5*F5 -> 0 | H5: 1400 | J5: =H5*I5 -> 0 | K5: =D5+G5+J5 -> 0 | L5: =C5+F5+I5 -> 0 | M5: 840 | N5: 100.8 | O5: 84 | P5: =((B5-M5)*C5)+((E5-M5)*F5)+((H5-M5)*I5) -> 0
A6: Black Tote Bag (Phased Out) | B6: 280 | D6: =B6*C6 -> 0 | G6: =E6*F6 -> 0 | J6: =H6*I6 -> 0 | K6: =D6+G6+J6 -> 0 | L6: =C6+F6+I6 -> 0 | M6: 230 | P6: =((B6-M6)*C6)+((E6-M6)*F6)+((H6-M6)*I6) -> 0
A7: Double Canopy | B7: 639 | D7: =B7*C7 -> 0 | E7: 575 | G7: =E7*F7 -> 0 | H7: 500 | J7: =H7*I7 -> 0 | K7: =D7+G7+J7 -> 0 | L7: =C7+F7+I7 -> 0 | M7: 330 | N7: 39.6 | O7: 33 | P7: =((B7-M7)*C7)+((E7-M7)*F7)+((H7-M7)*I7) -> 0
A8: Laptop Bag | B8: 1450 | D8: =B8*C8 -> 0 | E8: 1400 | G8: =E8*F8 -> 0 | H8: 1250 | J8: =H8*I8 -> 0 | K8: =D8+G8+J8 -> 0 | L8: =C8+F8+I8 -> 0 | M8: 840 | N8: 100.8 | O8: 84 | P8: =((B8-M8)*C8)+((E8-M8)*F8)+((H8-M8)*I8) -> 0
A9: Script Santo Tomas with Tiger Back (B) | B9: 480 | C9: 4 | D9: =B9*C9 -> 1920 | E9: 460 | G9: =E9*F9 -> 0 | H9: 450 | J9: =H9*I9 -> 0 | K9: =D9+G9+J9 -> 1920 | L9: =C9+F9+I9 -> 4 | M9: 360 | N9: 43.2 | O9: 36 | P9: =((B9-M9)*C9)+((E9-M9)*F9)+((H9-M9)*I9) -> 480
A10: Side Tiger Hoodie | B10: 1480 | D10: =B10*C10 -> 0 | E10: 1400 | G10: =E10*F10 -> 0 | H10: 1375 | J10: =H10*I10 -> 0 | K10: =D10+G10+J10 -> 0 | L10: =C10+F10+I10 -> 0 | M10: 1125 | N10: 135 | O10: 112.5 | P10: =((B10-M10)*C10)+((E10-M10)*F10)+((H10-M10)*I10) -> 0
A11: Sling Bag | B11: 330 | D11: =B11*C11 -> 0 | E11: 320 | G11: =E11*F11 -> 0 | H11: 300 | J11: =H11*I11 -> 0 | K11: =D11+G11+J11 -> 0 | L11: =C11+F11+I11 -> 0 | M11: 260 | N11: 31.2 | O11: 26 | P11: =((B11-M11)*C11)+((E11-M11)*F11)+((H11-M11)*I11) -> 0
A12: Front Tiger Hoodie | B12: 1440 | C12: 1 | D12: =B12*C12 -> 1440 | E12: 1400 | G12: =E12*F12 -> 0 | H12: 1375 | J12: =H12*I12 -> 0 | K12: =D12+G12+J12 -> 1440 | L12: =C12+F12+I12 -> 1 | M12: 1125 | N12: 135 | O12: 112.5 | P12: =((B12-M12)*C12)+((E12-M12)*F12)+((H12-M12)*I12) -> 315
A13: University of Santo Tomas (B) | B13: 450 | D13: =B13*C13 -> 0 | E13: 440 | G13: =E13*F13 -> 0 | H13: 425 | J13: =H13*I13 -> 0 | K13: =D13+G13+J13 -> 0 | L13: =C13+F13+I13 -> 0 | M13: 360 | N13: 43.2 | O13: 36 | P13: =((B13-M13)*C13)+((E13-M13)*F13)+((H13-M13)*I13) -> 0
A14: UST Tiger Front and Back Graphic (W) | B14: 500 | C14: 1 | D14: =B14*C14 -> 500 | E14: 480 | G14: =E14*F14 -> 0 | H14: 450 | J14: =H14*I14 -> 0 | K14: =D14+G14+J14 -> 500 | L14: =C14+F14+I14 -> 1 | M14: 360 | N14: 43.2 | O14: 36 | P14: =((B14-M14)*C14)+((E14-M14)*F14)+((H14-M14)*I14) -> 140
A15: White Tote Bag | B15: 260 | D15: =B15*C15 -> 0 | E15: 250 | G15: =E15*F15 -> 0 | H15: 240 | J15: =H15*I15 -> 0 | K15: =D15+G15+J15 -> 0 | L15: =C15+F15+I15 -> 0 | M15: 200 | N15: 24 | O15: 20 | P15: =((B15-M15)*C15)+((E15-M15)*F15)+((H15-M15)*I15) -> 0
A16: Wind Breaker | B16: 1650 | C16: 1 | D16: =B16*C16 -> 1650 | E16: 1600 | G16: =E16*F16 -> 0 | H16: 1500 | J16: =H16*I16 -> 0 | K16: =D16+G16+J16 -> 1650 | L16: =C16+F16+I16 -> 1 | M16: 1125 | N16: 135 | O16: 112.5 | P16: =((B16-M16)*C16)+((E16-M16)*F16)+((H16-M16)*I16) -> 525
C17: TOTAL | D17: =SUM(D5:D16) -> 5510 | F17: TOTAL | G17: =SUM(G5:G16) -> 0 | I17: TOTAL | J17: =SUM(J5:J16) -> 0 | K17: =D17+G17+J17 -> 5510 | M17: TOTAL | P17: =SUM(P5:P16) -> 1460
A18: JYL | B18: RETAIL PRICE | C18: PCS SOLD | D18: SALES | E18: DISCOUNTED PRICE | F18: PCS SOLD | G18: SALES | H18: SPECIAL DISC. PRICE | I18: PCS SOLD | J18: SALES | K18: TOTAL SALES | L18: TOTALQTY SOLD | M18: PRODUCTION PRICE | N18: 12% Vat | O18: 10% Mark Up | P18: PROFIT
A19: GT Shirt | B19: 375 | D19: =B19*C19 -> 0 | E19: 350 | G19: =E19*F19 -> 0 | H19: 325 | J19: =H19*I19 -> 0 | K19: =D19+G19+J19 -> 0 | L19: =C19+F19+I19 -> 0 | M19: 250 | N19: 30 | O19: 25 | P19: =((B19-M19)*C19)+((E19-M19)*F19)+((H19-M19)*I19) -> 0
A20: Jacket | B20: 1900 | D20: =B20*C20 -> 0 | E20: 1700 | G20: =E20*F20 -> 0 | H20: 1500 | J20: =H20*I20 -> 0 | K20: =D20+G20+J20 -> 0 | L20: =C20+F20+I20 -> 0 | M20: 1200 | N20: 144 | O20: 120 | P20: =((B20-M20)*C20)+((E20-M20)*F20)+((H20-M20)*I20) -> 0
A21: Poloshirt 123456 | B21: 860 | D21: =B21*C21 -> 0 | E21: 800 | G21: =E21*F21 -> 0 | H21: 750 | J21: =H21*I21 -> 0 | K21: =D21+G21+J21 -> 0 | L21: =C21+F21+I21 -> 0 | M21: 600 | N21: 72 | O21: 60 | P21: =((B21-M21)*C21)+((E21-M21)*F21)+((H21-M21)*I21) -> 0
A22: VB Jersey w/ sig. (Phased Out) | B22: 2800 | D22: =B22*C22 -> 0 | G22: =E22*F22 -> 0 | J22: =H22*I22 -> 0 | K22: =D22+G22+J22 -> 0 | L22: =C22+F22+I22 -> 0 | M22: 800 | N22: 96 | O22: 80 | P22: =((B22-M22)*C22)+((E22-M22)*F22)+((H22-M22)*I22) -> 0
A23: VB Jersey w/o sig. | B23: 2000 | D23: =B23*C23 -> 0 | E23: 1800 | G23: =E23*F23 -> 0 | H23: 1500 | J23: =H23*I23 -> 0 | K23: =D23+G23+J23 -> 0 | L23: =C23+F23+I23 -> 0 | M23: 800 | P23: =((B23-M23)*C23)+((E23-M23)*F23)+((H23-M23)*I23) -> 0
A24: VB Jersey w/o sig. | B24: 1500 | D24: =B24*C24 -> 0 | E24: 1400 | G24: =E24*F24 -> 0 | H24: 1300 | J24: =H24*I24 -> 0 | K24: =D24+G24+J24 -> 0 | L24: =C24+F24+I24 -> 0 | M24: 800 | P24: =((B24-M24)*C24)+((E24-M24)*F24)+((H24-M24)*I24) -> 0
A25: VB Jersey w/o sig. | B25: 1000 | D25: =B25*C25 -> 0 | E25: 980 | G25: =E25*F25 -> 0 | H25: 950 | J25: =H25*I25 -> 0 | K25: =D25+G25+J25 -> 0 | L25: =C25+F25+I25 -> 0 | M25: 800 | P25: =((B25-M25)*C25)+((E25-M25)*F25)+((H25-M25)*I25) -> 0
A26: VB Jersey with sig. (Phased Out) | B26: 1500 | D26: =B26*C26 -> 0 | G26: =E26*F26 -> 0 | J26: =H26*I26 -> 0 | K26: =D26+G26+J26 -> 0 | L26: =C26+F26+I26 -> 0 | M26: 800 | P26: =((B26-M26)*C26)+((E26-M26)*F26)+((H26-M26)*I26) -> 0
C27: TOTAL | D27: =SUM(D19:D26) -> 0 | F27: TOTAL | G27: =SUM(G19:G26) -> 0 | I27: TOTAL | J27: =SUM(J19:J26) -> 0 | K27: =D27+G27+J27 -> 0 | M27: TOTAL | P27: =SUM(P19:P26) -> 0
A28: JUC | B28: RETAIL PRICE | C28: PCS SOLD | D28: SALES | E28: DISCOUNTED PRICE | F28: PCS SOLD | G28: SALES | H28: SPECIAL DISC. PRICE | I28: PCS SOLD | J28: SALES | K28: TOTAL SALES | L28: TOTALQTY SOLD | M28: PRODUCTION PRICE | N28: 12% Vat | O28: 10% Mark Up | P28: PROFIT
A29: UST OAT Hoodie Jacket | B29: 1450 | C29: 2 | D29: =B29*C29 -> 2900 | E29: 1400 | G29: =E29*F29 -> 0 | H29: 1300 | J29: =H29*I29 -> 0 | K29: =D29+G29+J29 -> 2900 | L29: =C29+F29+I29 -> 2 | M29: 1000 | N29: 120 | O29: 100 | P29: =((B29-M29)*C29)+((E29-M29)*F29)+((H29-M29)*I29) -> 900
A30: UST OAT MUG | B30: 150 | D30: =B30*C30 -> 0 | E30: 140 | G30: =E30*F30 -> 0 | H30: 135 | J30: =H30*I30 -> 0 | K30: =D30+G30+J30 -> 0 | L30: =C30+F30+I30 -> 0 | M30: 110 | N30: 12 | O30: 10 | P30: =((B30-M30)*C30)+((E30-M30)*F30)+((H30-M30)*I30) -> 0
A31: UST OAT MUG (WE) Inside | B31: 150 | D31: =B31*C31 -> 0 | E31: 140 | G31: =E31*F31 -> 0 | H31: 135 | J31: =H31*I31 -> 0 | K31: =D31+G31+J31 -> 0 | L31: =C31+F31+I31 -> 0 | M31: 100 | N31: 12 | O31: 10 | P31: =((B31-M31)*C31)+((E31-M31)*F31)+((H31-M31)*I31) -> 0
A32: UST OAT T-Shirt | B32: 375 | D32: =B32*C32 -> 0 | E32: 360 | G32: =E32*F32 -> 0 | H32: 340 | J32: =H32*I32 -> 0 | K32: =D32+G32+J32 -> 0 | L32: =C32+F32+I32 -> 0 | M32: 280 | N32: 33.6 | O32: 28 | P32: =((B32-M32)*C32)+((E32-M32)*F32)+((H32-M32)*I32) -> 0
A33: UST T-Shirt Sports | B33: 430 | C33: 3 | D33: =B33*C33 -> 1290 | E33: 400 | G33: =E33*F33 -> 0 | H33: 350 | J33: =H33*I33 -> 0 | K33: =D33+G33+J33 -> 1290 | L33: =C33+F33+I33 -> 3 | M33: 260 | N33: 31.2 | O33: 26 | P33: =((B33-M33)*C33)+((E33-M33)*F33)+((H33-M33)*I33) -> 510
A34: UST T-Shirt Tiger Pattern | B34: 450 | C34: 1 | D34: =B34*C34 -> 450 | E34: 430 | G34: =E34*F34 -> 0 | H34: 400 | J34: =H34*I34 -> 0 | K34: =D34+G34+J34 -> 450 | L34: =C34+F34+I34 -> 1 | M34: 330 | N34: 39.6 | O34: 33 | P34: =((B34-M34)*C34)+((E34-M34)*F34)+((H34-M34)*I34) -> 120
A35: UST Happy Tiger | B35: 450 | C35: 4 | D35: =B35*C35 -> 1800 | E35: 400 | F35: 2 | G35: =E35*F35 -> 800 | H35: 375 | J35: =H35*I35 -> 0 | K35: =D35+G35+J35 -> 2600 | L35: =C35+F35+I35 -> 6 | M35: 280 | N35: 33.6 | O35: 28 | P35: =((B35-M35)*C35)+((E35-M35)*F35)+((H35-M35)*I35) -> 920
A36: OAT Tote Bag (Phased Out) | B36: 220 | D36: =B36*C36 -> 0 | G36: =E36*F36 -> 0 | J36: =H36*I36 -> 0 | K36: =D36+G36+J36 -> 0 | L36: =C36+F36+I36 -> 0 | M36: 120 | P36: =((B36-M36)*C36)+((E36-M36)*F36)+((H36-M36)*I36) -> 0
C37: TOTAL | D37: =SUM(D29:D36) -> 6440 | F37: TOTAL | G37: =SUM(G29:G36) -> 800 | I37: TOTAL | J37: =SUM(J29:J36) -> 0 | K37: =D37+G37+J37 -> 7240 | M37: TOTAL | P37: =SUM(P29:P36) -> 2450
A38: USTORE | B38: RETAIL PRICE | C38: PCS SOLD | D38: SALES | E38: DISCOUNTED PRICE | F38: PCS SOLD | G38: SALES | H38: SPECIAL DISC. PRICE | I38: PCS SOLD | J38: SALES | K38: TOTAL SALES | L38: TOTALQTY SOLD | M38: PRODUCTION PRICE | N38: 12% Vat | O38: 10% Mark Up | P38: PROFIT
A39: Auto Umbrella | B39: 250 | D39: =B39*C39 -> 0 | G39: =E39*F39 -> 0 | J39: =H39*I39 -> 0 | K39: =D39+G39+J39 -> 0 | L39: =C39+F39+I39 -> 0 | P39: =((B39-M39)*C39)+((E39-M39)*F39)+((H39-M39)*I39) -> 0
A40: Bag | B40: 250 | D40: =B40*C40 -> 0 | G40: =E40*F40 -> 0 | J40: =H40*I40 -> 0 | K40: =D40+G40+J40 -> 0 | L40: =C40+F40+I40 -> 0 | P40: =((B40-M40)*C40)+((E40-M40)*F40)+((H40-M40)*I40) -> 0
A41: Eco Bag CGEEE! | B41: 50 | D41: =B41*C41 -> 0 | E41: 35 | G41: =E41*F41 -> 0 | J41: =H41*I41 -> 0 | K41: =D41+G41+J41 -> 0 | L41: =C41+F41+I41 -> 0 | P41: =((B41-M41)*C41)+((E41-M41)*F41)+((H41-M41)*I41) -> 0
A42: Keychain | B42: 150 | C42: 1 | D42: =B42*C42 -> 150 | E42: 120 | G42: =E42*F42 -> 0 | H42: 75 | J42: =H42*I42 -> 0 | K42: =D42+G42+J42 -> 150 | L42: =C42+F42+I42 -> 1 | P42: =((B42-M42)*C42)+((E42-M42)*F42)+((H42-M42)*I42) -> 150
A43: Kit Set | B43: 800 | D43: =B43*C43 -> 0 | E43: 750 | G43: =E43*F43 -> 0 | H43: 700 | J43: =H43*I43 -> 0 | K43: =D43+G43+J43 -> 0 | L43: =C43+F43+I43 -> 0 | P43: =((B43-M43)*C43)+((E43-M43)*F43)+((H43-M43)*I43) -> 0
A44: Lanyard | B44: 190 | C44: 1 | D44: =B44*C44 -> 190 | E44: 175 | G44: =E44*F44 -> 0 | H44: 150 | J44: =H44*I44 -> 0 | K44: =D44+G44+J44 -> 190 | L44: =C44+F44+I44 -> 1 | M44: 117 | N44: 14.04 | O44: 11.7 | P44: =((B44-M44)*C44)+((E44-M44)*F44)+((H44-M44)*I44) -> 73
A45: Lanyard | B45: 180 | D45: =B45*C45 -> 0 | E45: 165 | G45: =E45*F45 -> 0 | H45: 140 | J45: =H45*I45 -> 0 | K45: =D45+G45+J45 -> 0 | L45: =C45+F45+I45 -> 0 | M45: 110 | N45: 13.2 | O45: 11 | P45: =((B45-M45)*C45)+((E45-M45)*F45)+((H45-M45)*I45) -> 0
A46: NB | B46: 75 | D46: =B46*C46 -> 0 | G46: =E46*F46 -> 0 | J46: =H46*I46 -> 0 | K46: =D46+G46+J46 -> 0 | L46: =C46+F46+I46 -> 0 | P46: =((B46-M46)*C46)+((E46-M46)*F46)+((H46-M46)*I46) -> 0
A47: NB | B47: 100 | D47: =B47*C47 -> 0 | E47: 80 | G47: =E47*F47 -> 0 | H47: 70 | J47: =H47*I47 -> 0 | K47: =D47+G47+J47 -> 0 | L47: =C47+F47+I47 -> 0 | P47: =((B47-M47)*C47)+((E47-M47)*F47)+((H47-M47)*I47) -> 0
A48: Sash Big | B48: 600 | C48: 2 | D48: =B48*C48 -> 1200 | E48: 500 | G48: =E48*F48 -> 0 | H48: 400 | J48: =H48*I48 -> 0 | K48: =D48+G48+J48 -> 1200 | L48: =C48+F48+I48 -> 2 | P48: =((B48-M48)*C48)+((E48-M48)*F48)+((H48-M48)*I48) -> 1200
A49: Sash Small | B49: 150 | C49: 2 | D49: =B49*C49 -> 300 | E49: 125 | G49: =E49*F49 -> 0 | H49: 100 | J49: =H49*I49 -> 0 | K49: =D49+G49+J49 -> 300 | L49: =C49+F49+I49 -> 2 | P49: =((B49-M49)*C49)+((E49-M49)*F49)+((H49-M49)*I49) -> 300
A50: Shabby Hat | B50: 200 | D50: =B50*C50 -> 0 | E50: 175 | G50: =E50*F50 -> 0 | H50: 150 | J50: =H50*I50 -> 0 | K50: =D50+G50+J50 -> 0 | L50: =C50+F50+I50 -> 0 | P50: =((B50-M50)*C50)+((E50-M50)*F50)+((H50-M50)*I50) -> 0
A51: Tiger Stuff Toy Small Grad | B51: 250 | C51: 4 | D51: =B51*C51 -> 1000 | E51: 230 | G51: =E51*F51 -> 0 | H51: 200 | J51: =H51*I51 -> 0 | K51: =D51+G51+J51 -> 1000 | L51: =C51+F51+I51 -> 4 | P51: =((B51-M51)*C51)+((E51-M51)*F51)+((H51-M51)*I51) -> 1000
A52: Tote Bag CGEEE! | B52: 120 | D52: =B52*C52 -> 0 | E52: 100 | G52: =E52*F52 -> 0 | H52: 80 | J52: =H52*I52 -> 0 | K52: =D52+G52+J52 -> 0 | L52: =C52+F52+I52 -> 0 | P52: =((B52-M52)*C52)+((E52-M52)*F52)+((H52-M52)*I52) -> 0
A53: Tote Bag Canvas White | B53: 160 | C53: 1 | D53: =B53*C53 -> 160 | G53: =E53*F53 -> 0 | J53: =H53*I53 -> 0 | K53: =D53+G53+J53 -> 160 | L53: =C53+F53+I53 -> 1 | P53: =((B53-M53)*C53)+((E53-M53)*F53)+((H53-M53)*I53) -> 160
A54: Tote (One For UST) | B54: 300 | C54: 1 | D54: =B54*C54 -> 300 | E54: 275 | G54: =E54*F54 -> 0 | H54: 250 | J54: =H54*I54 -> 0 | K54: =D54+G54+J54 -> 300 | L54: =C54+F54+I54 -> 1 | P54: =((B54-M54)*C54)+((E54-M54)*F54)+((H54-M54)*I54) -> 300
A55: Tumbler | B55: 150 | C55: 2 | D55: =B55*C55 -> 300 | G55: =E55*F55 -> 0 | J55: =H55*I55 -> 0 | K55: =D55+G55+J55 -> 300 | L55: =C55+F55+I55 -> 2 | P55: =((B55-M55)*C55)+((E55-M55)*F55)+((H55-M55)*I55) -> 300
A56: Umb. Cane | B56: 500 | D56: =B56*C56 -> 0 | E56: 450 | G56: =E56*F56 -> 0 | H56: 400 | J56: =H56*I56 -> 0 | K56: =D56+G56+J56 -> 0 | L56: =C56+F56+I56 -> 0 | P56: =((B56-M56)*C56)+((E56-M56)*F56)+((H56-M56)*I56) -> 0
A57: Umb (One For UST) | B57: 350 | D57: =B57*C57 -> 0 | E57: 300 | G57: =E57*F57 -> 0 | H57: 250 | J57: =H57*I57 -> 0 | K57: =D57+G57+J57 -> 0 | L57: =C57+F57+I57 -> 0 | P57: =((B57-M57)*C57)+((E57-M57)*F57)+((H57-M57)*I57) -> 0
A58: Utensil | B58: 250 | D58: =B58*C58 -> 0 | E58: 200 | G58: =E58*F58 -> 0 | H58: 180 | J58: =H58*I58 -> 0 | K58: =D58+G58+J58 -> 0 | L58: =C58+F58+I58 -> 0
C59: TOTAL | D59: =SUM(D39:D58) -> 3600 | F59: TOTAL | G59: =SUM(G39:G58) -> 0 | I59: TOTAL | J59: =SUM(J39:J58) -> 0 | K59: =D59+G59+J59 -> 3600 | M59: TOTAL | P59: =SUM(P39:P58) -> 3483
A60: TET AND DARS | B60: RETAIL PRICE | C60: PCS SOLD | D60: SALES | E60: DISCOUNTED PRICE | F60: PCS SOLD | G60: SALES | H60: SPECIAL DISC. PRICE | I60: PCS SOLD | J60: SALES | K60: TOTAL SALES | L60: TOTALQTY SOLD | M60: PRODUCTION PRICE | N60: 12% Vat | O60: 10% Mark Up | P60: PROFIT
A61: Arch | B61: 320 | D61: =B61*C61 -> 0 | E61: 300 | G61: =E61*F61 -> 0 | H61: 300 | J61: =H61*I61 -> 0 | K61: =D61+G61+J61 -> 0 | L61: =C61+F61+I61 -> 0 | M61: 240 | N61: 28.8 | O61: 24 | P61: =((B61-M61)*C61)+((E61-M61)*F61)+((H61-M61)*I61) -> 0
A62: Eco Bag | B62: 80 | D62: =B62*C62 -> 0 | E62: 70 | G62: =E62*F62 -> 0 | H62: 60 | J62: =H62*I62 -> 0 | K62: =D62+G62+J62 -> 0 | L62: =C62+F62+I62 -> 0 | M62: 60 | P62: =((B62-M62)*C62)+((E62-M62)*F62)+((H62-M62)*I62) -> 0
A63: Eco Bag | B63: 130 | D63: =B63*C63 -> 0 | E63: 120 | G63: =E63*F63 -> 0 | H63: 110 | J63: =H63*I63 -> 0 | K63: =D63+G63+J63 -> 0 | L63: =C63+F63+I63 -> 0 | M63: 100 | P63: =((B63-M63)*C63)+((E63-M63)*F63)+((H63-M63)*I63) -> 0
A64: Main Building | B64: 430 | D64: =B64*C64 -> 0 | E64: 430 | G64: =E64*F64 -> 0 | H64: 430 | J64: =H64*I64 -> 0 | K64: =D64+G64+J64 -> 0 | L64: =C64+F64+I64 -> 0 | M64: 350 | N64: 42 | O64: 35 | P64: =((B64-M64)*C64)+((E64-M64)*F64)+((H64-M64)*I64) -> 0
A65: Mug | B65: 170 | D65: =B65*C65 -> 0 | E65: 160 | G65: =E65*F65 -> 0 | H65: 150 | J65: =H65*I65 -> 0 | K65: =D65+G65+J65 -> 0 | L65: =C65+F65+I65 -> 0 | M65: 125 | N65: 15 | O65: 12.5 | P65: =((B65-M65)*C65)+((E65-M65)*F65)+((H65-M65)*I65) -> 0
A66: Notebook | B66: 220 | D66: =B66*C66 -> 0 | G66: =E66*F66 -> 0 | J66: =H66*I66 -> 0 | K66: =D66+G66+J66 -> 0 | L66: =C66+F66+I66 -> 0 | P66: =((B66-M66)*C66)+((E66-M66)*F66)+((H66-M66)*I66) -> 0
A67: Pen | B67: 50 | D67: =B67*C67 -> 0 | G67: =E67*F67 -> 0 | J67: =H67*I67 -> 0 | K67: =D67+G67+J67 -> 0 | L67: =C67+F67+I67 -> 0 | M67: 42 | P67: =((B67-M67)*C67)+((E67-M67)*F67)+((H67-M67)*I67) -> 0
A68: Pen | B68: 25 | D68: =B68*C68 -> 0 | G68: =E68*F68 -> 0 | J68: =H68*I68 -> 0 | K68: =D68+G68+J68 -> 0 | L68: =C68+F68+I68 -> 0 | M68: 20 | P68: =((B68-M68)*C68)+((E68-M68)*F68)+((H68-M68)*I68) -> 0
A69: Sticker | B69: 115 | D69: =B69*C69 -> 0 | E69: 110 | G69: =E69*F69 -> 0 | H69: 105 | J69: =H69*I69 -> 0 | K69: =D69+G69+J69 -> 0 | L69: =C69+F69+I69 -> 0 | M69: 85 | P69: =((B69-M69)*C69)+((E69-M69)*F69)+((H69-M69)*I69) -> 0
A70: Sticker | B70: 20 | D70: =B70*C70 -> 0 | E70: 20 | G70: =E70*F70 -> 0 | H70: 20 | J70: =H70*I70 -> 0 | K70: =D70+G70+J70 -> 0 | L70: =C70+F70+I70 -> 0 | M70: 15 | P70: =((B70-M70)*C70)+((E70-M70)*F70)+((H70-M70)*I70) -> 0
A71: Tote | B71: 230 | D71: =B71*C71 -> 0 | G71: =E71*F71 -> 0 | J71: =H71*I71 -> 0 | K71: =D71+G71+J71 -> 0 | L71: =C71+F71+I71 -> 0 | P71: =((B71-M71)*C71)+((E71-M71)*F71)+((H71-M71)*I71) -> 0
C72: TOTAL | D72: =SUM(D61:D71) -> 0 | F72: TOTAL | G72: =SUM(G61:G71) -> 0 | I72: TOTAL | J72: =SUM(J61:J71) -> 0 | K72: =D72+G72+J72 -> 0 | M72: TOTAL | P72: =SUM(P61:P71) -> 0
A73: BLAZE | B73: RETAIL PRICE | C73: PCS SOLD | D73: SALES | E73: DISCOUNTED PRICE | F73: PCS SOLD | G73: SALES | H73: SPECIAL DISC. PRICE | I73: PCS SOLD | J73: SALES | K73: TOTAL SALES | L73: TOTALQTY SOLD | M73: PRODUCTION PRICE | N73: 12% Vat | O73: 10% Mark Up | P73: PROFIT
A74: Crew Neck Shirt | B74: 475 | D74: =B74*C74 -> 0 | E74: 450 | G74: =E74*F74 -> 0 | H74: 430 | J74: =H74*I74 -> 0 | K74: =D74+G74+J74 -> 0 | L74: =C74+F74+I74 -> 0 | M74: 350 | N74: 42 | O74: 35 | P74: =((B74-M74)*C74)+((E74-M74)*F74)+((H74-M74)*I74) -> 0
A75: Polo Shirt | B75: 800 | D75: =B75*C75 -> 0 | E75: 750 | G75: =E75*F75 -> 0 | H75: 700 | J75: =H75*I75 -> 0 | K75: =D75+G75+J75 -> 0 | L75: =C75+F75+I75 -> 0 | M75: 550 | N75: 66 | O75: 55 | P75: =((B75-M75)*C75)+((E75-M75)*F75)+((H75-M75)*I75) -> 0
A76: Socks | B76: 375 | D76: =B76*C76 -> 0 | E76: 350 | G76: =E76*F76 -> 0 | H76: 325 | J76: =H76*I76 -> 0 | K76: =D76+G76+J76 -> 0 | L76: =C76+F76+I76 -> 0 | M76: 250 | N76: 30 | O76: 25 | P76: =((B76-M76)*C76)+((E76-M76)*F76)+((H76-M76)*I76) -> 0
A77: socks set of 3 | B77: 950 | D77: =B77*C77 -> 0 | E77: 900 | G77: =E77*F77 -> 0 | H77: 800 | J77: =H77*I77 -> 0 | K77: =D77+G77+J77 -> 0 | L77: =C77+F77+I77 -> 0 | M77: 750 | N77: 90 | O77: 75 | P77: =((B77-M77)*C77)+((E77-M77)*F77)+((H77-M77)*I77) -> 0
C78: TOTAL | D78: =SUM(D74:D77) -> 0 | F78: TOTAL | G78: =SUM(G74:G77) -> 0 | I78: TOTAL | J78: =SUM(J74:J77) -> 0 | K78: =D78+G78+J78 -> 0 | M78: TOTAL | P78: =SUM(P74:P77) -> 0
A79: VARSITY LIFE STYLE | B79: RETAIL PRICE | C79: PCS SOLD | D79: SALES | E79: DISCOUNTED PRICE | F79: PCS SOLD | G79: SALES | H79: SPECIAL DISC. PRICE | I79: PCS SOLD | J79: SALES | K79: TOTAL SALES | L79: TOTALQTY SOLD | M79: PRODUCTION PRICE | N79: 12% Vat | O79: 10% Mark Up | P79: PROFIT
A80: Baller | B80: 100 | D80: =B80*C80 -> 0 | K80: =D80+G80+J80 -> 0 | L80: =C80+F80+I80 -> 0 | M80: 90
A81: Caps | B81: 800 | D81: =B81*C81 -> 0 | K81: =D81+G81+J81 -> 0 | L81: =C81+F81+I81 -> 0 | M81: 700
A82: Hoodie | B82: 1750 | D82: =B82*C82 -> 0 | K82: =D82+G82+J82 -> 0 | L82: =C82+F82+I82 -> 0 | M82: 1500
A83: Keychain | B83: 100 | D83: =B83*C83 -> 0 | K83: =D83+G83+J83 -> 0 | L83: =C83+F83+I83 -> 0 | M83: 90
A84: Lanyard | B84: 250 | C84: 2 | D84: =B84*C84 -> 500 | K84: =D84+G84+J84 -> 500 | L84: =C84+F84+I84 -> 2 | M84: 200
A85: Long Sticker | B85: 100 | D85: =B85*C85 -> 0 | K85: =D85+G85+J85 -> 0 | L85: =C85+F85+I85 -> 0 | M85: 90
A86: Oversized Sweatshirt | B86: 1500 | D86: =B86*C86 -> 0 | K86: =D86+G86+J86 -> 0 | L86: =C86+F86+I86 -> 0 | M86: 1300
A87: Scarves | B87: 400 | D87: =B87*C87 -> 0 | K87: =D87+G87+J87 -> 0 | L87: =C87+F87+I87 -> 0 | M87: 350
A88: Shirts | B88: 700 | D88: =B88*C88 -> 0 | K88: =D88+G88+J88 -> 0 | L88: =C88+F88+I88 -> 0 | M88: 600
A89: Sticker Pack | B89: 150 | D89: =B89*C89 -> 0 | K89: =D89+G89+J89 -> 0 | L89: =C89+F89+I89 -> 0 | M89: 130
A90: Varsity Jacket | B90: 2100 | D90: =B90*C90 -> 0 | K90: =D90+G90+J90 -> 0 | L90: =C90+F90+I90 -> 0 | M90: 1900
C91: TOTAL | D91: =SUM(D80:D90) -> 500 | F91: TOTAL | G91: =SUM(G80:G90) -> 0 | I91: TOTAL | J91: =SUM(J80:J90) -> 0 | K91: =D91+G91+J91 -> 500 | M91: TOTAL | P91: =SUM(P80:P90) -> 0
A92: MITSUI | B92: RETAIL PRICE | C92: PCS SOLD | D92: SALES | E92: DISCOUNTED PRICE | F92: PCS SOLD | G92: SALES | H92: SPECIAL DISC. PRICE | I92: PCS SOLD | J92: SALES | K92: TOTAL SALES | L92: TOTALQTY SOLD | M92: PRODUCTION PRICE | N92: 12% Vat | O92: 10% Mark Up | P92: PROFIT
A93: Stylus pen | B93: 45 | D93: =B93*C93 -> 0 | E93: 40 | G93: =E93*F93 -> 0 | H93: 25 | J93: =H93*I93 -> 0 | K93: =D93+G93+J93 -> 0 | L93: =C93+F93+I93 -> 0 | M93: 17.36 | N93: 2.08 | O93: 1.74 | P93: =((B93-M93)*C93)+((E93-M93)*F93)+((H93-M93)*I93) -> 0
A94: Retractable | B94: 25 | D94: =B94*C94 -> 0 | E94: 15 | G94: =E94*F94 -> 0 | H94: 20 | J94: =H94*I94 -> 0 | K94: =D94+G94+J94 -> 0 | L94: =C94+F94+I94 -> 0 | M94: 10.08 | N94: 1.21 | O94: 1.01 | P94: =((B94-M94)*C94)+((E94-M94)*F94)+((H94-M94)*I94) -> 0
C95: TOTAL | D95: =SUM(D93+D94) -> 0 | F95: TOTAL | G95: =SUM(G93+G94) -> 0 | I95: TOTAL | J95: =SUM(J93+J94) -> 0 | K95: =D95+G95+J95 -> 0 | M95: TOTAL | P95: =SUM(P93) -> 0
A96: CENTRAL SEMINARY | B96: RETAIL PRICE | C96: PCS SOLD | D96: SALES | E96: DISCOUNTED PRICE | F96: PCS SOLD | G96: SALES | H96: SPECIAL DISC. PRICE | I96: PCS SOLD | J96: SALES | K96: TOTAL SALES | L96: TOTALQTY SOLD | M96: PRODUCTION PRICE | N96: 12% Vat | O96: 10% Mark Up | P96: PROFIT
A97: Subli. Shirt | B97: 550 | C97: 2 | D97: =B97*C97 -> 1100 | G97: =E97*F97 -> 0 | J97: =H97*I97 -> 0 | K97: =D97+G97+J97 -> 1100 | L97: =C97+F97+I97 -> 2 | M97: 500 | P97: =((B97-M97)*C97)+((E97-M97)*F97)+((H97-M97)*I97) -> 100
C98: GRAND TOTAL | D98: =D17+D27+D37+D59+D72+D78+D95+D97+D91 -> 17150 | F98: GRAND TOTAL | G98: =G17+G27+G37+G59+G72+G78+G95+G97+G91 -> 800 | I98: GRAND TOTAL | J98: =J17+J27+J37+J59+J72+J78+J95+J97 -> 0 | K98: =D98+G98+J98 -> 17950 | M98: GRAND TOTAL | P98: =P17+P27+P37+P59+P72+P78+P95+P97 -> 7493
C99: TOTAL SALE | E99: =K98 -> 17950 | N99: TOTAL PROFIT | P99: =P98 -> 7493
B100: CASH BREAKDOWN
...

Sheet May 6
A1: DAILY SALES REPORT
A2: 45415
A3: ITEMS | B3: RETAIL PRICE | C3: PCS SOLD | D3: SALES | E3: DISCOUNTED PRICE | F3: PCS SOLD | G3: SALES | H3: SPECIAL DISC. PRICE | I3: PCS SOLD | J3: SALES | K3: TOTAL SALES | L3: TOTALQTY SOLD | M3: PRODUCTION PRICE | N3: 12% Vat | O3: 10% Mark Up | P3: PROFIT
A4: NAPOLIZ
A5: Backpack Bag | B5: 1750 | D5: =B5*C5 -> 0 | E5: 1600 | G5: =E5*F5 -> 0 | H5: 1400 | J5: =H5*I5 -> 0 | K5: =D5+G5+J5 -> 0 | L5: =C5+F5+I5 -> 0 | M5: 840 | N5: 100.8 | O5: 84 | P5: =((B5-M5)*C5)+((E5-M5)*F5)+((H5-M5)*I5) -> 0
A6: Black Tote Bag (Phased Out) | B6: 280 | D6: =B6*C6 -> 0 | G6: =E6*F6 -> 0 | J6: =H6*I6 -> 0 | K6: =D6+G6+J6 -> 0 | L6: =C6+F6+I6 -> 0 | M6: 230 | P6: =((B6-M6)*C6)+((E6-M6)*F6)+((H6-M6)*I6) -> 0
A7: Double Canopy | B7: 639 | D7: =B7*C7 -> 0 | E7: 575 | G7: =E7*F7 -> 0 | H7: 500 | J7: =H7*I7 -> 0 | K7: =D7+G7+J7 -> 0 | L7: =C7+F7+I7 -> 0 | M7: 330 | N7: 39.6 | O7: 33 | P7: =((B7-M7)*C7)+((E7-M7)*F7)+((H7-M7)*I7) -> 0
A8: Laptop Bag | B8: 1450 | D8: =B8*C8 -> 0 | E8: 1400 | G8: =E8*F8 -> 0 | H8: 1250 | J8: =H8*I8 -> 0 | K8: =D8+G8+J8 -> 0 | L8: =C8+F8+I8 -> 0 | M8: 840 | N8: 100.8 | O8: 84 | P8: =((B8-M8)*C8)+((E8-M8)*F8)+((H8-M8)*I8) -> 0
A9: Script Santo Tomas with Tiger Back (B) | B9: 480 | D9: =B9*C9 -> 0 | E9: 460 | G9: =E9*F9 -> 0 | H9: 450 | J9: =H9*I9 -> 0 | K9: =D9+G9+J9 -> 0 | L9: =C9+F9+I9 -> 0 | M9: 360 | N9: 43.2 | O9: 36 | P9: =((B9-M9)*C9)+((E9-M9)*F9)+((H9-M9)*I9) -> 0
A10: Side Tiger Hoodie | B10: 1480 | C10: 1 | D10: =B10*C10 -> 1480 | E10: 1400 | G10: =E10*F10 -> 0 | H10: 1375 | J10: =H10*I10 -> 0 | K10: =D10+G10+J10 -> 1480 | L10: =C10+F10+I10 -> 1 | M10: 1125 | N10: 135 | O10: 112.5 | P10: =((B10-M10)*C10)+((E10-M10)*F10)+((H10-M10)*I10) -> 355
A11: Sling Bag | B11: 330 | D11: =B11*C11 -> 0 | E11: 320 | G11: =E11*F11 -> 0 | H11: 300 | J11: =H11*I11 -> 0 | K11: =D11+G11+J11 -> 0 | L11: =C11+F11+I11 -> 0 | M11: 260 | N11: 31.2 | O11: 26 | P11: =((B11-M11)*C11)+((E11-M11)*F11)+((H11-M11)*I11) -> 0
A12: Front Tiger Hoodie | B12: 1440 | C12: 1 | D12: =B12*C12 -> 1440 | E12: 1400 | G12: =E12*F12 -> 0 | H12: 1375 | J12: =H12*I12 -> 0 | K12: =D12+G12+J12 -> 1440 | L12: =C12+F12+I12 -> 1 | M12: 1125 | N12: 135 | O12: 112.5 | P12: =((B12-M12)*C12)+((E12-M12)*F12)+((H12-M12)*I12) -> 315
A13: University of Santo Tomas (B) | B13: 450 | C13: 1 | D13: =B13*C13 -> 450 | E13: 440 | G13: =E13*F13 -> 0 | H13: 425 | J13: =H13*I13 -> 0 | K13: =D13+G13+J13 -> 450 | L13: =C13+F13+I13 -> 1 | M13: 360 | N13: 43.2 | O13: 36 | P13: =((B13-M13)*C13)+((E13-M13)*F13)+((H13-M13)*I13) -> 90
A14: UST Tiger Front and Back Graphic (W) | B14: 500 | D14: =B14*C14 -> 0 | E14: 480 | G14: =E14*F14 -> 0 | H14: 450 | J14: =H14*I14 -> 0 | K14: =D14+G14+J14 -> 0 | L14: =C14+F14+I14 -> 0 | M14: 360 | N14: 43.2 | O14: 36 | P14: =((B14-M14)*C14)+((E14-M14)*F14)+((H14-M14)*I14) -> 0
A15: White Tote Bag | B15: 260 | C15: 2 | D15: =B15*C15 -> 520 | E15: 250 | G15: =E15*F15 -> 0 | H15: 240 | J15: =H15*I15 -> 0 | K15: =D15+G15+J15 -> 520 | L15: =C15+F15+I15 -> 2 | M15: 200 | N15: 24 | O15: 20 | P15: =((B15-M15)*C15)+((E15-M15)*F15)+((H15-M15)*I15) -> 120
A16: Wind Breaker | B16: 1650 | C16: 1 | D16: =B16*C16 -> 1650 | E16: 1600 | G16: =E16*F16 -> 0 | H16: 1500 | J16: =H16*I16 -> 0 | K16: =D16+G16+J16 -> 1650 | L16: =C16+F16+I16 -> 1 | M16: 1125 | N16: 135 | O16: 112.5 | P16: =((B16-M16)*C16)+((E16-M16)*F16)+((H16-M16)*I16) -> 525
C17: TOTAL | D17: =SUM(D5:D16) -> 5540 | F17: TOTAL | G17: =SUM(G5:G16) -> 0 | I17: TOTAL | J17: =SUM(J5:J16) -> 0 | K17: =D17+G17+J17 -> 5540 | M17: TOTAL | P17: =SUM(P5:P16) -> 1405
A18: JYL | B18: RETAIL PRICE | C18: PCS SOLD | D18: SALES | E18: DISCOUNTED PRICE | F18: PCS SOLD | G18: SALES | H18: SPECIAL DISC. PRICE | I18: PCS SOLD | J18: SALES | K18: TOTAL SALES | L18: TOTALQTY SOLD | M18: PRODUCTION PRICE | N18: 12% Vat | O18: 10% Mark Up | P18: PROFIT
A19: GT Shirt | B19: 375 | D19: =B19*C19 -> 0 | E19: 350 | G19: =E19*F19 -> 0 | H19: 325 | J19: =H19*I19 -> 0 | K19: =D19+G19+J19 -> 0 | L19: =C19+F19+I19 -> 0 | M19: 250 | N19: 30 | O19: 25 | P19: =((B19-M19)*C19)+((E19-M19)*F19)+((H19-M19)*I19) -> 0
A20: Jacket | B20: 1900 | C20: 2 | D20: =B20*C20 -> 3800 | E20: 1700 | F20: 1 | G20: =E20*F20 -> 1700 | H20: 1500 | J20: =H20*I20 -> 0 | K20: =D20+G20+J20 -> 5500 | L20: =C20+F20+I20 -> 3 | M20: 1200 | N20: 144 | O20: 120 | P20: =((B20-M20)*C20)+((E20-M20)*F20)+((H20-M20)*I20) -> 1900
A21: Poloshirt 123456 | B21: 860 | D21: =B21*C21 -> 0 | E21: 800 | F21: 1 | G21: =E21*F21 -> 800 | H21: 750 | J21: =H21*I21 -> 0 | K21: =D21+G21+J21 -> 800 | L21: =C21+F21+I21 -> 1 | M21: 600 | N21: 72 | O21: 60 | P21: =((B21-M21)*C21)+((E21-M21)*F21)+((H21-M21)*I21) -> 200
A22: VB Jersey w/ sig. (Phased Out) | B22: 2800 | D22: =B22*C22 -> 0 | G22: =E22*F22 -> 0 | J22: =H22*I22 -> 0 | K22: =D22+G22+J22 -> 0 | L22: =C22+F22+I22 -> 0 | M22: 800 | N22: 96 | O22: 80 | P22: =((B22-M22)*C22)+((E22-M22)*F22)+((H22-M22)*I22) -> 0
A23: VB Jersey w/o sig. | B23: 2000 | D23: =B23*C23 -> 0 | E23: 1800 | G23: =E23*F23 -> 0 | H23: 1500 | J23: =H23*I23 -> 0 | K23: =D23+G23+J23 -> 0 | L23: =C23+F23+I23 -> 0 | M23: 800 | P23: =((B23-M23)*C23)+((E23-M23)*F23)+((H23-M23)*I23) -> 0
A24: VB Jersey w/o sig. | B24: 1500 | D24: =B24*C24 -> 0 | E24: 1400 | G24: =E24*F24 -> 0 | H24: 1300 | J24: =H24*I24 -> 0 | K24: =D24+G24+J24 -> 0 | L24: =C24+F24+I24 -> 0 | M24: 800 | P24: =((B24-M24)*C24)+((E24-M24)*F24)+((H24-M24)*I24) -> 0
A25: VB Jersey w/o sig. | B25: 1000 | D25: =B25*C25 -> 0 | E25: 980 | G25: =E25*F25 -> 0 | H25: 950 | J25: =H25*I25 -> 0 | K25: =D25+G25+J25 -> 0 | L25: =C25+F25+I25 -> 0 | M25: 800 | P25: =((B25-M25)*C25)+((E25-M25)*F25)+((H25-M25)*I25) -> 0
A26: VB Jersey with sig. (Phased Out) | B26: 1500 | D26: =B26*C26 -> 0 | G26: =E26*F26 -> 0 | J26: =H26*I26 -> 0 | K26: =D26+G26+J26 -> 0 | L26: =C26+F26+I26 -> 0 | M26: 800 | P26: =((B26-M26)*C26)+((E26-M26)*F26)+((H26-M26)*I26) -> 0
C27: TOTAL | D27: =SUM(D19:D26) -> 3800 | F27: TOTAL | G27: =SUM(G19:G26) -> 2500 | I27: TOTAL | J27: =SUM(J19:J26) -> 0 | K27: =D27+G27+J27 -> 6300 | M27: TOTAL | P27: =SUM(P19:P26) -> 2100
A28: JUC | B28: RETAIL PRICE | C28: PCS SOLD | D28: SALES | E28: DISCOUNTED PRICE | F28: PCS SOLD | G28: SALES | H28: SPECIAL DISC. PRICE | I28: PCS SOLD | J28: SALES | K28: TOTAL SALES | L28: TOTALQTY SOLD | M28: PRODUCTION PRICE | N28: 12% Vat | O28: 10% Mark Up | P28: PROFIT
A29: UST OAT Hoodie Jacket | B29: 1450 | D29: =B29*C29 -> 0 | E29: 1400 | G29: =E29*F29 -> 0 | H29: 1300 | I29: 1 | J29: =H29*I29 -> 1300 | K29: =D29+G29+J29 -> 1300 | L29: =C29+F29+I29 -> 1 | M29: 1000 | N29: 120 | O29: 100 | P29: =((B29-M29)*C29)+((E29-M29)*F29)+((H29-M29)*I29) -> 300
A30: UST OAT MUG | B30: 150 | C30: 2 | D30: =B30*C30 -> 300 | E30: 140 | G30: =E30*F30 -> 0 | H30: 135 | J30: =H30*I30 -> 0 | K30: =D30+G30+J30 -> 300 | L30: =C30+F30+I30 -> 2 | M30: 110 | N30: 12 | O30: 10 | P30: =((B30-M30)*C30)+((E30-M30)*F30)+((H30-M30)*I30) -> 80
A31: UST OAT MUG (WE) Inside | B31: 150 | C31: 1 | D31: =B31*C31 -> 150 | E31: 140 | G31: =E31*F31 -> 0 | H31: 135 | J31: =H31*I31 -> 0 | K31: =D31+G31+J31 -> 150 | L31: =C31+F31+I31 -> 1 | M31: 100 | N31: 12 | O31: 10 | P31: =((B31-M31)*C31)+((E31-M31)*F31)+((H31-M31)*I31) -> 50
A32: UST OAT T-Shirt | B32: 375 | D32: =B32*C32 -> 0 | E32: 360 | G32: =E32*F32 -> 0 | H32: 340 | J32: =H32*I32 -> 0 | K32: =D32+G32+J32 -> 0 | L32: =C32+F32+I32 -> 0 | M32: 280 | N32: 33.6 | O32: 28 | P32: =((B32-M32)*C32)+((E32-M32)*F32)+((H32-M32)*I32) -> 0
A33: UST T-Shirt Sports | B33: 430 | C33: 5 | D33: =B33*C33 -> 2150 | E33: 400 | G33: =E33*F33 -> 0 | H33: 350 | J33: =H33*I33 -> 0 | K33: =D33+G33+J33 -> 2150 | L33: =C33+F33+I33 -> 5 | M33: 260 | N33: 31.2 | O33: 26 | P33: =((B33-M33)*C33)+((E33-M33)*F33)+((H33-M33)*I33) -> 850
A34: UST T-Shirt Tiger Pattern | B34: 450 | D34: =B34*C34 -> 0 | E34: 430 | G34: =E34*F34 -> 0 | H34: 400 | J34: =H34*I34 -> 0 | K34: =D34+G34+J34 -> 0 | L34: =C34+F34+I34 -> 0 | M34: 330 | N34: 39.6 | O34: 33 | P34: =((B34-M34)*C34)+((E34-M34)*F34)+((H34-M34)*I34) -> 0
A35: UST Happy Tiger | B35: 450 | C35: 2 | D35: =B35*C35 -> 900 | E35: 400 | G35: =E35*F35 -> 0 | H35: 375 | J35: =H35*I35 -> 0 | K35: =D35+G35+J35 -> 900 | L35: =C35+F35+I35 -> 2 | M35: 280 | N35: 33.6 | O35: 28 | P35: =((B35-M35)*C35)+((E35-M35)*F35)+((H35-M35)*I35) -> 340
A36: OAT Tote Bag (Phased Out) | B36: 220 | D36: =B36*C36 -> 0 | G36: =E36*F36 -> 0 | J36: =H36*I36 -> 0 | K36: =D36+G36+J36 -> 0 | L36: =C36+F36+I36 -> 0 | M36: 120 | P36: =((B36-M36)*C36)+((E36-M36)*F36)+((H36-M36)*I36) -> 0
C37: TOTAL | D37: =SUM(D29:D36) -> 3500 | F37: TOTAL | G37: =SUM(G29:G36) -> 0 | I37: TOTAL | J37: =SUM(J29:J36) -> 1300 | K37: =D37+G37+J37 -> 4800 | M37: TOTAL | P37: =SUM(P29:P36) -> 1620
A38: USTORE | B38: RETAIL PRICE | C38: PCS SOLD | D38: SALES | E38: DISCOUNTED PRICE | F38: PCS SOLD | G38: SALES | H38: SPECIAL DISC. PRICE | I38: PCS SOLD | J38: SALES | K38: TOTAL SALES | L38: TOTALQTY SOLD | M38: PRODUCTION PRICE | N38: 12% Vat | O38: 10% Mark Up | P38: PROFIT
A39: Auto Umbrella | B39: 250 | D39: =B39*C39 -> 0 | G39: =E39*F39 -> 0 | J39: =H39*I39 -> 0 | K39: =D39+G39+J39 -> 0 | L39: =C39+F39+I39 -> 0 | P39: =((B39-M39)*C39)+((E39-M39)*F39)+((H39-M39)*I39) -> 0
A40: Bag | B40: 250 | D40: =B40*C40 -> 0 | G40: =E40*F40 -> 0 | J40: =H40*I40 -> 0 | K40: =D40+G40+J40 -> 0 | L40: =C40+F40+I40 -> 0 | P40: =((B40-M40)*C40)+((E40-M40)*F40)+((H40-M40)*I40) -> 0
A41: Eco Bag CGEEE! | B41: 50 | D41: =B41*C41 -> 0 | E41: 35 | G41: =E41*F41 -> 0 | J41: =H41*I41 -> 0 | K41: =D41+G41+J41 -> 0 | L41: =C41+F41+I41 -> 0 | P41: =((B41-M41)*C41)+((E41-M41)*F41)+((H41-M41)*I41) -> 0
A42: Keychain | B42: 150 | C42: 2 | D42: =B42*C42 -> 300 | E42: 120 | G42: =E42*F42 -> 0 | H42: 75 | J42: =H42*I42 -> 0 | K42: =D42+G42+J42 -> 300 | L42: =C42+F42+I42 -> 2 | P42: =((B42-M42)*C42)+((E42-M42)*F42)+((H42-M42)*I42) -> 300
A43: Kit Set | B43: 800 | D43: =B43*C43 -> 0 | E43: 750 | G43: =E43*F43 -> 0 | H43: 700 | J43: =H43*I43 -> 0 | K43: =D43+G43+J43 -> 0 | L43: =C43+F43+I43 -> 0 | P43: =((B43-M43)*C43)+((E43-M43)*F43)+((H43-M43)*I43) -> 0
A44: Lanyard | B44: 190 | C44: 4 | D44: =B44*C44 -> 760 | E44: 175 | G44: =E44*F44 -> 0 | H44: 150 | J44: =H44*I44 -> 0 | K44: =D44+G44+J44 -> 760 | L44: =C44+F44+I44 -> 4 | M44: 117 | N44: 14.04 | O44: 11.7 | P44: =((B44-M44)*C44)+((E44-M44)*F44)+((H44-M44)*I44) -> 292
A45: Lanyard | B45: 180 | C45: 6 | D45: =B45*C45 -> 1080 | E45: 165 | G45: =E45*F45 -> 0 | H45: 140 | J45: =H45*I45 -> 0 | K45: =D45+G45+J45 -> 1080 | L45: =C45+F45+I45 -> 6 | M45: 110 | N45: 13.2 | O45: 11 | P45: =((B45-M45)*C45)+((E45-M45)*F45)+((H45-M45)*I45) -> 420
A46: NB | B46: 75 | D46: =B46*C46 -> 0 | G46: =E46*F46 -> 0 | J46: =H46*I46 -> 0 | K46: =D46+G46+J46 -> 0 | L46: =C46+F46+I46 -> 0 | P46: =((B46-M46)*C46)+((E46-M46)*F46)+((H46-M46)*I46) -> 0
A47: NB | B47: 100 | C47: 2 | D47: =B47*C47 -> 200 | E47: 80 | G47: =E47*F47 -> 0 | H47: 70 | J47: =H47*I47 -> 0 | K47: =D47+G47+J47 -> 200 | L47: =C47+F47+I47 -> 2 | P47: =((B47-M47)*C47)+((E47-M47)*F47)+((H47-M47)*I47) -> 200
A48: Sash Big | B48: 600 | D48: =B48*C48 -> 0 | E48: 500 | G48: =E48*F48 -> 0 | H48: 400 | J48: =H48*I48 -> 0 | K48: =D48+G48+J48 -> 0 | L48: =C48+F48+I48 -> 0 | P48: =((B48-M48)*C48)+((E48-M48)*F48)+((H48-M48)*I48) -> 0
A49: Sash Small | B49: 150 | D49: =B49*C49 -> 0 | E49: 125 | G49: =E49*F49 -> 0 | H49: 100 | J49: =H49*I49 -> 0 | K49: =D49+G49+J49 -> 0 | L49: =C49+F49+I49 -> 0 | P49: =((B49-M49)*C49)+((E49-M49)*F49)+((H49-M49)*I49) -> 0
A50: Shabby Hat | B50: 200 | C50: 3 | D50: =B50*C50 -> 600 | E50: 175 | G50: =E50*F50 -> 0 | H50: 150 | J50: =H50*I50 -> 0 | K50: =D50+G50+J50 -> 600 | L50: =C50+F50+I50 -> 3 | P50: =((B50-M50)*C50)+((E50-M50)*F50)+((H50-M50)*I50) -> 600
A51: Tiger Stuff Toy Small Grad | B51: 250 | C51: 3 | D51: =B51*C51 -> 750 | E51: 230 | G51: =E51*F51 -> 0 | H51: 200 | I51: 1 | J51: =H51*I51 -> 200 | K51: =D51+G51+J51 -> 950 | L51: =C51+F51+I51 -> 4 | P51: =((B51-M51)*C51)+((E51-M51)*F51)+((H51-M51)*I51) -> 950
A52: Tote Bag CGEEE! | B52: 120 | D52: =B52*C52 -> 0 | E52: 100 | G52: =E52*F52 -> 0 | H52: 80 | J52: =H52*I52 -> 0 | K52: =D52+G52+J52 -> 0 | L52: =C52+F52+I52 -> 0 | P52: =((B52-M52)*C52)+((E52-M52)*F52)+((H52-M52)*I52) -> 0
A53: Tote Bag Canvas White | B53: 160 | C53: 3 | D53: =B53*C53 -> 480 | G53: =E53*F53 -> 0 | J53: =H53*I53 -> 0 | K53: =D53+G53+J53 -> 480 | L53: =C53+F53+I53 -> 3 | P53: =((B53-M53)*C53)+((E53-M53)*F53)+((H53-M53)*I53) -> 480
A54: Tote (One For UST) | B54: 300 | D54: =B54*C54 -> 0 | E54: 275 | G54: =E54*F54 -> 0 | H54: 250 | J54: =H54*I54 -> 0 | K54: =D54+G54+J54 -> 0 | L54: =C54+F54+I54 -> 0 | P54: =((B54-M54)*C54)+((E54-M54)*F54)+((H54-M54)*I54) -> 0
A55: Tumbler | B55: 150 | D55: =B55*C55 -> 0 | G55: =E55*F55 -> 0 | J55: =H55*I55 -> 0 | K55: =D55+G55+J55 -> 0 | L55: =C55+F55+I55 -> 0 | P55: =((B55-M55)*C55)+((E55-M55)*F55)+((H55-M55)*I55) -> 0
A56: Umb. Cane | B56: 500 | D56: =B56*C56 -> 0 | E56: 450 | G56: =E56*F56 -> 0 | H56: 400 | J56: =H56*I56 -> 0 | K56: =D56+G56+J56 -> 0 | L56: =C56+F56+I56 -> 0 | P56: =((B56-M56)*C56)+((E56-M56)*F56)+((H56-M56)*I56) -> 0
A57: Umb (One For UST) | B57: 350 | D57: =B57*C57 -> 0 | E57: 300 | G57: =E57*F57 -> 0 | H57: 250 | J57: =H57*I57 -> 0 | K57: =D57+G57+J57 -> 0 | L57: =C57+F57+I57 -> 0 | P57: =((B57-M57)*C57)+((E57-M57)*F57)+((H57-M57)*I57) -> 0
A58: Utensil | B58: 250 | D58: =B58*C58 -> 0 | E58: 200 | G58: =E58*F58 -> 0 | H58: 180 | J58: =H58*I58 -> 0 | K58: =D58+G58+J58 -> 0 | L58: =C58+F58+I58 -> 0
C59: TOTAL | D59: =SUM(D39:D58) -> 4170 | F59: TOTAL | G59: =SUM(G39:G58) -> 0 | I59: TOTAL | J59: =SUM(J39:J58) -> 200 | K59: =D59+G59+J59 -> 4370 | M59: TOTAL | P59: =SUM(P39:P58) -> 3242
A60: TET AND DARS | B60: RETAIL PRICE | C60: PCS SOLD | D60: SALES | E60: DISCOUNTED PRICE | F60: PCS SOLD | G60: SALES | H60: SPECIAL DISC. PRICE | I60: PCS SOLD | J60: SALES | K60: TOTAL SALES | L60: TOTALQTY SOLD | M60: PRODUCTION PRICE | N60: 12% Vat | O60: 10% Mark Up | P60: PROFIT
A61: Arch | B61: 320 | D61: =B61*C61 -> 0 | E61: 300 | G61: =E61*F61 -> 0 | H61: 300 | J61: =H61*I61 -> 0 | K61: =D61+G61+J61 -> 0 | L61: =C61+F61+I61 -> 0 | M61: 240 | N61: 28.8 | O61: 24 | P61: =((B61-M61)*C61)+((E61-M61)*F61)+((H61-M61)*I61) -> 0
A62: Eco Bag | B62: 80 | D62: =B62*C62 -> 0 | E62: 70 | G62: =E62*F62 -> 0 | H62: 60 | J62: =H62*I62 -> 0 | K62: =D62+G62+J62 -> 0 | L62: =C62+F62+I62 -> 0 | M62: 60 | P62: =((B62-M62)*C62)+((E62-M62)*F62)+((H62-M62)*I62) -> 0
A63: Eco Bag | B63: 130 | D63: =B63*C63 -> 0 | E63: 120 | G63: =E63*F63 -> 0 | H63: 110 | J63: =H63*I63 -> 0 | K63: =D63+G63+J63 -> 0 | L63: =C63+F63+I63 -> 0 | M63: 100 | P63: =((B63-M63)*C63)+((E63-M63)*F63)+((H63-M63)*I63) -> 0
A64: Main Building | B64: 430 | D64: =B64*C64 -> 0 | E64: 430 | G64: =E64*F64 -> 0 | H64: 430 | J64: =H64*I64 -> 0 | K64: =D64+G64+J64 -> 0 | L64: =C64+F64+I64 -> 0 | M64: 350 | N64: 42 | O64: 35 | P64: =((B64-M64)*C64)+((E64-M64)*F64)+((H64-M64)*I64) -> 0
A65: Mug | B65: 170 | D65: =B65*C65 -> 0 | E65: 160 | G65: =E65*F65 -> 0 | H65: 150 | J65: =H65*I65 -> 0 | K65: =D65+G65+J65 -> 0 | L65: =C65+F65+I65 -> 0 | M65: 125 | N65: 15 | O65: 12.5 | P65: =((B65-M65)*C65)+((E65-M65)*F65)+((H65-M65)*I65) -> 0
A66: Notebook | B66: 220 | D66: =B66*C66 -> 0 | G66: =E66*F66 -> 0 | J66: =H66*I66 -> 0 | K66: =D66+G66+J66 -> 0 | L66: =C66+F66+I66 -> 0 | P66: =((B66-M66)*C66)+((E66-M66)*F66)+((H66-M66)*I66) -> 0
A67: Pen | B67: 50 | D67: =B67*C67 -> 0 | G67: =E67*F67 -> 0 | J67: =H67*I67 -> 0 | K67: =D67+G67+J67 -> 0 | L67: =C67+F67+I67 -> 0 | M67: 42 | P67: =((B67-M67)*C67)+((E67-M67)*F67)+((H67-M67)*I67) -> 0
A68: Pen | B68: 25 | D68: =B68*C68 -> 0 | G68: =E68*F68 -> 0 | J68: =H68*I68 -> 0 | K68: =D68+G68+J68 -> 0 | L68: =C68+F68+I68 -> 0 | M68: 20 | P68: =((B68-M68)*C68)+((E68-M68)*F68)+((H68-M68)*I68) -> 0
A69: Sticker | B69: 115 | C69: 2 | D69: =B69*C69 -> 230 | E69: 110 | G69: =E69*F69 -> 0 | H69: 105 | J69: =H69*I69 -> 0 | K69: =D69+G69+J69 -> 230 | L69: =C69+F69+I69 -> 2 | M69: 85 | P69: =((B69-M69)*C69)+((E69-M69)*F69)+((H69-M69)*I69) -> 60
A70: Sticker | B70: 20 | D70: =B70*C70 -> 0 | E70: 20 | G70: =E70*F70 -> 0 | H70: 20 | J70: =H70*I70 -> 0 | K70: =D70+G70+J70 -> 0 | L70: =C70+F70+I70 -> 0 | M70: 15 | P70: =((B70-M70)*C70)+((E70-M70)*F70)+((H70-M70)*I70) -> 0
A71: Tote | B71: 230 | D71: =B71*C71 -> 0 | G71: =E71*F71 -> 0 | J71: =H71*I71 -> 0 | K71: =D71+G71+J71 -> 0 | L71: =C71+F71+I71 -> 0 | P71: =((B71-M71)*C71)+((E71-M71)*F71)+((H71-M71)*I71) -> 0
C72: TOTAL | D72: =SUM(D61:D71) -> 230 | F72: TOTAL | G72: =SUM(G61:G71) -> 0 | I72: TOTAL | J72: =SUM(J61:J71) -> 0 | K72: =D72+G72+J72 -> 230 | M72: TOTAL | P72: =SUM(P61:P71) -> 60
A73: BLAZE | B73: RETAIL PRICE | C73: PCS SOLD | D73: SALES | E73: DISCOUNTED PRICE | F73: PCS SOLD | G73: SALES | H73: SPECIAL DISC. PRICE | I73: PCS SOLD | J73: SALES | K73: TOTAL SALES | L73: TOTALQTY SOLD | M73: PRODUCTION PRICE | N73: 12% Vat | O73: 10% Mark Up | P73: PROFIT
A74: Crew Neck Shirt | B74: 475 | D74: =B74*C74 -> 0 | E74: 450 | G74: =E74*F74 -> 0 | H74: 430 | J74: =H74*I74 -> 0 | K74: =D74+G74+J74 -> 0 | L74: =C74+F74+I74 -> 0 | M74: 350 | N74: 42 | O74: 35 | P74: =((B74-M74)*C74)+((E74-M74)*F74)+((H74-M74)*I74) -> 0
A75: Polo Shirt | B75: 800 | C75: 1 | D75: =B75*C75 -> 800 | E75: 750 | G75: =E75*F75 -> 0 | H75: 700 | J75: =H75*I75 -> 0 | K75: =D75+G75+J75 -> 800 | L75: =C75+F75+I75 -> 1 | M75: 550 | N75: 66 | O75: 55 | P75: =((B75-M75)*C75)+((E75-M75)*F75)+((H75-M75)*I75) -> 250
A76: Socks | B76: 375 | D76: =B76*C76 -> 0 | E76: 350 | G76: =E76*F76 -> 0 | H76: 325 | J76: =H76*I76 -> 0 | K76: =D76+G76+J76 -> 0 | L76: =C76+F76+I76 -> 0 | M76: 250 | N76: 30 | O76: 25 | P76: =((B76-M76)*C76)+((E76-M76)*F76)+((H76-M76)*I76) -> 0
A77: socks set of 3 | B77: 950 | D77: =B77*C77 -> 0 | E77: 900 | G77: =E77*F77 -> 0 | H77: 800 | J77: =H77*I77 -> 0 | K77: =D77+G77+J77 -> 0 | L77: =C77+F77+I77 -> 0 | M77: 750 | N77: 90 | O77: 75 | P77: =((B77-M77)*C77)+((E77-M77)*F77)+((H77-M77)*I77) -> 0
C78: TOTAL | D78: =SUM(D74:D77) -> 800 | F78: TOTAL | G78: =SUM(G74:G77) -> 0 | I78: TOTAL | J78: =SUM(J74:J77) -> 0 | K78: =D78+G78+J78 -> 800 | M78: TOTAL | P78: =SUM(P74:P77) -> 250
A79: VARSITY LIFE STYLE | B79: RETAIL PRICE | C79: PCS SOLD | D79: SALES | E79: DISCOUNTED PRICE | F79: PCS SOLD | G79: SALES | H79: SPECIAL DISC. PRICE | I79: PCS SOLD | J79: SALES | K79: TOTAL SALES | L79: TOTALQTY SOLD | M79: PRODUCTION PRICE | N79: 12% Vat | O79: 10% Mark Up | P79: PROFIT
A80: Baller | B80: 100 | D80: =B80*C80 -> 0 | K80: =D80+G80+J80 -> 0 | L80: =C80+F80+I80 -> 0 | M80: 90
A81: Caps | B81: 800 | D81: =B81*C81 -> 0 | K81: =D81+G81+J81 -> 0 | L81: =C81+F81+I81 -> 0 | M81: 700
A82: Hoodie | B82: 1750 | D82: =B82*C82 -> 0 | K82: =D82+G82+J82 -> 0 | L82: =C82+F82+I82 -> 0 | M82: 1500
A83: Keychain | B83: 100 | D83: =B83*C83 -> 0 | K83: =D83+G83+J83 -> 0 | L83: =C83+F83+I83 -> 0 | M83: 90
A84: Lanyard | B84: 250 | D84: =B84*C84 -> 0 | K84: =D84+G84+J84 -> 0 | L84: =C84+F84+I84 -> 0 | M84: 200
A85: Long Sticker | B85: 100 | D85: =B85*C85 -> 0 | K85: =D85+G85+J85 -> 0 | L85: =C85+F85+I85 -> 0 | M85: 90
A86: Oversized Sweatshirt | B86: 1500 | D86: =B86*C86 -> 0 | K86: =D86+G86+J86 -> 0 | L86: =C86+F86+I86 -> 0 | M86: 1300
A87: Scarves | B87: 400 | D87: =B87*C87 -> 0 | K87: =D87+G87+J87 -> 0 | L87: =C87+F87+I87 -> 0 | M87: 350
A88: Shirts | B88: 700 | D88: =B88*C88 -> 0 | K88: =D88+G88+J88 -> 0 | L88: =C88+F88+I88 -> 0 | M88: 600
A89: Sticker Pack | B89: 150 | D89: =B89*C89 -> 0 | K89: =D89+G89+J89 -> 0 | L89: =C89+F89+I89 -> 0 | M89: 130
A90: Varsity Jacket | B90: 2100 | D90: =B90*C90 -> 0 | K90: =D90+G90+J90 -> 0 | L90: =C90+F90+I90 -> 0 | M90: 1900
C91: TOTAL | D91: =SUM(D80:D90) -> 0 | F91: TOTAL | G91: =SUM(G80:G90) -> 0 | I91: TOTAL | J91: =SUM(J80:J90) -> 0 | K91: =D91+G91+J91 -> 0 | M91: TOTAL | P91: =SUM(P80:P90) -> 0
A92: MITSUI | B92: RETAIL PRICE | C92: PCS SOLD | D92: SALES | E92: DISCOUNTED PRICE | F92: PCS SOLD | G92: SALES | H92: SPECIAL DISC. PRICE | I92: PCS SOLD | J92: SALES | K92: TOTAL SALES | L92: TOTALQTY SOLD | M92: PRODUCTION PRICE | N92: 12% Vat | O92: 10% Mark Up | P92: PROFIT
A93: Stylus pen | B93: 45 | D93: =B93*C93 -> 0 | E93: 40 | G93: =E93*F93 -> 0 | H93: 25 | J93: =H93*I93 -> 0 | K93: =D93+G93+J93 -> 0 | L93: =C93+F93+I93 -> 0 | M93: 17.36 | N93: 2.08 | O93: 1.74 | P93: =((B93-M93)*C93)+((E93-M93)*F93)+((H93-M93)*I93) -> 0
A94: Retractable | B94: 25 | D94: =B94*C94 -> 0 | E94: 15 | G94: =E94*F94 -> 0 | H94: 20 | J94: =H94*I94 -> 0 | K94: =D94+G94+J94 -> 0 | L94: =C94+F94+I94 -> 0 | M94: 10.08 | N94: 1.21 | O94: 1.01 | P94: =((B94-M94)*C94)+((E94-M94)*F94)+((H94-M94)*I94) -> 0
C95: TOTAL | D95: =SUM(D93+D94) -> 0 | F95: TOTAL | G95: =SUM(G93+G94) -> 0 | I95: TOTAL | J95: =SUM(J93+J94) -> 0 | K95: =D95+G95+J95 -> 0 | M95: TOTAL | P95: =SUM(P93) -> 0
A96: CENTRAL SEMINARY | B96: RETAIL PRICE | C96: PCS SOLD | D96: SALES | E96: DISCOUNTED PRICE | F96: PCS SOLD | G96: SALES | H96: SPECIAL DISC. PRICE | I96: PCS SOLD | J96: SALES | K96: TOTAL SALES | L96: TOTALQTY SOLD | M96: PRODUCTION PRICE | N96: 12% Vat | O96: 10% Mark Up | P96: PROFIT
A97: Subli. Shirt | B97: 550 | C97: 7 | D97: =B97*C97 -> 3850 | G97: =E97*F97 -> 0 | J97: =H97*I97 -> 0 | K97: =D97+G97+J97 -> 3850 | L97: =C97+F97+I97 -> 7 | M97: 500 | P97: =((B97-M97)*C97)+((E97-M97)*F97)+((H97-M97)*I97) -> 350
C98: GRAND TOTAL | D98: =D17+D27+D37+D59+D72+D78+D95+D97+D91 -> 21890 | F98: GRAND TOTAL | G98: =G17+G27+G37+G59+G72+G78+G95+G97+G91 -> 2500 | I98: GRAND TOTAL | J98: =J17+J27+J37+J59+J72+J78+J95+J97 -> 1500 | K98: =D98+G98+J98 -> 25890 | M98: GRAND TOTAL | P98: =P17+P27+P37+P59+P72+P78+P95+P97 -> 9027
C99: TOTAL SALE | E99: =K98 -> 25890 | N99: TOTAL PROFIT | P99: =P98 -> 9027
B100: CASH BREAKDOWN
...

Sheet May 7
A1: DAILY SALES REPORT
A2: 45415
A3: ITEMS | B3: RETAIL PRICE | C3: PCS SOLD | D3: SALES | E3: DISCOUNTED PRICE | F3: PCS SOLD | G3: SALES | H3: SPECIAL DISC. PRICE | I3: PCS SOLD | J3: SALES | K3: TOTAL SALES | L3: TOTALQTY SOLD | M3: PRODUCTION PRICE | N3: 12% Vat | O3: 10% Mark Up | P3: PROFIT
A4: NAPOLIZ
A5: Backpack Bag | B5: 1750 | C5: 1 | D5: =B5*C5 -> 1750 | E5: 1600 | G5: =E5*F5 -> 0 | H5: 1400 | J5: =H5*I5 -> 0 | K5: =D5+G5+J5 -> 1750 | L5: =C5+F5+I5 -> 1 | M5: 840 | N5: 100.8 | O5: 84 | P5: =((B5-M5)*C5)+((E5-M5)*F5)+((H5-M5)*I5) -> 910
A6: Black Tote Bag (Phased Out) | B6: 280 | D6: =B6*C6 -> 0 | G6: =E6*F6 -> 0 | J6: =H6*I6 -> 0 | K6: =D6+G6+J6 -> 0 | L6: =C6+F6+I6 -> 0 | M6: 230 | P6: =((B6-M6)*C6)+((E6-M6)*F6)+((H6-M6)*I6) -> 0
A7: Double Canopy | B7: 639 | D7: =B7*C7 -> 0 | E7: 575 | G7: =E7*F7 -> 0 | H7: 500 | J7: =H7*I7 -> 0 | K7: =D7+G7+J7 -> 0 | L7: =C7+F7+I7 -> 0 | M7: 330 | N7: 39.6 | O7: 33 | P7: =((B7-M7)*C7)+((E7-M7)*F7)+((H7-M7)*I7) -> 0
A8: Laptop Bag | B8: 1450 | D8: =B8*C8 -> 0 | E8: 1400 | G8: =E8*F8 -> 0 | H8: 1250 | J8: =H8*I8 -> 0 | K8: =D8+G8+J8 -> 0 | L8: =C8+F8+I8 -> 0 | M8: 840 | N8: 100.8 | O8: 84 | P8: =((B8-M8)*C8)+((E8-M8)*F8)+((H8-M8)*I8) -> 0
A9: Script Santo Tomas with Tiger Back (B) | B9: 480 | C9: 1 | D9: =B9*C9 -> 480 | E9: 460 | G9: =E9*F9 -> 0 | H9: 450 | J9: =H9*I9 -> 0 | K9: =D9+G9+J9 -> 480 | L9: =C9+F9+I9 -> 1 | M9: 360 | N9: 43.2 | O9: 36 | P9: =((B9-M9)*C9)+((E9-M9)*F9)+((H9-M9)*I9) -> 120
A10: Side Tiger Hoodie | B10: 1480 | D10: =B10*C10 -> 0 | E10: 1400 | G10: =E10*F10 -> 0 | H10: 1375 | J10: =H10*I10 -> 0 | K10: =D10+G10+J10 -> 0 | L10: =C10+F10+I10 -> 0 | M10: 1125 | N10: 135 | O10: 112.5 | P10: =((B10-M10)*C10)+((E10-M10)*F10)+((H10-M10)*I10) -> 0
A11: Sling Bag | B11: 330 | D11: =B11*C11 -> 0 | E11: 320 | G11: =E11*F11 -> 0 | H11: 300 | J11: =H11*I11 -> 0 | K11: =D11+G11+J11 -> 0 | L11: =C11+F11+I11 -> 0 | M11: 260 | N11: 31.2 | O11: 26 | P11: =((B11-M11)*C11)+((E11-M11)*F11)+((H11-M11)*I11) -> 0
A12: Front Tiger Hoodie | B12: 1440 | D12: =B12*C12 -> 0 | E12: 1400 | G12: =E12*F12 -> 0 | H12: 1375 | J12: =H12*I12 -> 0 | K12: =D12+G12+J12 -> 0 | L12: =C12+F12+I12 -> 0 | M12: 1125 | N12: 135 | O12: 112.5 | P12: =((B12-M12)*C12)+((E12-M12)*F12)+((H12-M12)*I12) -> 0
A13: University of Santo Tomas (B) | B13: 450 | C13: 1 | D13: =B13*C13 -> 450 | E13: 440 | G13: =E13*F13 -> 0 | H13: 425 | J13: =H13*I13 -> 0 | K13: =D13+G13+J13 -> 450 | L13: =C13+F13+I13 -> 1 | M13: 360 | N13: 43.2 | O13: 36 | P13: =((B13-M13)*C13)+((E13-M13)*F13)+((H13-M13)*I13) -> 90
A14: UST Tiger Front and Back Graphic (W) | B14: 500 | D14: =B14*C14 -> 0 | E14: 480 | G14: =E14*F14 -> 0 | H14: 450 | J14: =H14*I14 -> 0 | K14: =D14+G14+J14 -> 0 | L14: =C14+F14+I14 -> 0 | M14: 360 | N14: 43.2 | O14: 36 | P14: =((B14-M14)*C14)+((E14-M14)*F14)+((H14-M14)*I14) -> 0
A15: White Tote Bag | B15: 260 | D15: =B15*C15 -> 0 | E15: 250 | G15: =E15*F15 -> 0 | H15: 240 | J15: =H15*I15 -> 0 | K15: =D15+G15+J15 -> 0 | L15: =C15+F15+I15 -> 0 | M15: 200 | N15: 24 | O15: 20 | P15: =((B15-M15)*C15)+((E15-M15)*F15)+((H15-M15)*I15) -> 0
A16: Wind Breaker | B16: 1650 | C16: 2 | D16: =B16*C16 -> 3300 | E16: 1600 | G16: =E16*F16 -> 0 | H16: 1500 | J16: =H16*I16 -> 0 | K16: =D16+G16+J16 -> 3300 | L16: =C16+F16+I16 -> 2 | M16: 1125 | N16: 135 | O16: 112.5 | P16: =((B16-M16)*C16)+((E16-M16)*F16)+((H16-M16)*I16) -> 1050
C17: TOTAL | D17: =SUM(D5:D16) -> 5980 | F17: TOTAL | G17: =SUM(G5:G16) -> 0 | I17: TOTAL | J17: =SUM(J5:J16) -> 0 | K17: =D17+G17+J17 -> 5980 | M17: TOTAL | P17: =SUM(P5:P16) -> 2170
A18: JYL | B18: RETAIL PRICE | C18: PCS SOLD | D18: SALES | E18: DISCOUNTED PRICE | F18: PCS SOLD | G18: SALES | H18: SPECIAL DISC. PRICE | I18: PCS SOLD | J18: SALES | K18: TOTAL SALES | L18: TOTALQTY SOLD | M18: PRODUCTION PRICE | N18: 12% Vat | O18: 10% Mark Up | P18: PROFIT
A19: GT Shirt | B19: 375 | D19: =B19*C19 -> 0 | E19: 350 | G19: =E19*F19 -> 0 | H19: 325 | J19: =H19*I19 -> 0 | K19: =D19+G19+J19 -> 0 | L19: =C19+F19+I19 -> 0 | M19: 250 | N19: 30 | O19: 25 | P19: =((B19-M19)*C19)+((E19-M19)*F19)+((H19-M19)*I19) -> 0
A20: Jacket | B20: 1900 | C20: 2 | D20: =B20*C20 -> 3800 | E20: 1700 | G20: =E20*F20 -> 0 | H20: 1500 | J20: =H20*I20 -> 0 | K20: =D20+G20+J20 -> 3800 | L20: =C20+F20+I20 -> 2 | M20: 1200 | N20: 144 | O20: 120 | P20: =((B20-M20)*C20)+((E20-M20)*F20)+((H20-M20)*I20) -> 1400
A21: Poloshirt 123456 | B21: 860 | D21: =B21*C21 -> 0 | E21: 800 | G21: =E21*F21 -> 0 | H21: 750 | J21: =H21*I21 -> 0 | K21: =D21+G21+J21 -> 0 | L21: =C21+F21+I21 -> 0 | M21: 600 | N21: 72 | O21: 60 | P21: =((B21-M21)*C21)+((E21-M21)*F21)+((H21-M21)*I21) -> 0
A22: VB Jersey w/ sig. (Phased Out) | B22: 2800 | D22: =B22*C22 -> 0 | G22: =E22*F22 -> 0 | J22: =H22*I22 -> 0 | K22: =D22+G22+J22 -> 0 | L22: =C22+F22+I22 -> 0 | M22: 800 | N22: 96 | O22: 80 | P22: =((B22-M22)*C22)+((E22-M22)*F22)+((H22-M22)*I22) -> 0
A23: VB Jersey w/o sig. | B23: 2000 | D23: =B23*C23 -> 0 | E23: 1800 | G23: =E23*F23 -> 0 | H23: 1500 | J23: =H23*I23 -> 0 | K23: =D23+G23+J23 -> 0 | L23: =C23+F23+I23 -> 0 | M23: 800 | P23: =((B23-M23)*C23)+((E23-M23)*F23)+((H23-M23)*I23) -> 0
A24: VB Jersey w/o sig. | B24: 1500 | D24: =B24*C24 -> 0 | E24: 1400 | G24: =E24*F24 -> 0 | H24: 1300 | J24: =H24*I24 -> 0 | K24: =D24+G24+J24 -> 0 | L24: =C24+F24+I24 -> 0 | M24: 800 | P24: =((B24-M24)*C24)+((E24-M24)*F24)+((H24-M24)*I24) -> 0
A25: VB Jersey w/o sig. | B25: 1000 | D25: =B25*C25 -> 0 | E25: 980 | G25: =E25*F25 -> 0 | H25: 950 | J25: =H25*I25 -> 0 | K25: =D25+G25+J25 -> 0 | L25: =C25+F25+I25 -> 0 | M25: 800 | P25: =((B25-M25)*C25)+((E25-M25)*F25)+((H25-M25)*I25) -> 0
A26: VB Jersey with sig. (Phased Out) | B26: 1500 | D26: =B26*C26 -> 0 | G26: =E26*F26 -> 0 | J26: =H26*I26 -> 0 | K26: =D26+G26+J26 -> 0 | L26: =C26+F26+I26 -> 0 | M26: 800 | P26: =((B26-M26)*C26)+((E26-M26)*F26)+((H26-M26)*I26) -> 0
C27: TOTAL | D27: =SUM(D19:D26) -> 3800 | F27: TOTAL | G27: =SUM(G19:G26) -> 0 | I27: TOTAL | J27: =SUM(J19:J26) -> 0 | K27: =D27+G27+J27 -> 3800 | M27: TOTAL | P27: =SUM(P19:P26) -> 1400
A28: JUC | B28: RETAIL PRICE | C28: PCS SOLD | D28: SALES | E28: DISCOUNTED PRICE | F28: PCS SOLD | G28: SALES | H28: SPECIAL DISC. PRICE | I28: PCS SOLD | J28: SALES | K28: TOTAL SALES | L28: TOTALQTY SOLD | M28: PRODUCTION PRICE | N28: 12% Vat | O28: 10% Mark Up | P28: PROFIT
A29: UST OAT Hoodie Jacket | B29: 1450 | C29: 3 | D29: =B29*C29 -> 4350 | E29: 1400 | G29: =E29*F29 -> 0 | H29: 1300 | J29: =H29*I29 -> 0 | K29: =D29+G29+J29 -> 4350 | L29: =C29+F29+I29 -> 3 | M29: 1000 | N29: 120 | O29: 100 | P29: =((B29-M29)*C29)+((E29-M29)*F29)+((H29-M29)*I29) -> 1350
A30: UST OAT MUG | B30: 150 | C30: 13 | D30: =B30*C30 -> 1950 | E30: 140 | G30: =E30*F30 -> 0 | H30: 135 | J30: =H30*I30 -> 0 | K30: =D30+G30+J30 -> 1950 | L30: =C30+F30+I30 -> 13 | M30: 110 | N30: 12 | O30: 10 | P30: =((B30-M30)*C30)+((E30-M30)*F30)+((H30-M30)*I30) -> 520
A31: UST OAT MUG (WE) Inside | B31: 150 | C31: 7 | D31: =B31*C31 -> 1050 | E31: 140 | G31: =E31*F31 -> 0 | H31: 135 | J31: =H31*I31 -> 0 | K31: =D31+G31+J31 -> 1050 | L31: =C31+F31+I31 -> 7 | M31: 100 | N31: 12 | O31: 10 | P31: =((B31-M31)*C31)+((E31-M31)*F31)+((H31-M31)*I31) -> 350
A32: UST OAT T-Shirt | B32: 375 | C32: 1 | D32: =B32*C32 -> 375 | E32: 360 | G32: =E32*F32 -> 0 | H32: 340 | J32: =H32*I32 -> 0 | K32: =D32+G32+J32 -> 375 | L32: =C32+F32+I32 -> 1 | M32: 280 | N32: 33.6 | O32: 28 | P32: =((B32-M32)*C32)+((E32-M32)*F32)+((H32-M32)*I32) -> 95
A33: UST T-Shirt Sports | B33: 430 | C33: 4 | D33: =B33*C33 -> 1720 | E33: 400 | G33: =E33*F33 -> 0 | H33: 350 | J33: =H33*I33 -> 0 | K33: =D33+G33+J33 -> 1720 | L33: =C33+F33+I33 -> 4 | M33: 260 | N33: 31.2 | O33: 26 | P33: =((B33-M33)*C33)+((E33-M33)*F33)+((H33-M33)*I33) -> 680
A34: UST T-Shirt Tiger Pattern | B34: 450 | C34: 4 | D34: =B34*C34 -> 1800 | E34: 430 | G34: =E34*F34 -> 0 | H34: 400 | J34: =H34*I34 -> 0 | K34: =D34+G34+J34 -> 1800 | L34: =C34+F34+I34 -> 4 | M34: 330 | N34: 39.6 | O34: 33 | P34: =((B34-M34)*C34)+((E34-M34)*F34)+((H34-M34)*I34) -> 480
A35: UST Happy Tiger | B35: 450 | C35: 2 | D35: =B35*C35 -> 900 | E35: 400 | G35: =E35*F35 -> 0 | H35: 375 | J35: =H35*I35 -> 0 | K35: =D35+G35+J35 -> 900 | L35: =C35+F35+I35 -> 2 | M35: 280 | N35: 33.6 | O35: 28 | P35: =((B35-M35)*C35)+((E35-M35)*F35)+((H35-M35)*I35) -> 340
A36: OAT Tote Bag (Phased Out) | B36: 220 | D36: =B36*C36 -> 0 | G36: =E36*F36 -> 0 | J36: =H36*I36 -> 0 | K36: =D36+G36+J36 -> 0 | L36: =C36+F36+I36 -> 0 | M36: 120 | P36: =((B36-M36)*C36)+((E36-M36)*F36)+((H36-M36)*I36) -> 0
C37: TOTAL | D37: =SUM(D29:D36) -> 12145 | F37: TOTAL | G37: =SUM(G29:G36) -> 0 | I37: TOTAL | J37: =SUM(J29:J36) -> 0 | K37: =D37+G37+J37 -> 12145 | L37: =SUM(L29:L36) -> 34 | M37: TOTAL | P37: =SUM(P29:P36) -> 3815
A38: USTORE | B38: RETAIL PRICE | C38: PCS SOLD | D38: SALES | E38: DISCOUNTED PRICE | F38: PCS SOLD | G38: SALES | H38: SPECIAL DISC. PRICE | I38: PCS SOLD | J38: SALES | K38: TOTAL SALES | L38: TOTALQTY SOLD | M38: PRODUCTION PRICE | N38: 12% Vat | O38: 10% Mark Up | P38: PROFIT
A39: Auto Umbrella | B39: 250 | D39: =B39*C39 -> 0 | G39: =E39*F39 -> 0 | J39: =H39*I39 -> 0 | K39: =D39+G39+J39 -> 0 | L39: =C39+F39+I39 -> 0 | P39: =((B39-M39)*C39)+((E39-M39)*F39)+((H39-M39)*I39) -> 0
A40: Bag | B40: 250 | D40: =B40*C40 -> 0 | E40: 150 | F40: 26 | G40: =E40*F40 -> 3900 | J40: =H40*I40 -> 0 | K40: =D40+G40+J40 -> 3900 | L40: =C40+F40+I40 -> 26 | P40: =((B40-M40)*C40)+((E40-M40)*F40)+((H40-M40)*I40) -> 3900
A41: Eco Bag CGEEE! | B41: 50 | D41: =B41*C41 -> 0 | E41: 35 | G41: =E41*F41 -> 0 | J41: =H41*I41 -> 0 | K41: =D41+G41+J41 -> 0 | L41: =C41+F41+I41 -> 0 | P41: =((B41-M41)*C41)+((E41-M41)*F41)+((H41-M41)*I41) -> 0
A42: Keychain | B42: 150 | C42: 6 | D42: =B42*C42 -> 900 | E42: 120 | G42: =E42*F42 -> 0 | H42: 75 | J42: =H42*I42 -> 0 | K42: =D42+G42+J42 -> 900 | L42: =C42+F42+I42 -> 6 | P42: =((B42-M42)*C42)+((E42-M42)*F42)+((H42-M42)*I42) -> 900
A43: Kit Set | B43: 800 | D43: =B43*C43 -> 0 | E43: 750 | G43: =E43*F43 -> 0 | H43: 700 | J43: =H43*I43 -> 0 | K43: =D43+G43+J43 -> 0 | L43: =C43+F43+I43 -> 0 | P43: =((B43-M43)*C43)+((E43-M43)*F43)+((H43-M43)*I43) -> 0
A44: Lanyard | B44: 190 | C44: 1 | D44: =B44*C44 -> 190 | E44: 175 | G44: =E44*F44 -> 0 | H44: 150 | J44: =H44*I44 -> 0 | K44: =D44+G44+J44 -> 190 | L44: =C44+F44+I44 -> 1 | M44: 117 | N44: 14.04 | O44: 11.7 | P44: =((B44-M44)*C44)+((E44-M44)*F44)+((H44-M44)*I44) -> 73
A45: Lanyard | B45: 180 | C45: 2 | D45: =B45*C45 -> 360 | E45: 165 | G45: =E45*F45 -> 0 | H45: 140 | J45: =H45*I45 -> 0 | K45: =D45+G45+J45 -> 360 | L45: =C45+F45+I45 -> 2 | M45: 110 | N45: 13.2 | O45: 11 | P45: =((B45-M45)*C45)+((E45-M45)*F45)+((H45-M45)*I45) -> 140
A46: NB | B46: 75 | D46: =B46*C46 -> 0 | G46: =E46*F46 -> 0 | J46: =H46*I46 -> 0 | K46: =D46+G46+J46 -> 0 | L46: =C46+F46+I46 -> 0 | P46: =((B46-M46)*C46)+((E46-M46)*F46)+((H46-M46)*I46) -> 0
A47: NB | B47: 100 | D47: =B47*C47 -> 0 | E47: 80 | G47: =E47*F47 -> 0 | H47: 70 | J47: =H47*I47 -> 0 | K47: =D47+G47+J47 -> 0 | L47: =C47+F47+I47 -> 0 | P47: =((B47-M47)*C47)+((E47-M47)*F47)+((H47-M47)*I47) -> 0
A48: Sash Big | B48: 600 | D48: =B48*C48 -> 0 | E48: 500 | G48: =E48*F48 -> 0 | H48: 400 | J48: =H48*I48 -> 0 | K48: =D48+G48+J48 -> 0 | L48: =C48+F48+I48 -> 0 | P48: =((B48-M48)*C48)+((E48-M48)*F48)+((H48-M48)*I48) -> 0
A49: Sash Small | B49: 150 | C49: 26 | D49: =B49*C49 -> 3900 | E49: 125 | G49: =E49*F49 -> 0 | H49: 100 | J49: =H49*I49 -> 0 | K49: =D49+G49+J49 -> 3900 | L49: =C49+F49+I49 -> 26 | P49: =((B49-M49)*C49)+((E49-M49)*F49)+((H49-M49)*I49) -> 3900
A50: Shabby Hat | B50: 200 | C50: 1 | D50: =B50*C50 -> 200 | E50: 175 | G50: =E50*F50 -> 0 | H50: 150 | J50: =H50*I50 -> 0 | K50: =D50+G50+J50 -> 200 | L50: =C50+F50+I50 -> 1 | P50: =((B50-M50)*C50)+((E50-M50)*F50)+((H50-M50)*I50) -> 200
A51: Tiger Stuff Toy Small Grad | B51: 250 | C51: 2 | D51: =B51*C51 -> 500 | E51: 230 | G51: =E51*F51 -> 0 | H51: 200 | J51: =H51*I51 -> 0 | K51: =D51+G51+J51 -> 500 | L51: =C51+F51+I51 -> 2 | P51: =((B51-M51)*C51)+((E51-M51)*F51)+((H51-M51)*I51) -> 500
A52: Tote Bag CGEEE! | B52: 120 | D52: =B52*C52 -> 0 | E52: 100 | G52: =E52*F52 -> 0 | H52: 80 | J52: =H52*I52 -> 0 | K52: =D52+G52+J52 -> 0 | L52: =C52+F52+I52 -> 0 | P52: =((B52-M52)*C52)+((E52-M52)*F52)+((H52-M52)*I52) -> 0
A53: Tote Bag Canvas White | B53: 160 | C53: 1 | D53: =B53*C53 -> 160 | G53: =E53*F53 -> 0 | J53: =H53*I53 -> 0 | K53: =D53+G53+J53 -> 160 | L53: =C53+F53+I53 -> 1 | P53: =((B53-M53)*C53)+((E53-M53)*F53)+((H53-M53)*I53) -> 160
A54: Tote (One For UST) | B54: 300 | C54: 1 | D54: =B54*C54 -> 300 | E54: 275 | G54: =E54*F54 -> 0 | H54: 250 | I54: 3 | J54: =H54*I54 -> 750 | K54: =D54+G54+J54 -> 1050 | L54: =C54+F54+I54 -> 4 | P54: =((B54-M54)*C54)+((E54-M54)*F54)+((H54-M54)*I54) -> 1050
A55: Tumbler | B55: 150 | D55: =B55*C55 -> 0 | G55: =E55*F55 -> 0 | J55: =H55*I55 -> 0 | K55: =D55+G55+J55 -> 0 | L55: =C55+F55+I55 -> 0 | P55: =((B55-M55)*C55)+((E55-M55)*F55)+((H55-M55)*I55) -> 0
A56: Umb. Cane | B56: 500 | D56: =B56*C56 -> 0 | E56: 450 | G56: =E56*F56 -> 0 | H56: 400 | J56: =H56*I56 -> 0 | K56: =D56+G56+J56 -> 0 | L56: =C56+F56+I56 -> 0 | P56: =((B56-M56)*C56)+((E56-M56)*F56)+((H56-M56)*I56) -> 0
A57: Umb (One For UST) | B57: 350 | C57: 2 | D57: =B57*C57 -> 700 | E57: 300 | G57: =E57*F57 -> 0 | H57: 250 | J57: =H57*I57 -> 0 | K57: =D57+G57+J57 -> 700 | L57: =C57+F57+I57 -> 2 | P57: =((B57-M57)*C57)+((E57-M57)*F57)+((H57-M57)*I57) -> 700
A58: Old Umbrella | B58: 250 | C58: 41 | D58: =B58*C58 -> 10250 | E58: 200 | G58: =E58*F58 -> 0 | H58: 180 | J58: =H58*I58 -> 0 | K58: =D58+G58+J58 -> 10250 | L58: =C58+F58+I58 -> 41
A59: Utensil | B59: 250 | D59: =B59*C59 -> 0 | E59: 200 | G59: =E59*F59 -> 0 | H59: 180 | J59: =H59*I59 -> 0 | K59: =D59+G59+J59 -> 0 | L59: =C59+F59+I59 -> 0
C60: TOTAL | D60: =SUM(D39:D59) -> 17460 | F60: TOTAL | G60: =SUM(G39:G59) -> 3900 | I60: TOTAL | J60: =SUM(J39:J59) -> 750 | K60: =D60+G60+J60 -> 22110 | M60: TOTAL | P60: =SUM(P39:P59) -> 11523
A61: TET AND DARS | B61: RETAIL PRICE | C61: PCS SOLD | D61: SALES | E61: DISCOUNTED PRICE | F61: PCS SOLD | G61: SALES | H61: SPECIAL DISC. PRICE | I61: PCS SOLD | J61: SALES | K61: TOTAL SALES | L61: TOTALQTY SOLD | M61: PRODUCTION PRICE | N61: 12% Vat | O61: 10% Mark Up | P61: PROFIT
A62: Arch | B62: 320 | C62: 12 | D62: =B62*C62 -> 3840 | E62: 300 | G62: =E62*F62 -> 0 | H62: 300 | J62: =H62*I62 -> 0 | K62: =D62+G62+J62 -> 3840 | L62: =C62+F62+I62 -> 12 | M62: 240 | N62: 28.8 | O62: 24 | P62: =((B62-M62)*C62)+((E62-M62)*F62)+((H62-M62)*I62) -> 960
A63: Eco Bag | B63: 80 | D63: =B63*C63 -> 0 | E63: 70 | G63: =E63*F63 -> 0 | H63: 60 | J63: =H63*I63 -> 0 | K63: =D63+G63+J63 -> 0 | L63: =C63+F63+I63 -> 0 | M63: 60 | P63: =((B63-M63)*C63)+((E63-M63)*F63)+((H63-M63)*I63) -> 0
A64: Eco Bag | B64: 130 | D64: =B64*C64 -> 0 | E64: 120 | G64: =E64*F64 -> 0 | H64: 110 | J64: =H64*I64 -> 0 | K64: =D64+G64+J64 -> 0 | L64: =C64+F64+I64 -> 0 | M64: 100 | P64: =((B64-M64)*C64)+((E64-M64)*F64)+((H64-M64)*I64) -> 0
A65: Main Building | B65: 430 | D65: =B65*C65 -> 0 | E65: 430 | G65: =E65*F65 -> 0 | H65: 430 | J65: =H65*I65 -> 0 | K65: =D65+G65+J65 -> 0 | L65: =C65+F65+I65 -> 0 | M65: 350 | N65: 42 | O65: 35 | P65: =((B65-M65)*C65)+((E65-M65)*F65)+((H65-M65)*I65) -> 0
A66: Mug | B66: 170 | D66: =B66*C66 -> 0 | E66: 160 | G66: =E66*F66 -> 0 | H66: 150 | J66: =H66*I66 -> 0 | K66: =D66+G66+J66 -> 0 | L66: =C66+F66+I66 -> 0 | M66: 125 | N66: 15 | O66: 12.5 | P66: =((B66-M66)*C66)+((E66-M66)*F66)+((H66-M66)*I66) -> 0
A67: Notebook | B67: 220 | D67: =B67*C67 -> 0 | G67: =E67*F67 -> 0 | J67: =H67*I67 -> 0 | K67: =D67+G67+J67 -> 0 | L67: =C67+F67+I67 -> 0 | P67: =((B67-M67)*C67)+((E67-M67)*F67)+((H67-M67)*I67) -> 0
A68: Pen | B68: 50 | D68: =B68*C68 -> 0 | G68: =E68*F68 -> 0 | J68: =H68*I68 -> 0 | K68: =D68+G68+J68 -> 0 | L68: =C68+F68+I68 -> 0 | M68: 42 | P68: =((B68-M68)*C68)+((E68-M68)*F68)+((H68-M68)*I68) -> 0
A69: Pen | B69: 25 | D69: =B69*C69 -> 0 | G69: =E69*F69 -> 0 | J69: =H69*I69 -> 0 | K69: =D69+G69+J69 -> 0 | L69: =C69+F69+I69 -> 0 | M69: 20 | P69: =((B69-M69)*C69)+((E69-M69)*F69)+((H69-M69)*I69) -> 0
A70: Sticker | B70: 115 | D70: =B70*C70 -> 0 | E70: 110 | G70: =E70*F70 -> 0 | H70: 105 | J70: =H70*I70 -> 0 | K70: =D70+G70+J70 -> 0 | L70: =C70+F70+I70 -> 0 | M70: 85 | P70: =((B70-M70)*C70)+((E70-M70)*F70)+((H70-M70)*I70) -> 0
A71: Sticker | B71: 20 | D71: =B71*C71 -> 0 | E71: 20 | G71: =E71*F71 -> 0 | H71: 20 | J71: =H71*I71 -> 0 | K71: =D71+G71+J71 -> 0 | L71: =C71+F71+I71 -> 0 | M71: 15 | P71: =((B71-M71)*C71)+((E71-M71)*F71)+((H71-M71)*I71) -> 0
A72: Tote | B72: 230 | D72: =B72*C72 -> 0 | G72: =E72*F72 -> 0 | J72: =H72*I72 -> 0 | K72: =D72+G72+J72 -> 0 | L72: =C72+F72+I72 -> 0 | P72: =((B72-M72)*C72)+((E72-M72)*F72)+((H72-M72)*I72) -> 0
C73: TOTAL | D73: =SUM(D62:D72) -> 3840 | F73: TOTAL | G73: =SUM(G62:G72) -> 0 | I73: TOTAL | J73: =SUM(J62:J72) -> 0 | K73: =D73+G73+J73 -> 3840 | M73: TOTAL | P73: =SUM(P62:P72) -> 960
A74: BLAZE | B74: RETAIL PRICE | C74: PCS SOLD | D74: SALES | E74: DISCOUNTED PRICE | F74: PCS SOLD | G74: SALES | H74: SPECIAL DISC. PRICE | I74: PCS SOLD | J74: SALES | K74: TOTAL SALES | L74: TOTALQTY SOLD | M74: PRODUCTION PRICE | N74: 12% Vat | O74: 10% Mark Up | P74: PROFIT
A75: Crew Neck Shirt | B75: 475 | D75: =B75*C75 -> 0 | E75: 450 | G75: =E75*F75 -> 0 | H75: 430 | J75: =H75*I75 -> 0 | K75: =D75+G75+J75 -> 0 | L75: =C75+F75+I75 -> 0 | M75: 350 | N75: 42 | O75: 35 | P75: =((B75-M75)*C75)+((E75-M75)*F75)+((H75-M75)*I75) -> 0
A76: Polo Shirt | B76: 800 | D76: =B76*C76 -> 0 | E76: 750 | G76: =E76*F76 -> 0 | H76: 700 | J76: =H76*I76 -> 0 | K76: =D76+G76+J76 -> 0 | L76: =C76+F76+I76 -> 0 | M76: 550 | N76: 66 | O76: 55 | P76: =((B76-M76)*C76)+((E76-M76)*F76)+((H76-M76)*I76) -> 0
A77: Socks | B77: 375 | D77: =B77*C77 -> 0 | E77: 350 | G77: =E77*F77 -> 0 | H77: 325 | J77: =H77*I77 -> 0 | K77: =D77+G77+J77 -> 0 | L77: =C77+F77+I77 -> 0 | M77: 250 | N77: 30 | O77: 25 | P77: =((B77-M77)*C77)+((E77-M77)*F77)+((H77-M77)*I77) -> 0
A78: socks set of 3 | B78: 950 | D78: =B78*C78 -> 0 | E78: 900 | G78: =E78*F78 -> 0 | H78: 800 | J78: =H78*I78 -> 0 | K78: =D78+G78+J78 -> 0 | L78: =C78+F78+I78 -> 0 | M78: 750 | N78: 90 | O78: 75 | P78: =((B78-M78)*C78)+((E78-M78)*F78)+((H78-M78)*I78) -> 0
C79: TOTAL | D79: =SUM(D75:D78) -> 0 | F79: TOTAL | G79: =SUM(G75:G78) -> 0 | I79: TOTAL | J79: =SUM(J75:J78) -> 0 | K79: =D79+G79+J79 -> 0 | M79: TOTAL | P79: =SUM(P75:P78) -> 0
A80: VARSITY LIFE STYLE | B80: RETAIL PRICE | C80: PCS SOLD | D80: SALES | E80: DISCOUNTED PRICE | F80: PCS SOLD | G80: SALES | H80: SPECIAL DISC. PRICE | I80: PCS SOLD | J80: SALES | K80: TOTAL SALES | L80: TOTALQTY SOLD | M80: PRODUCTION PRICE | N80: 12% Vat | O80: 10% Mark Up | P80: PROFIT
A81: Baller | B81: 100 | D81: =B81*C81 -> 0 | K81: =D81+G81+J81 -> 0 | L81: =C81+F81+I81 -> 0 | M81: 90
A82: Caps | B82: 800 | C82: 1 | D82: =B82*C82 -> 800 | K82: =D82+G82+J82 -> 800 | L82: =C82+F82+I82 -> 1 | M82: 700
A83: Hoodie | B83: 1750 | D83: =B83*C83 -> 0 | K83: =D83+G83+J83 -> 0 | L83: =C83+F83+I83 -> 0 | M83: 1500
A84: Keychain | B84: 100 | D84: =B84*C84 -> 0 | K84: =D84+G84+J84 -> 0 | L84: =C84+F84+I84 -> 0 | M84: 90
A85: Lanyard | B85: 250 | C85: 1 | D85: =B85*C85 -> 250 | K85: =D85+G85+J85 -> 250 | L85: =C85+F85+I85 -> 1 | M85: 200
A86: Long Sticker | B86: 100 | D86: =B86*C86 -> 0 | K86: =D86+G86+J86 -> 0 | L86: =C86+F86+I86 -> 0 | M86: 90
A87: Oversized Sweatshirt | B87: 1500 | D87: =B87*C87 -> 0 | K87: =D87+G87+J87 -> 0 | L87: =C87+F87+I87 -> 0 | M87: 1300
A88: Scarves | B88: 400 | D88: =B88*C88 -> 0 | K88: =D88+G88+J88 -> 0 | L88: =C88+F88+I88 -> 0 | M88: 350
A89: Shirts | B89: 700 | D89: =B89*C89 -> 0 | K89: =D89+G89+J89 -> 0 | L89: =C89+F89+I89 -> 0 | M89: 600
A90: Sticker Pack | B90: 150 | D90: =B90*C90 -> 0 | K90: =D90+G90+J90 -> 0 | L90: =C90+F90+I90 -> 0 | M90: 130
A91: Varsity Jacket | B91: 2100 | D91: =B91*C91 -> 0 | K91: =D91+G91+J91 -> 0 | L91: =C91+F91+I91 -> 0 | M91: 1900
C92: TOTAL | D92: =SUM(D81:D91) -> 1050 | F92: TOTAL | G92: =SUM(G81:G91) -> 0 | I92: TOTAL | J92: =SUM(J81:J91) -> 0 | K92: =D92+G92+J92 -> 1050 | M92: TOTAL | P92: =SUM(P81:P91) -> 0
A93: MITSUI | B93: RETAIL PRICE | C93: PCS SOLD | D93: SALES | E93: DISCOUNTED PRICE | F93: PCS SOLD | G93: SALES | H93: SPECIAL DISC. PRICE | I93: PCS SOLD | J93: SALES | K93: TOTAL SALES | L93: TOTALQTY SOLD | M93: PRODUCTION PRICE | N93: 12% Vat | O93: 10% Mark Up | P93: PROFIT
A94: Stylus pen | B94: 45 | D94: =B94*C94 -> 0 | E94: 40 | G94: =E94*F94 -> 0 | H94: 25 | J94: =H94*I94 -> 0 | K94: =D94+G94+J94 -> 0 | L94: =C94+F94+I94 -> 0 | M94: 17.36 | N94: 2.08 | O94: 1.74 | P94: =((B94-M94)*C94)+((E94-M94)*F94)+((H94-M94)*I94) -> 0
A95: Retractable | B95: 25 | D95: =B95*C95 -> 0 | E95: 15 | G95: =E95*F95 -> 0 | H95: 20 | J95: =H95*I95 -> 0 | K95: =D95+G95+J95 -> 0 | L95: =C95+F95+I95 -> 0 | M95: 10.08 | N95: 1.21 | O95: 1.01 | P95: =((B95-M95)*C95)+((E95-M95)*F95)+((H95-M95)*I95) -> 0
C96: TOTAL | D96: =SUM(D94+D95) -> 0 | F96: TOTAL | G96: =SUM(G94+G95) -> 0 | I96: TOTAL | J96: =SUM(J94+J95) -> 0 | K96: =D96+G96+J96 -> 0 | M96: TOTAL | P96: =SUM(P94) -> 0
A97: CENTRAL SEMINARY | B97: RETAIL PRICE | C97: PCS SOLD | D97: SALES | E97: DISCOUNTED PRICE | F97: PCS SOLD | G97: SALES | H97: SPECIAL DISC. PRICE | I97: PCS SOLD | J97: SALES | K97: TOTAL SALES | L97: TOTALQTY SOLD | M97: PRODUCTION PRICE | N97: 12% Vat | O97: 10% Mark Up | P97: PROFIT
A98: Subli. Shirt | B98: 550 | C98: 1 | D98: =B98*C98 -> 550 | G98: =E98*F98 -> 0 | J98: =H98*I98 -> 0 | K98: =D98+G98+J98 -> 550 | L98: =C98+F98+I98 -> 1 | M98: 500 | P98: =((B98-M98)*C98)+((E98-M98)*F98)+((H98-M98)*I98) -> 50
C99: GRAND TOTAL | D99: =D17+D27+D37+D60+D73+D79+D96+D98+D92 -> 44825 | F99: GRAND TOTAL | G99: =G17+G27+G37+G60+G73+G79+G96+G98+G92 -> 3900 | I99: GRAND TOTAL | J99: =J17+J27+J37+J60+J73+J79+J96+J98 -> 750 | K99: =D99+G99+J99 -> 49475 | M99: GRAND TOTAL | P99: =P17+P27+P37+P60+P73+P79+P96+P98 -> 19918
C100: TOTAL SALE | E100: =K99 -> 49475 | N100: TOTAL PROFIT | P100: =P99 -> 19918
...

Sheet May 8
A1: DAILY SALES REPORT
A2: 45420
A3: ITEMS | B3: RETAIL PRICE | C3: PCS SOLD | D3: SALES | E3: DISCOUNTED PRICE | F3: PCS SOLD | G3: SALES | H3: SPECIAL DISC. PRICE | I3: PCS SOLD | J3: SALES | K3: TOTAL SALES | L3: TOTALQTY SOLD | M3: PRODUCTION PRICE | N3: 12% Vat | O3: 10% Mark Up | P3: PROFIT
A4: NAPOLIZ
A5: Backpack Bag | B5: 1750 | D5: =B5*C5 -> 0 | E5: 1600 | G5: =E5*F5 -> 0 | H5: 1400 | J5: =H5*I5 -> 0 | K5: =D5+G5+J5 -> 0 | L5: =C5+F5+I5 -> 0 | M5: 840 | N5: 100.8 | O5: 84 | P5: =((B5-M5)*C5)+((E5-M5)*F5)+((H5-M5)*I5) -> 0
A6: Black Tote Bag (Phased Out) | B6: 280 | D6: =B6*C6 -> 0 | G6: =E6*F6 -> 0 | J6: =H6*I6 -> 0 | K6: =D6+G6+J6 -> 0 | L6: =C6+F6+I6 -> 0 | M6: 230 | P6: =((B6-M6)*C6)+((E6-M6)*F6)+((H6-M6)*I6) -> 0
A7: Double Canopy | B7: 639 | D7: =B7*C7 -> 0 | E7: 575 | G7: =E7*F7 -> 0 | H7: 500 | J7: =H7*I7 -> 0 | K7: =D7+G7+J7 -> 0 | L7: =C7+F7+I7 -> 0 | M7: 330 | N7: 39.6 | O7: 33 | P7: =((B7-M7)*C7)+((E7-M7)*F7)+((H7-M7)*I7) -> 0
A8: Laptop Bag | B8: 1450 | D8: =B8*C8 -> 0 | E8: 1400 | G8: =E8*F8 -> 0 | H8: 1250 | J8: =H8*I8 -> 0 | K8: =D8+G8+J8 -> 0 | L8: =C8+F8+I8 -> 0 | M8: 840 | N8: 100.8 | O8: 84 | P8: =((B8-M8)*C8)+((E8-M8)*F8)+((H8-M8)*I8) -> 0
A9: Script Santo Tomas with Tiger Back (B) | B9: 480 | C9: 2 | D9: =B9*C9 -> 960 | E9: 460 | G9: =E9*F9 -> 0 | H9: 450 | J9: =H9*I9 -> 0 | K9: =D9+G9+J9 -> 960 | L9: =C9+F9+I9 -> 2 | M9: 360 | N9: 43.2 | O9: 36 | P9: =((B9-M9)*C9)+((E9-M9)*F9)+((H9-M9)*I9) -> 240
A10: Side Tiger Hoodie | B10: 1480 | C10: 1 | D10: =B10*C10 -> 1480 | E10: 1400 | G10: =E10*F10 -> 0 | H10: 1375 | J10: =H10*I10 -> 0 | K10: =D10+G10+J10 -> 1480 | L10: =C10+F10+I10 -> 1 | M10: 1125 | N10: 135 | O10: 112.5 | P10: =((B10-M10)*C10)+((E10-M10)*F10)+((H10-M10)*I10) -> 355
A11: Sling Bag | B11: 330 | D11: =B11*C11 -> 0 | E11: 320 | G11: =E11*F11 -> 0 | H11: 300 | J11: =H11*I11 -> 0 | K11: =D11+G11+J11 -> 0 | L11: =C11+F11+I11 -> 0 | M11: 260 | N11: 31.2 | O11: 26 | P11: =((B11-M11)*C11)+((E11-M11)*F11)+((H11-M11)*I11) -> 0
A12: Front Tiger Hoodie | B12: 1440 | D12: =B12*C12 -> 0 | E12: 1400 | G12: =E12*F12 -> 0 | H12: 1375 | J12: =H12*I12 -> 0 | K12: =D12+G12+J12 -> 0 | L12: =C12+F12+I12 -> 0 | M12: 1125 | N12: 135 | O12: 112.5 | P12: =((B12-M12)*C12)+((E12-M12)*F12)+((H12-M12)*I12) -> 0
A13: University of Santo Tomas (B) | B13: 450 | C13: 15 | D13: =B13*C13 -> 6750 | E13: 440 | G13: =E13*F13 -> 0 | H13: 425 | J13: =H13*I13 -> 0 | K13: =D13+G13+J13 -> 6750 | L13: =C13+F13+I13 -> 15 | M13: 360 | N13: 43.2 | O13: 36 | P13: =((B13-M13)*C13)+((E13-M13)*F13)+((H13-M13)*I13) -> 1350
A14: UST Tiger Front and Back Graphic (W) | B14: 500 | C14: 1 | D14: =B14*C14 -> 500 | E14: 480 | G14: =E14*F14 -> 0 | H14: 450 | J14: =H14*I14 -> 0 | K14: =D14+G14+J14 -> 500 | L14: =C14+F14+I14 -> 1 | M14: 360 | N14: 43.2 | O14: 36 | P14: =((B14-M14)*C14)+((E14-M14)*F14)+((H14-M14)*I14) -> 140
A15: White Tote Bag | B15: 260 | D15: =B15*C15 -> 0 | E15: 250 | G15: =E15*F15 -> 0 | H15: 240 | J15: =H15*I15 -> 0 | K15: =D15+G15+J15 -> 0 | L15: =C15+F15+I15 -> 0 | M15: 200 | N15: 24 | O15: 20 | P15: =((B15-M15)*C15)+((E15-M15)*F15)+((H15-M15)*I15) -> 0
A16: Wind Breaker | B16: 1650 | C16: 6 | D16: =B16*C16 -> 9900 | E16: 1600 | G16: =E16*F16 -> 0 | H16: 1500 | J16: =H16*I16 -> 0 | K16: =D16+G16+J16 -> 9900 | L16: =C16+F16+I16 -> 6 | M16: 1125 | N16: 135 | O16: 112.5 | P16: =((B16-M16)*C16)+((E16-M16)*F16)+((H16-M16)*I16) -> 3150
C17: TOTAL | D17: =SUM(D5:D16) -> 19590 | F17: TOTAL | G17: =SUM(G5:G16) -> 0 | I17: TOTAL | J17: =SUM(J5:J16) -> 0 | K17: =D17+G17+J17 -> 19590 | M17: TOTAL | P17: =SUM(P5:P16) -> 5235
A18: JYL | B18: RETAIL PRICE | C18: PCS SOLD | D18: SALES | E18: DISCOUNTED PRICE | F18: PCS SOLD | G18: SALES | H18: SPECIAL DISC. PRICE | I18: PCS SOLD | J18: SALES | K18: TOTAL SALES | L18: TOTALQTY SOLD | M18: PRODUCTION PRICE | N18: 12% Vat | O18: 10% Mark Up | P18: PROFIT
A19: GT Shirt | B19: 375 | D19: =B19*C19 -> 0 | E19: 350 | G19: =E19*F19 -> 0 | H19: 325 | J19: =H19*I19 -> 0 | K19: =D19+G19+J19 -> 0 | L19: =C19+F19+I19 -> 0 | M19: 250 | N19: 30 | O19: 25 | P19: =((B19-M19)*C19)+((E19-M19)*F19)+((H19-M19)*I19) -> 0
A20: Jacket | B20: 1900 | C20: 1 | D20: =B20*C20 -> 1900 | E20: 1700 | G20: =E20*F20 -> 0 | H20: 1500 | J20: =H20*I20 -> 0 | K20: =D20+G20+J20 -> 1900 | L20: =C20+F20+I20 -> 1 | M20: 1200 | N20: 144 | O20: 120 | P20: =((B20-M20)*C20)+((E20-M20)*F20)+((H20-M20)*I20) -> 700
A21: Poloshirt 123456 | B21: 860 | D21: =B21*C21 -> 0 | E21: 800 | G21: =E21*F21 -> 0 | H21: 750 | J21: =H21*I21 -> 0 | K21: =D21+G21+J21 -> 0 | L21: =C21+F21+I21 -> 0 | M21: 600 | N21: 72 | O21: 60 | P21: =((B21-M21)*C21)+((E21-M21)*F21)+((H21-M21)*I21) -> 0
A22: VB Jersey w/ sig. (Phased Out) | B22: 2800 | D22: =B22*C22 -> 0 | G22: =E22*F22 -> 0 | J22: =H22*I22 -> 0 | K22: =D22+G22+J22 -> 0 | L22: =C22+F22+I22 -> 0 | M22: 800 | N22: 96 | O22: 80 | P22: =((B22-M22)*C22)+((E22-M22)*F22)+((H22-M22)*I22) -> 0
A23: VB Jersey w/o sig. | B23: 2000 | D23: =B23*C23 -> 0 | E23: 1800 | G23: =E23*F23 -> 0 | H23: 1500 | J23: =H23*I23 -> 0 | K23: =D23+G23+J23 -> 0 | L23: =C23+F23+I23 -> 0 | M23: 800 | P23: =((B23-M23)*C23)+((E23-M23)*F23)+((H23-M23)*I23) -> 0
A24: VB Jersey w/o sig. | B24: 1500 | D24: =B24*C24 -> 0 | E24: 1400 | G24: =E24*F24 -> 0 | H24: 1300 | J24: =H24*I24 -> 0 | K24: =D24+G24+J24 -> 0 | L24: =C24+F24+I24 -> 0 | M24: 800 | P24: =((B24-M24)*C24)+((E24-M24)*F24)+((H24-M24)*I24) -> 0
A25: VB Jersey w/o sig. | B25: 1000 | D25: =B25*C25 -> 0 | E25: 980 | G25: =E25*F25 -> 0 | H25: 950 | J25: =H25*I25 -> 0 | K25: =D25+G25+J25 -> 0 | L25: =C25+F25+I25 -> 0 | M25: 800 | P25: =((B25-M25)*C25)+((E25-M25)*F25)+((H25-M25)*I25) -> 0
A26: VB Jersey with sig. (Phased Out) | B26: 1500 | D26: =B26*C26 -> 0 | G26: =E26*F26 -> 0 | J26: =H26*I26 -> 0 | K26: =D26+G26+J26 -> 0 | L26: =C26+F26+I26 -> 0 | M26: 800 | P26: =((B26-M26)*C26)+((E26-M26)*F26)+((H26-M26)*I26) -> 0
C27: TOTAL | D27: =SUM(D19:D26) -> 1900 | F27: TOTAL | G27: =SUM(G19:G26) -> 0 | I27: TOTAL | J27: =SUM(J19:J26) -> 0 | K27: =D27+G27+J27 -> 1900 | M27: TOTAL | P27: =SUM(P19:P26) -> 700
A28: JUC | B28: RETAIL PRICE | C28: PCS SOLD | D28: SALES | E28: DISCOUNTED PRICE | F28: PCS SOLD | G28: SALES | H28: SPECIAL DISC. PRICE | I28: PCS SOLD | J28: SALES | K28: TOTAL SALES | L28: TOTALQTY SOLD | M28: PRODUCTION PRICE | N28: 12% Vat | O28: 10% Mark Up | P28: PROFIT
A29: UST OAT Hoodie Jacket | B29: 1450 | D29: =B29*C29 -> 0 | E29: 1400 | G29: =E29*F29 -> 0 | H29: 1300 | J29: =H29*I29 -> 0 | K29: =D29+G29+J29 -> 0 | L29: =C29+F29+I29 -> 0 | M29: 1000 | N29: 120 | O29: 100 | P29: =((B29-M29)*C29)+((E29-M29)*F29)+((H29-M29)*I29) -> 0
A30: UST OAT MUG | B30: 150 | C30: 2 | D30: =B30*C30 -> 300 | E30: 140 | G30: =E30*F30 -> 0 | H30: 135 | J30: =H30*I30 -> 0 | K30: =D30+G30+J30 -> 300 | L30: =C30+F30+I30 -> 2 | M30: 110 | N30: 12 | O30: 10 | P30: =((B30-M30)*C30)+((E30-M30)*F30)+((H30-M30)*I30) -> 80
A31: UST OAT MUG (WE) Inside | B31: 150 | C31: 1 | D31: =B31*C31 -> 150 | E31: 140 | G31: =E31*F31 -> 0 | H31: 135 | J31: =H31*I31 -> 0 | K31: =D31+G31+J31 -> 150 | L31: =C31+F31+I31 -> 1 | M31: 100 | N31: 12 | O31: 10 | P31: =((B31-M31)*C31)+((E31-M31)*F31)+((H31-M31)*I31) -> 50
A32: UST OAT T-Shirt | B32: 375 | C32: 2 | D32: =B32*C32 -> 750 | E32: 360 | G32: =E32*F32 -> 0 | H32: 340 | J32: =H32*I32 -> 0 | K32: =D32+G32+J32 -> 750 | L32: =C32+F32+I32 -> 2 | M32: 280 | N32: 33.6 | O32: 28 | P32: =((B32-M32)*C32)+((E32-M32)*F32)+((H32-M32)*I32) -> 190
A33: UST T-Shirt Sports | B33: 430 | C33: 14 | D33: =B33*C33 -> 6020 | E33: 400 | F33: 2 | G33: =E33*F33 -> 800 | H33: 350 | I33: 1 | J33: =H33*I33 -> 350 | K33: =D33+G33+J33 -> 7170 | L33: =C33+F33+I33 -> 17 | M33: 260 | N33: 31.2 | O33: 26 | P33: =((B33-M33)*C33)+((E33-M33)*F33)+((H33-M33)*I33) -> 2750
A34: UST T-Shirt Tiger Pattern | B34: 450 | C34: 14 | D34: =B34*C34 -> 6300 | E34: 430 | G34: =E34*F34 -> 0 | H34: 400 | J34: =H34*I34 -> 0 | K34: =D34+G34+J34 -> 6300 | L34: =C34+F34+I34 -> 14 | M34: 330 | N34: 39.6 | O34: 33 | P34: =((B34-M34)*C34)+((E34-M34)*F34)+((H34-M34)*I34) -> 1680
A35: UST Happy Tiger | B35: 450 | C35: 11 | D35: =B35*C35 -> 4950 | E35: 400 | G35: =E35*F35 -> 0 | H35: 375 | J35: =H35*I35 -> 0 | K35: =D35+G35+J35 -> 4950 | L35: =C35+F35+I35 -> 11 | M35: 280 | N35: 33.6 | O35: 28 | P35: =((B35-M35)*C35)+((E35-M35)*F35)+((H35-M35)*I35) -> 1870
A36: OAT Tote Bag (Phased Out) | B36: 220 | D36: =B36*C36 -> 0 | G36: =E36*F36 -> 0 | J36: =H36*I36 -> 0 | K36: =D36+G36+J36 -> 0 | L36: =C36+F36+I36 -> 0 | M36: 120 | P36: =((B36-M36)*C36)+((E36-M36)*F36)+((H36-M36)*I36) -> 0
C37: TOTAL | D37: =SUM(D29:D36) -> 18470 | F37: TOTAL | G37: =SUM(G29:G36) -> 800 | I37: TOTAL | J37: =SUM(J29:J36) -> 350 | K37: =D37+G37+J37 -> 19620 | M37: TOTAL | P37: =SUM(P29:P36) -> 6620
A38: USTORE | B38: RETAIL PRICE | C38: PCS SOLD | D38: SALES | E38: DISCOUNTED PRICE | F38: PCS SOLD | G38: SALES | H38: SPECIAL DISC. PRICE | I38: PCS SOLD | J38: SALES | K38: TOTAL SALES | L38: TOTALQTY SOLD | M38: PRODUCTION PRICE | N38: 12% Vat | O38: 10% Mark Up | P38: PROFIT
A39: Auto Umbrella | B39: 250 | D39: =B39*C39 -> 0 | G39: =E39*F39 -> 0 | J39: =H39*I39 -> 0 | K39: =D39+G39+J39 -> 0 | L39: =C39+F39+I39 -> 0 | P39: =((B39-M39)*C39)+((E39-M39)*F39)+((H39-M39)*I39) -> 0
A40: Bag | B40: 250 | D40: =B40*C40 -> 0 | E40: 150 | G40: =E40*F40 -> 0 | J40: =H40*I40 -> 0 | K40: =D40+G40+J40 -> 0 | L40: =C40+F40+I40 -> 0 | P40: =((B40-M40)*C40)+((E40-M40)*F40)+((H40-M40)*I40) -> 0
A41: Eco Bag CGEEE! | B41: 50 | D41: =B41*C41 -> 0 | E41: 35 | G41: =E41*F41 -> 0 | J41: =H41*I41 -> 0 | K41: =D41+G41+J41 -> 0 | L41: =C41+F41+I41 -> 0 | P41: =((B41-M41)*C41)+((E41-M41)*F41)+((H41-M41)*I41) -> 0
A42: Keychain | B42: 150 | C42: 10 | D42: =B42*C42 -> 1500 | E42: 120 | G42: =E42*F42 -> 0 | H42: 75 | J42: =H42*I42 -> 0 | K42: =D42+G42+J42 -> 1500 | L42: =C42+F42+I42 -> 10 | P42: =((B42-M42)*C42)+((E42-M42)*F42)+((H42-M42)*I42) -> 1500
A43: Kit Set | B43: 800 | D43: =B43*C43 -> 0 | E43: 750 | G43: =E43*F43 -> 0 | H43: 700 | J43: =H43*I43 -> 0 | K43: =D43+G43+J43 -> 0 | L43: =C43+F43+I43 -> 0 | P43: =((B43-M43)*C43)+((E43-M43)*F43)+((H43-M43)*I43) -> 0
A44: Lanyard | B44: 190 | C44: 6 | D44: =B44*C44 -> 1140 | E44: 175 | G44: =E44*F44 -> 0 | H44: 150 | J44: =H44*I44 -> 0 | K44: =D44+G44+J44 -> 1140 | L44: =C44+F44+I44 -> 6 | M44: 117 | N44: 14.04 | O44: 11.7 | P44: =((B44-M44)*C44)+((E44-M44)*F44)+((H44-M44)*I44) -> 438
A45: Lanyard | B45: 180 | C45: 4 | D45: =B45*C45 -> 720 | E45: 165 | G45: =E45*F45 -> 0 | H45: 140 | J45: =H45*I45 -> 0 | K45: =D45+G45+J45 -> 720 | L45: =C45+F45+I45 -> 4 | M45: 110 | N45: 13.2 | O45: 11 | P45: =((B45-M45)*C45)+((E45-M45)*F45)+((H45-M45)*I45) -> 280
A46: NB | B46: 75 | D46: =B46*C46 -> 0 | G46: =E46*F46 -> 0 | J46: =H46*I46 -> 0 | K46: =D46+G46+J46 -> 0 | L46: =C46+F46+I46 -> 0 | P46: =((B46-M46)*C46)+((E46-M46)*F46)+((H46-M46)*I46) -> 0
A47: NB | B47: 100 | D47: =B47*C47 -> 0 | E47: 80 | G47: =E47*F47 -> 0 | H47: 70 | J47: =H47*I47 -> 0 | K47: =D47+G47+J47 -> 0 | L47: =C47+F47+I47 -> 0 | P47: =((B47-M47)*C47)+((E47-M47)*F47)+((H47-M47)*I47) -> 0
A48: Sash Big | B48: 600 | D48: =B48*C48 -> 0 | E48: 500 | G48: =E48*F48 -> 0 | H48: 400 | J48: =H48*I48 -> 0 | K48: =D48+G48+J48 -> 0 | L48: =C48+F48+I48 -> 0 | P48: =((B48-M48)*C48)+((E48-M48)*F48)+((H48-M48)*I48) -> 0
A49: Sash Small | B49: 150 | D49: =B49*C49 -> 0 | E49: 125 | G49: =E49*F49 -> 0 | H49: 100 | J49: =H49*I49 -> 0 | K49: =D49+G49+J49 -> 0 | L49: =C49+F49+I49 -> 0 | P49: =((B49-M49)*C49)+((E49-M49)*F49)+((H49-M49)*I49) -> 0
A50: Shabby Hat | B50: 200 | D50: =B50*C50 -> 0 | E50: 175 | G50: =E50*F50 -> 0 | H50: 150 | J50: =H50*I50 -> 0 | K50: =D50+G50+J50 -> 0 | L50: =C50+F50+I50 -> 0 | P50: =((B50-M50)*C50)+((E50-M50)*F50)+((H50-M50)*I50) -> 0
A51: Tiger Stuff Toy Small Grad | B51: 250 | C51: 3 | D51: =B51*C51 -> 750 | E51: 230 | G51: =E51*F51 -> 0 | H51: 200 | J51: =H51*I51 -> 0 | K51: =D51+G51+J51 -> 750 | L51: =C51+F51+I51 -> 3 | P51: =((B51-M51)*C51)+((E51-M51)*F51)+((H51-M51)*I51) -> 750
A52: Tote Bag CGEEE! | B52: 120 | D52: =B52*C52 -> 0 | E52: 100 | G52: =E52*F52 -> 0 | H52: 80 | J52: =H52*I52 -> 0 | K52: =D52+G52+J52 -> 0 | L52: =C52+F52+I52 -> 0 | P52: =((B52-M52)*C52)+((E52-M52)*F52)+((H52-M52)*I52) -> 0
A53: Tote Bag Canvas White | B53: 160 | C53: 1 | D53: =B53*C53 -> 160 | G53: =E53*F53 -> 0 | J53: =H53*I53 -> 0 | K53: =D53+G53+J53 -> 160 | L53: =C53+F53+I53 -> 1 | P53: =((B53-M53)*C53)+((E53-M53)*F53)+((H53-M53)*I53) -> 160
A54: Tote (One For UST) | B54: 300 | C54: 1 | D54: =B54*C54 -> 300 | E54: 275 | G54: =E54*F54 -> 0 | H54: 250 | J54: =H54*I54 -> 0 | K54: =D54+G54+J54 -> 300 | L54: =C54+F54+I54 -> 1 | P54: =((B54-M54)*C54)+((E54-M54)*F54)+((H54-M54)*I54) -> 300
A55: Tumbler | B55: 150 | D55: =B55*C55 -> 0 | G55: =E55*F55 -> 0 | J55: =H55*I55 -> 0 | K55: =D55+G55+J55 -> 0 | L55: =C55+F55+I55 -> 0 | P55: =((B55-M55)*C55)+((E55-M55)*F55)+((H55-M55)*I55) -> 0
A56: Umb. Cane | B56: 500 | D56: =B56*C56 -> 0 | E56: 450 | G56: =E56*F56 -> 0 | H56: 400 | J56: =H56*I56 -> 0 | K56: =D56+G56+J56 -> 0 | L56: =C56+F56+I56 -> 0 | P56: =((B56-M56)*C56)+((E56-M56)*F56)+((H56-M56)*I56) -> 0
A57: Umb (One For UST) | B57: 350 | C57: 3 | D57: =B57*C57 -> 1050 | E57: 300 | G57: =E57*F57 -> 0 | H57: 250 | J57: =H57*I57 -> 0 | K57: =D57+G57+J57 -> 1050 | L57: =C57+F57+I57 -> 3 | P57: =((B57-M57)*C57)+((E57-M57)*F57)+((H57-M57)*I57) -> 1050
A58: Old Umbrella | B58: 250 | D58: =B58*C58 -> 0 | E58: 200 | G58: =E58*F58 -> 0 | H58: 180 | J58: =H58*I58 -> 0 | K58: =D58+G58+J58 -> 0 | L58: =C58+F58+I58 -> 0
A59: Utensil | B59: 250 | D59: =B59*C59 -> 0 | E59: 200 | G59: =E59*F59 -> 0 | H59: 180 | J59: =H59*I59 -> 0 | K59: =D59+G59+J59 -> 0 | L59: =C59+F59+I59 -> 0
C60: TOTAL | D60: =SUM(D39:D59) -> 5620 | F60: TOTAL | G60: =SUM(G39:G59) -> 0 | I60: TOTAL | J60: =SUM(J39:J59) -> 0 | K60: =D60+G60+J60 -> 5620 | M60: TOTAL | P60: =SUM(P39:P59) -> 4478
A61: TET AND DARS | B61: RETAIL PRICE | C61: PCS SOLD | D61: SALES | E61: DISCOUNTED PRICE | F61: PCS SOLD | G61: SALES | H61: SPECIAL DISC. PRICE | I61: PCS SOLD | J61: SALES | K61: TOTAL SALES | L61: TOTALQTY SOLD | M61: PRODUCTION PRICE | N61: 12% Vat | O61: 10% Mark Up | P61: PROFIT
A62: Arch | B62: 320 | C62: 3 | D62: =B62*C62 -> 960 | E62: 300 | G62: =E62*F62 -> 0 | H62: 300 | J62: =H62*I62 -> 0 | K62: =D62+G62+J62 -> 960 | L62: =C62+F62+I62 -> 3 | M62: 240 | N62: 28.8 | O62: 24 | P62: =((B62-M62)*C62)+((E62-M62)*F62)+((H62-M62)*I62) -> 240
A63: Eco Bag | B63: 80 | C63: 2 | D63: =B63*C63 -> 160 | E63: 70 | G63: =E63*F63 -> 0 | H63: 60 | J63: =H63*I63 -> 0 | K63: =D63+G63+J63 -> 160 | L63: =C63+F63+I63 -> 2 | M63: 60 | P63: =((B63-M63)*C63)+((E63-M63)*F63)+((H63-M63)*I63) -> 40
A64: Eco Bag | B64: 130 | D64: =B64*C64 -> 0 | E64: 120 | G64: =E64*F64 -> 0 | H64: 110 | J64: =H64*I64 -> 0 | K64: =D64+G64+J64 -> 0 | L64: =C64+F64+I64 -> 0 | M64: 100 | P64: =((B64-M64)*C64)+((E64-M64)*F64)+((H64-M64)*I64) -> 0
A65: Main Building | B65: 430 | D65: =B65*C65 -> 0 | E65: 430 | G65: =E65*F65 -> 0 | H65: 430 | J65: =H65*I65 -> 0 | K65: =D65+G65+J65 -> 0 | L65: =C65+F65+I65 -> 0 | M65: 350 | N65: 42 | O65: 35 | P65: =((B65-M65)*C65)+((E65-M65)*F65)+((H65-M65)*I65) -> 0
A66: Mug | B66: 170 | D66: =B66*C66 -> 0 | E66: 160 | G66: =E66*F66 -> 0 | H66: 150 | J66: =H66*I66 -> 0 | K66: =D66+G66+J66 -> 0 | L66: =C66+F66+I66 -> 0 | M66: 125 | N66: 15 | O66: 12.5 | P66: =((B66-M66)*C66)+((E66-M66)*F66)+((H66-M66)*I66) -> 0
A67: Notebook | B67: 220 | D67: =B67*C67 -> 0 | G67: =E67*F67 -> 0 | J67: =H67*I67 -> 0 | K67: =D67+G67+J67 -> 0 | L67: =C67+F67+I67 -> 0 | P67: =((B67-M67)*C67)+((E67-M67)*F67)+((H67-M67)*I67) -> 0
A68: Pen | B68: 50 | D68: =B68*C68 -> 0 | G68: =E68*F68 -> 0 | J68: =H68*I68 -> 0 | K68: =D68+G68+J68 -> 0 | L68: =C68+F68+I68 -> 0 | M68: 42 | P68: =((B68-M68)*C68)+((E68-M68)*F68)+((H68-M68)*I68) -> 0
A69: Pen | B69: 25 | D69: =B69*C69 -> 0 | G69: =E69*F69 -> 0 | J69: =H69*I69 -> 0 | K69: =D69+G69+J69 -> 0 | L69: =C69+F69+I69 -> 0 | M69: 20 | P69: =((B69-M69)*C69)+((E69-M69)*F69)+((H69-M69)*I69) -> 0
A70: Sticker | B70: 115 | C70: 2 | D70: =B70*C70 -> 230 | E70: 110 | G70: =E70*F70 -> 0 | H70: 105 | J70: =H70*I70 -> 0 | K70: =D70+G70+J70 -> 230 | L70: =C70+F70+I70 -> 2 | M70: 85 | P70: =((B70-M70)*C70)+((E70-M70)*F70)+((H70-M70)*I70) -> 60
A71: Sticker | B71: 20 | D71: =B71*C71 -> 0 | E71: 20 | G71: =E71*F71 -> 0 | H71: 20 | J71: =H71*I71 -> 0 | K71: =D71+G71+J71 -> 0 | L71: =C71+F71+I71 -> 0 | M71: 15 | P71: =((B71-M71)*C71)+((E71-M71)*F71)+((H71-M71)*I71) -> 0
A72: Tote | B72: 230 | D72: =B72*C72 -> 0 | G72: =E72*F72 -> 0 | J72: =H72*I72 -> 0 | K72: =D72+G72+J72 -> 0 | L72: =C72+F72+I72 -> 0 | P72: =((B72-M72)*C72)+((E72-M72)*F72)+((H72-M72)*I72) -> 0
C73: TOTAL | D73: =SUM(D62:D72) -> 1350 | F73: TOTAL | G73: =SUM(G62:G72) -> 0 | I73: TOTAL | J73: =SUM(J62:J72) -> 0 | K73: =D73+G73+J73 -> 1350 | M73: TOTAL | P73: =SUM(P62:P72) -> 340
A74: BLAZE | B74: RETAIL PRICE | C74: PCS SOLD | D74: SALES | E74: DISCOUNTED PRICE | F74: PCS SOLD | G74: SALES | H74: SPECIAL DISC. PRICE | I74: PCS SOLD | J74: SALES | K74: TOTAL SALES | L74: TOTALQTY SOLD | M74: PRODUCTION PRICE | N74: 12% Vat | O74: 10% Mark Up | P74: PROFIT
A75: Crew Neck Shirt | B75: 475 | D75: =B75*C75 -> 0 | E75: 450 | G75: =E75*F75 -> 0 | H75: 430 | J75: =H75*I75 -> 0 | K75: =D75+G75+J75 -> 0 | L75: =C75+F75+I75 -> 0 | M75: 350 | N75: 42 | O75: 35 | P75: =((B75-M75)*C75)+((E75-M75)*F75)+((H75-M75)*I75) -> 0
A76: Polo Shirt | B76: 800 | C76: 1 | D76: =B76*C76 -> 800 | E76: 750 | G76: =E76*F76 -> 0 | H76: 700 | J76: =H76*I76 -> 0 | K76: =D76+G76+J76 -> 800 | L76: =C76+F76+I76 -> 1 | M76: 550 | N76: 66 | O76: 55 | P76: =((B76-M76)*C76)+((E76-M76)*F76)+((H76-M76)*I76) -> 250
A77: Socks | B77: 375 | D77: =B77*C77 -> 0 | E77: 350 | G77: =E77*F77 -> 0 | H77: 325 | J77: =H77*I77 -> 0 | K77: =D77+G77+J77 -> 0 | L77: =C77+F77+I77 -> 0 | M77: 250 | N77: 30 | O77: 25 | P77: =((B77-M77)*C77)+((E77-M77)*F77)+((H77-M77)*I77) -> 0
A78: socks set of 3 | B78: 950 | D78: =B78*C78 -> 0 | E78: 900 | G78: =E78*F78 -> 0 | H78: 800 | J78: =H78*I78 -> 0 | K78: =D78+G78+J78 -> 0 | L78: =C78+F78+I78 -> 0 | M78: 750 | N78: 90 | O78: 75 | P78: =((B78-M78)*C78)+((E78-M78)*F78)+((H78-M78)*I78) -> 0
C79: TOTAL | D79: =SUM(D75:D78) -> 800 | F79: TOTAL | G79: =SUM(G75:G78) -> 0 | I79: TOTAL | J79: =SUM(J75:J78) -> 0 | K79: =D79+G79+J79 -> 800 | M79: TOTAL | P79: =SUM(P75:P78) -> 250
A80: VARSITY LIFE STYLE | B80: RETAIL PRICE | C80: PCS SOLD | D80: SALES | E80: DISCOUNTED PRICE | F80: PCS SOLD | G80: SALES | H80: SPECIAL DISC. PRICE | I80: PCS SOLD | J80: SALES | K80: TOTAL SALES | L80: TOTALQTY SOLD | M80: PRODUCTION PRICE | N80: 12% Vat | O80: 10% Mark Up | P80: PROFIT
A81: Baller | B81: 100 | C81: 5 | D81: =B81*C81 -> 500 | K81: =D81+G81+J81 -> 500 | L81: =C81+F81+I81 -> 5 | M81: 90
A82: Caps | B82: 800 | D82: =B82*C82 -> 0 | K82: =D82+G82+J82 -> 0 | L82: =C82+F82+I82 -> 0 | M82: 700
A83: Hoodie | B83: 1750 | D83: =B83*C83 -> 0 | K83: =D83+G83+J83 -> 0 | L83: =C83+F83+I83 -> 0 | M83: 1500
A84: Keychain | B84: 100 | D84: =B84*C84 -> 0 | K84: =D84+G84+J84 -> 0 | L84: =C84+F84+I84 -> 0 | M84: 90
A85: Lanyard | B85: 250 | C85: 3 | D85: =B85*C85 -> 750 | K85: =D85+G85+J85 -> 750 | L85: =C85+F85+I85 -> 3 | M85: 200
A86: Long Sticker | B86: 100 | D86: =B86*C86 -> 0 | K86: =D86+G86+J86 -> 0 | L86: =C86+F86+I86 -> 0 | M86: 90
A87: Oversized Sweatshirt | B87: 1500 | D87: =B87*C87 -> 0 | K87: =D87+G87+J87 -> 0 | L87: =C87+F87+I87 -> 0 | M87: 1300
A88: Scarves | B88: 400 | D88: =B88*C88 -> 0 | K88: =D88+G88+J88 -> 0 | L88: =C88+F88+I88 -> 0 | M88: 350
A89: Shirts | B89: 700 | D89: =B89*C89 -> 0 | K89: =D89+G89+J89 -> 0 | L89: =C89+F89+I89 -> 0 | M89: 600
A90: Sticker Pack | B90: 150 | D90: =B90*C90 -> 0 | K90: =D90+G90+J90 -> 0 | L90: =C90+F90+I90 -> 0 | M90: 130
A91: Varsity Jacket | B91: 2100 | D91: =B91*C91 -> 0 | K91: =D91+G91+J91 -> 0 | L91: =C91+F91+I91 -> 0 | M91: 1900
C92: TOTAL | D92: =SUM(D81:D91) -> 1250 | F92: TOTAL | G92: =SUM(G81:G91) -> 0 | I92: TOTAL | J92: =SUM(J81:J91) -> 0 | K92: =D92+G92+J92 -> 1250 | M92: TOTAL | P92: =SUM(P81:P91) -> 0
A93: MITSUI | B93: RETAIL PRICE | C93: PCS SOLD | D93: SALES | E93: DISCOUNTED PRICE | F93: PCS SOLD | G93: SALES | H93: SPECIAL DISC. PRICE | I93: PCS SOLD | J93: SALES | K93: TOTAL SALES | L93: TOTALQTY SOLD | M93: PRODUCTION PRICE | N93: 12% Vat | O93: 10% Mark Up | P93: PROFIT
A94: Stylus pen | B94: 45 | D94: =B94*C94 -> 0 | E94: 40 | G94: =E94*F94 -> 0 | H94: 25 | J94: =H94*I94 -> 0 | K94: =D94+G94+J94 -> 0 | L94: =C94+F94+I94 -> 0 | M94: 17.36 | N94: 2.08 | O94: 1.74 | P94: =((B94-M94)*C94)+((E94-M94)*F94)+((H94-M94)*I94) -> 0
A95: Retractable | B95: 25 | D95: =B95*C95 -> 0 | E95: 15 | G95: =E95*F95 -> 0 | H95: 20 | J95: =H95*I95 -> 0 | K95: =D95+G95+J95 -> 0 | L95: =C95+F95+I95 -> 0 | M95: 10.08 | N95: 1.21 | O95: 1.01 | P95: =((B95-M95)*C95)+((E95-M95)*F95)+((H95-M95)*I95) -> 0
C96: TOTAL | D96: =SUM(D94+D95) -> 0 | F96: TOTAL | G96: =SUM(G94+G95) -> 0 | I96: TOTAL | J96: =SUM(J94+J95) -> 0 | K96: =D96+G96+J96 -> 0 | M96: TOTAL | P96: =SUM(P94) -> 0
A97: CENTRAL SEMINARY | B97: RETAIL PRICE | C97: PCS SOLD | D97: SALES | E97: DISCOUNTED PRICE | F97: PCS SOLD | G97: SALES | H97: SPECIAL DISC. PRICE | I97: PCS SOLD | J97: SALES | K97: TOTAL SALES | L97: TOTALQTY SOLD | M97: PRODUCTION PRICE | N97: 12% Vat | O97: 10% Mark Up | P97: PROFIT
A98: Subli. Shirt | B98: 550 | C98: 8 | D98: =B98*C98 -> 4400 | G98: =E98*F98 -> 0 | J98: =H98*I98 -> 0 | K98: =D98+G98+J98 -> 4400 | L98: =C98+F98+I98 -> 8 | M98: 500 | P98: =((B98-M98)*C98)+((E98-M98)*F98)+((H98-M98)*I98) -> 400
C99: GRAND TOTAL | D99: =D17+D27+D37+D60+D73+D79+D96+D98+D92 -> 53380 | F99: GRAND TOTAL | G99: =G17+G27+G37+G60+G73+G79+G96+G98+G92 -> 800 | I99: GRAND TOTAL | J99: =J17+J27+J37+J60+J73+J79+J96+J98 -> 350 | K99: =D99+G99+J99 -> 54530 | M99: GRAND TOTAL | P99: =P17+P27+P37+P60+P73+P79+P96+P98 -> 18023
C100: TOTAL SALE | E100: =K99 -> 54530 | N100: TOTAL PROFIT | P100: =P99 -> 18023
...

Sheet May 9
A1: DAILY SALES REPORT
A2: 45421
A3: ITEMS | B3: RETAIL PRICE | C3: PCS SOLD | D3: SALES | E3: DISCOUNTED PRICE | F3: PCS SOLD | G3: SALES | H3: SPECIAL DISC. PRICE | I3: PCS SOLD | J3: SALES | K3: TOTAL SALES | L3: TOTALQTY SOLD | M3: PRODUCTION PRICE | N3: 12% Vat | O3: 10% Mark Up | P3: PROFIT
A4: NAPOLIZ
A5: Backpack Bag | B5: 1750 | D5: =B5*C5 -> 0 | E5: 1600 | G5: =E5*F5 -> 0 | H5: 1400 | J5: =H5*I5 -> 0 | K5: =D5+G5+J5 -> 0 | L5: =C5+F5+I5 -> 0 | M5: 840 | N5: 100.8 | O5: 84 | P5: =((B5-M5)*C5)+((E5-M5)*F5)+((H5-M5)*I5) -> 0
A6: Black Tote Bag (Phased Out) | B6: 280 | D6: =B6*C6 -> 0 | G6: =E6*F6 -> 0 | J6: =H6*I6 -> 0 | K6: =D6+G6+J6 -> 0 | L6: =C6+F6+I6 -> 0 | M6: 230 | P6: =((B6-M6)*C6)+((E6-M6)*F6)+((H6-M6)*I6) -> 0
A7: Double Canopy | B7: 639 | D7: =B7*C7 -> 0 | E7: 575 | G7: =E7*F7 -> 0 | H7: 500 | J7: =H7*I7 -> 0 | K7: =D7+G7+J7 -> 0 | L7: =C7+F7+I7 -> 0 | M7: 330 | N7: 39.6 | O7: 33 | P7: =((B7-M7)*C7)+((E7-M7)*F7)+((H7-M7)*I7) -> 0
A8: Laptop Bag | B8: 1450 | D8: =B8*C8 -> 0 | E8: 1400 | G8: =E8*F8 -> 0 | H8: 1250 | J8: =H8*I8 -> 0 | K8: =D8+G8+J8 -> 0 | L8: =C8+F8+I8 -> 0 | M8: 840 | N8: 100.8 | O8: 84 | P8: =((B8-M8)*C8)+((E8-M8)*F8)+((H8-M8)*I8) -> 0
A9: Script Santo Tomas with Tiger Back (B) | B9: 480 | C9: 3 | D9: =B9*C9 -> 1440 | E9: 460 | G9: =E9*F9 -> 0 | H9: 450 | I9: 1 | J9: =H9*I9 -> 450 | K9: =D9+G9+J9 -> 1890 | L9: =C9+F9+I9 -> 4 | M9: 360 | N9: 43.2 | O9: 36 | P9: =((B9-M9)*C9)+((E9-M9)*F9)+((H9-M9)*I9) -> 450
A10: Side Tiger Hoodie | B10: 1480 | D10: =B10*C10 -> 0 | E10: 1400 | G10: =E10*F10 -> 0 | H10: 1375 | J10: =H10*I10 -> 0 | K10: =D10+G10+J10 -> 0 | L10: =C10+F10+I10 -> 0 | M10: 1125 | N10: 135 | O10: 112.5 | P10: =((B10-M10)*C10)+((E10-M10)*F10)+((H10-M10)*I10) -> 0
A11: Sling Bag | B11: 330 | D11: =B11*C11 -> 0 | E11: 320 | G11: =E11*F11 -> 0 | H11: 300 | J11: =H11*I11 -> 0 | K11: =D11+G11+J11 -> 0 | L11: =C11+F11+I11 -> 0 | M11: 260 | N11: 31.2 | O11: 26 | P11: =((B11-M11)*C11)+((E11-M11)*F11)+((H11-M11)*I11) -> 0
A12: Front Tiger Hoodie | B12: 1440 | C12: 1 | D12: =B12*C12 -> 1440 | E12: 1400 | G12: =E12*F12 -> 0 | H12: 1375 | J12: =H12*I12 -> 0 | K12: =D12+G12+J12 -> 1440 | L12: =C12+F12+I12 -> 1 | M12: 1125 | N12: 135 | O12: 112.5 | P12: =((B12-M12)*C12)+((E12-M12)*F12)+((H12-M12)*I12) -> 315
A13: University of Santo Tomas (B) | B13: 450 | C13: 6 | D13: =B13*C13 -> 2700 | E13: 440 | G13: =E13*F13 -> 0 | H13: 425 | J13: =H13*I13 -> 0 | K13: =D13+G13+J13 -> 2700 | L13: =C13+F13+I13 -> 6 | M13: 360 | N13: 43.2 | O13: 36 | P13: =((B13-M13)*C13)+((E13-M13)*F13)+((H13-M13)*I13) -> 540
A14: UST Tiger Front and Back Graphic (W) | B14: 500 | C14: 7 | D14: =B14*C14 -> 3500 | E14: 480 | G14: =E14*F14 -> 0 | H14: 450 | J14: =H14*I14 -> 0 | K14: =D14+G14+J14 -> 3500 | L14: =C14+F14+I14 -> 7 | M14: 360 | N14: 43.2 | O14: 36 | P14: =((B14-M14)*C14)+((E14-M14)*F14)+((H14-M14)*I14) -> 980
A15: White Tote Bag | B15: 260 | D15: =B15*C15 -> 0 | E15: 250 | G15: =E15*F15 -> 0 | H15: 240 | J15: =H15*I15 -> 0 | K15: =D15+G15+J15 -> 0 | L15: =C15+F15+I15 -> 0 | M15: 200 | N15: 24 | O15: 20 | P15: =((B15-M15)*C15)+((E15-M15)*F15)+((H15-M15)*I15) -> 0
A16: Wind Breaker | B16: 1650 | C16: 1 | D16: =B16*C16 -> 1650 | E16: 1600 | G16: =E16*F16 -> 0 | H16: 1500 | J16: =H16*I16 -> 0 | K16: =D16+G16+J16 -> 1650 | L16: =C16+F16+I16 -> 1 | M16: 1125 | N16: 135 | O16: 112.5 | P16: =((B16-M16)*C16)+((E16-M16)*F16)+((H16-M16)*I16) -> 525
C17: TOTAL | D17: =SUM(D5:D16) -> 10730 | F17: TOTAL | G17: =SUM(G5:G16) -> 0 | I17: TOTAL | J17: =SUM(J5:J16) -> 450 | K17: =D17+G17+J17 -> 11180 | M17: TOTAL | P17: =SUM(P5:P16) -> 2810
A18: JYL | B18: RETAIL PRICE | C18: PCS SOLD | D18: SALES | E18: DISCOUNTED PRICE | F18: PCS SOLD | G18: SALES | H18: SPECIAL DISC. PRICE | I18: PCS SOLD | J18: SALES | K18: TOTAL SALES | L18: TOTALQTY SOLD | M18: PRODUCTION PRICE | N18: 12% Vat | O18: 10% Mark Up | P18: PROFIT
A19: GT Shirt | B19: 375 | D19: =B19*C19 -> 0 | E19: 350 | G19: =E19*F19 -> 0 | H19: 325 | J19: =H19*I19 -> 0 | K19: =D19+G19+J19 -> 0 | L19: =C19+F19+I19 -> 0 | M19: 250 | N19: 30 | O19: 25 | P19: =((B19-M19)*C19)+((E19-M19)*F19)+((H19-M19)*I19) -> 0
A20: Jacket | B20: 1900 | C20: 4 | D20: =B20*C20 -> 7600 | E20: 1700 | G20: =E20*F20 -> 0 | H20: 1500 | J20: =H20*I20 -> 0 | K20: =D20+G20+J20 -> 7600 | L20: =C20+F20+I20 -> 4 | M20: 1200 | N20: 144 | O20: 120 | P20: =((B20-M20)*C20)+((E20-M20)*F20)+((H20-M20)*I20) -> 2800
A21: Poloshirt 123456 | B21: 860 | C21: 1 | D21: =B21*C21 -> 860 | E21: 800 | G21: =E21*F21 -> 0 | H21: 750 | J21: =H21*I21 -> 0 | K21: =D21+G21+J21 -> 860 | L21: =C21+F21+I21 -> 1 | M21: 600 | N21: 72 | O21: 60 | P21: =((B21-M21)*C21)+((E21-M21)*F21)+((H21-M21)*I21) -> 260
A22: VB Jersey w/ sig. (Phased Out) | B22: 2800 | D22: =B22*C22 -> 0 | G22: =E22*F22 -> 0 | J22: =H22*I22 -> 0 | K22: =D22+G22+J22 -> 0 | L22: =C22+F22+I22 -> 0 | M22: 800 | N22: 96 | O22: 80 | P22: =((B22-M22)*C22)+((E22-M22)*F22)+((H22-M22)*I22) -> 0
A23: VB Jersey w/o sig. | B23: 2000 | D23: =B23*C23 -> 0 | E23: 1800 | G23: =E23*F23 -> 0 | H23: 1500 | J23: =H23*I23 -> 0 | K23: =D23+G23+J23 -> 0 | L23: =C23+F23+I23 -> 0 | M23: 800 | P23: =((B23-M23)*C23)+((E23-M23)*F23)+((H23-M23)*I23) -> 0
A24: VB Jersey w/o sig. | B24: 1500 | C24: 2 | D24: =B24*C24 -> 3000 | E24: 1400 | G24: =E24*F24 -> 0 | H24: 1300 | J24: =H24*I24 -> 0 | K24: =D24+G24+J24 -> 3000 | L24: =C24+F24+I24 -> 2 | M24: 800 | P24: =((B24-M24)*C24)+((E24-M24)*F24)+((H24-M24)*I24) -> 1400
A25: VB Jersey w/o sig. | B25: 1000 | D25: =B25*C25 -> 0 | E25: 980 | G25: =E25*F25 -> 0 | H25: 950 | J25: =H25*I25 -> 0 | K25: =D25+G25+J25 -> 0 | L25: =C25+F25+I25 -> 0 | M25: 800 | P25: =((B25-M25)*C25)+((E25-M25)*F25)+((H25-M25)*I25) -> 0
A26: VB Jersey with sig. (Phased Out) | B26: 1500 | D26: =B26*C26 -> 0 | G26: =E26*F26 -> 0 | J26: =H26*I26 -> 0 | K26: =D26+G26+J26 -> 0 | L26: =C26+F26+I26 -> 0 | M26: 800 | P26: =((B26-M26)*C26)+((E26-M26)*F26)+((H26-M26)*I26) -> 0
C27: TOTAL | D27: =SUM(D19:D26) -> 11460 | F27: TOTAL | G27: =SUM(G19:G26) -> 0 | I27: TOTAL | J27: =SUM(J19:J26) -> 0 | K27: =D27+G27+J27 -> 11460 | M27: TOTAL | P27: =SUM(P19:P26) -> 4460
A28: JUC | B28: RETAIL PRICE | C28: PCS SOLD | D28: SALES | E28: DISCOUNTED PRICE | F28: PCS SOLD | G28: SALES | H28: SPECIAL DISC. PRICE | I28: PCS SOLD | J28: SALES | K28: TOTAL SALES | L28: TOTALQTY SOLD | M28: PRODUCTION PRICE | N28: 12% Vat | O28: 10% Mark Up | P28: PROFIT
A29: UST OAT Hoodie Jacket | B29: 1450 | C29: 1 | D29: =B29*C29 -> 1450 | E29: 1400 | G29: =E29*F29 -> 0 | H29: 1300 | I29: 1 | J29: =H29*I29 -> 1300 | K29: =D29+G29+J29 -> 2750 | L29: =C29+F29+I29 -> 2 | M29: 1000 | N29: 120 | O29: 100 | P29: =((B29-M29)*C29)+((E29-M29)*F29)+((H29-M29)*I29) -> 750
A30: UST OAT MUG | B30: 150 | C30: 2 | D30: =B30*C30 -> 300 | E30: 140 | G30: =E30*F30 -> 0 | H30: 135 | J30: =H30*I30 -> 0 | K30: =D30+G30+J30 -> 300 | L30: =C30+F30+I30 -> 2 | M30: 110 | N30: 12 | O30: 10 | P30: =((B30-M30)*C30)+((E30-M30)*F30)+((H30-M30)*I30) -> 80
A31: UST OAT MUG (WE) Inside | B31: 150 | C31: 1 | D31: =B31*C31 -> 150 | E31: 140 | G31: =E31*F31 -> 0 | H31: 135 | J31: =H31*I31 -> 0 | K31: =D31+G31+J31 -> 150 | L31: =C31+F31+I31 -> 1 | M31: 100 | N31: 12 | O31: 10 | P31: =((B31-M31)*C31)+((E31-M31)*F31)+((H31-M31)*I31) -> 50
A32: UST OAT T-Shirt | B32: 375 | D32: =B32*C32 -> 0 | E32: 360 | G32: =E32*F32 -> 0 | H32: 340 | J32: =H32*I32 -> 0 | K32: =D32+G32+J32 -> 0 | L32: =C32+F32+I32 -> 0 | M32: 280 | N32: 33.6 | O32: 28 | P32: =((B32-M32)*C32)+((E32-M32)*F32)+((H32-M32)*I32) -> 0
A33: UST T-Shirt Sports | B33: 430 | C33: 15 | D33: =B33*C33 -> 6450 | E33: 400 | F33: 1 | G33: =E33*F33 -> 400 | H33: 350 | J33: =H33*I33 -> 0 | K33: =D33+G33+J33 -> 6850 | L33: =C33+F33+I33 -> 16 | M33: 260 | N33: 31.2 | O33: 26 | P33: =((B33-M33)*C33)+((E33-M33)*F33)+((H33-M33)*I33) -> 2690
A34: UST T-Shirt Tiger Pattern | B34: 450 | C34: 12 | D34: =B34*C34 -> 5400 | E34: 430 | G34: =E34*F34 -> 0 | H34: 400 | J34: =H34*I34 -> 0 | K34: =D34+G34+J34 -> 5400 | L34: =C34+F34+I34 -> 12 | M34: 330 | N34: 39.6 | O34: 33 | P34: =((B34-M34)*C34)+((E34-M34)*F34)+((H34-M34)*I34) -> 1440
A35: UST Happy Tiger | B35: 450 | C35: 14 | D35: =B35*C35 -> 6300 | E35: 400 | G35: =E35*F35 -> 0 | H35: 350 | I35: 1 | J35: =H35*I35 -> 350 | K35: =D35+G35+J35 -> 6650 | L35: =C35+F35+I35 -> 15 | M35: 280 | N35: 33.6 | O35: 28 | P35: =((B35-M35)*C35)+((E35-M35)*F35)+((H35-M35)*I35) -> 2450
A36: OAT Tote Bag (Phased Out) | B36: 220 | D36: =B36*C36 -> 0 | G36: =E36*F36 -> 0 | J36: =H36*I36 -> 0 | K36: =D36+G36+J36 -> 0 | L36: =C36+F36+I36 -> 0 | M36: 120 | P36: =((B36-M36)*C36)+((E36-M36)*F36)+((H36-M36)*I36) -> 0
C37: TOTAL | D37: =SUM(D29:D36) -> 20050 | F37: TOTAL | G37: =SUM(G29:G36) -> 400 | I37: TOTAL | J37: =SUM(J29:J36) -> 1650 | K37: =D37+G37+J37 -> 22100 | M37: TOTAL | P37: =SUM(P29:P36) -> 7460
A38: USTORE | B38: RETAIL PRICE | C38: PCS SOLD | D38: SALES | E38: DISCOUNTED PRICE | F38: PCS SOLD | G38: SALES | H38: SPECIAL DISC. PRICE | I38: PCS SOLD | J38: SALES | K38: TOTAL SALES | L38: TOTALQTY SOLD | M38: PRODUCTION PRICE | N38: 12% Vat | O38: 10% Mark Up | P38: PROFIT
A39: Auto Umbrella | B39: 250 | D39: =B39*C39 -> 0 | G39: =E39*F39 -> 0 | J39: =H39*I39 -> 0 | K39: =D39+G39+J39 -> 0 | L39: =C39+F39+I39 -> 0 | P39: =((B39-M39)*C39)+((E39-M39)*F39)+((H39-M39)*I39) -> 0
A40: Bag | B40: 250 | D40: =B40*C40 -> 0 | E40: 150 | G40: =E40*F40 -> 0 | J40: =H40*I40 -> 0 | K40: =D40+G40+J40 -> 0 | L40: =C40+F40+I40 -> 0 | P40: =((B40-M40)*C40)+((E40-M40)*F40)+((H40-M40)*I40) -> 0
A41: Eco Bag CGEEE! | B41: 50 | C41: 2 | D41: =B41*C41 -> 100 | E41: 35 | G41: =E41*F41 -> 0 | J41: =H41*I41 -> 0 | K41: =D41+G41+J41 -> 100 | L41: =C41+F41+I41 -> 2 | P41: =((B41-M41)*C41)+((E41-M41)*F41)+((H41-M41)*I41) -> 100
A42: Keychain | B42: 150 | C42: 13 | D42: =B42*C42 -> 1950 | E42: 120 | G42: =E42*F42 -> 0 | H42: 75 | J42: =H42*I42 -> 0 | K42: =D42+G42+J42 -> 1950 | L42: =C42+F42+I42 -> 13 | P42: =((B42-M42)*C42)+((E42-M42)*F42)+((H42-M42)*I42) -> 1950
A43: Kit Set | B43: 800 | D43: =B43*C43 -> 0 | E43: 750 | G43: =E43*F43 -> 0 | H43: 700 | J43: =H43*I43 -> 0 | K43: =D43+G43+J43 -> 0 | L43: =C43+F43+I43 -> 0 | P43: =((B43-M43)*C43)+((E43-M43)*F43)+((H43-M43)*I43) -> 0
A44: Lanyard | B44: 190 | C44: 3 | D44: =B44*C44 -> 570 | E44: 175 | G44: =E44*F44 -> 0 | H44: 150 | J44: =H44*I44 -> 0 | K44: =D44+G44+J44 -> 570 | L44: =C44+F44+I44 -> 3 | M44: 117 | N44: 14.04 | O44: 11.7 | P44: =((B44-M44)*C44)+((E44-M44)*F44)+((H44-M44)*I44) -> 219
A45: Lanyard | B45: 180 | C45: 3 | D45: =B45*C45 -> 540 | E45: 165 | G45: =E45*F45 -> 0 | H45: 140 | J45: =H45*I45 -> 0 | K45: =D45+G45+J45 -> 540 | L45: =C45+F45+I45 -> 3 | M45: 110 | N45: 13.2 | O45: 11 | P45: =((B45-M45)*C45)+((E45-M45)*F45)+((H45-M45)*I45) -> 210
A46: NB | B46: 75 | D46: =B46*C46 -> 0 | G46: =E46*F46 -> 0 | J46: =H46*I46 -> 0 | K46: =D46+G46+J46 -> 0 | L46: =C46+F46+I46 -> 0 | P46: =((B46-M46)*C46)+((E46-M46)*F46)+((H46-M46)*I46) -> 0
A47: NB | B47: 100 | C47: 2 | D47: =B47*C47 -> 200 | E47: 80 | G47: =E47*F47 -> 0 | H47: 70 | J47: =H47*I47 -> 0 | K47: =D47+G47+J47 -> 200 | L47: =C47+F47+I47 -> 2 | P47: =((B47-M47)*C47)+((E47-M47)*F47)+((H47-M47)*I47) -> 200
A48: Sash Big | B48: 600 | D48: =B48*C48 -> 0 | E48: 500 | G48: =E48*F48 -> 0 | H48: 400 | J48: =H48*I48 -> 0 | K48: =D48+G48+J48 -> 0 | L48: =C48+F48+I48 -> 0 | P48: =((B48-M48)*C48)+((E48-M48)*F48)+((H48-M48)*I48) -> 0
A49: Sash Small | B49: 150 | C49: 1 | D49: =B49*C49 -> 150 | E49: 125 | G49: =E49*F49 -> 0 | H49: 100 | J49: =H49*I49 -> 0 | K49: =D49+G49+J49 -> 150 | L49: =C49+F49+I49 -> 1 | P49: =((B49-M49)*C49)+((E49-M49)*F49)+((H49-M49)*I49) -> 150
A50: Shabby Hat | B50: 200 | C50: 1 | D50: =B50*C50 -> 200 | E50: 175 | G50: =E50*F50 -> 0 | H50: 150 | J50: =H50*I50 -> 0 | K50: =D50+G50+J50 -> 200 | L50: =C50+F50+I50 -> 1 | P50: =((B50-M50)*C50)+((E50-M50)*F50)+((H50-M50)*I50) -> 200
A51: Tiger Stuff Toy Small Grad | B51: 250 | C51: 9 | D51: =B51*C51 -> 2250 | E51: 230 | G51: =E51*F51 -> 0 | H51: 200 | J51: =H51*I51 -> 0 | K51: =D51+G51+J51 -> 2250 | L51: =C51+F51+I51 -> 9 | P51: =((B51-M51)*C51)+((E51-M51)*F51)+((H51-M51)*I51) -> 2250
A52: Tote Bag CGEEE! | B52: 120 | D52: =B52*C52 -> 0 | E52: 100 | G52: =E52*F52 -> 0 | H52: 80 | J52: =H52*I52 -> 0 | K52: =D52+G52+J52 -> 0 | L52: =C52+F52+I52 -> 0 | P52: =((B52-M52)*C52)+((E52-M52)*F52)+((H52-M52)*I52) -> 0
A53: Tote Bag Canvas White | B53: 160 | C53: 2 | D53: =B53*C53 -> 320 | G53: =E53*F53 -> 0 | J53: =H53*I53 -> 0 | K53: =D53+G53+J53 -> 320 | L53: =C53+F53+I53 -> 2 | P53: =((B53-M53)*C53)+((E53-M53)*F53)+((H53-M53)*I53) -> 320
A54: Tote (One For UST) | B54: 300 | D54: =B54*C54 -> 0 | E54: 275 | G54: =E54*F54 -> 0 | H54: 250 | I54: 2 | J54: =H54*I54 -> 500 | K54: =D54+G54+J54 -> 500 | L54: =C54+F54+I54 -> 2 | P54: =((B54-M54)*C54)+((E54-M54)*F54)+((H54-M54)*I54) -> 500
A55: Tumbler | B55: 150 | D55: =B55*C55 -> 0 | G55: =E55*F55 -> 0 | J55: =H55*I55 -> 0 | K55: =D55+G55+J55 -> 0 | L55: =C55+F55+I55 -> 0 | P55: =((B55-M55)*C55)+((E55-M55)*F55)+((H55-M55)*I55) -> 0
A56: Umb. Cane | B56: 500 | D56: =B56*C56 -> 0 | E56: 450 | G56: =E56*F56 -> 0 | H56: 400 | J56: =H56*I56 -> 0 | K56: =D56+G56+J56 -> 0 | L56: =C56+F56+I56 -> 0 | P56: =((B56-M56)*C56)+((E56-M56)*F56)+((H56-M56)*I56) -> 0
A57: Umb (One For UST) | B57: 350 | C57: 3 | D57: =B57*C57 -> 1050 | E57: 300 | G57: =E57*F57 -> 0 | H57: 250 | J57: =H57*I57 -> 0 | K57: =D57+G57+J57 -> 1050 | L57: =C57+F57+I57 -> 3 | P57: =((B57-M57)*C57)+((E57-M57)*F57)+((H57-M57)*I57) -> 1050
A58: Old Umbrella | B58: 250 | D58: =B58*C58 -> 0 | E58: 200 | G58: =E58*F58 -> 0 | H58: 180 | J58: =H58*I58 -> 0 | K58: =D58+G58+J58 -> 0 | L58: =C58+F58+I58 -> 0
A59: Utensil | B59: 250 | D59: =B59*C59 -> 0 | E59: 200 | G59: =E59*F59 -> 0 | H59: 180 | J59: =H59*I59 -> 0 | K59: =D59+G59+J59 -> 0 | L59: =C59+F59+I59 -> 0
C60: TOTAL | D60: =SUM(D39:D59) -> 7330 | F60: TOTAL | G60: =SUM(G39:G59) -> 0 | I60: TOTAL | J60: =SUM(J39:J59) -> 500 | K60: =D60+G60+J60 -> 7830 | M60: TOTAL | P60: =SUM(P39:P59) -> 7149
A61: TET AND DARS | B61: RETAIL PRICE | C61: PCS SOLD | D61: SALES | E61: DISCOUNTED PRICE | F61: PCS SOLD | G61: SALES | H61: SPECIAL DISC. PRICE | I61: PCS SOLD | J61: SALES | K61: TOTAL SALES | L61: TOTALQTY SOLD | M61: PRODUCTION PRICE | N61: 12% Vat | O61: 10% Mark Up | P61: PROFIT
A62: Arch | B62: 320 | D62: =B62*C62 -> 0 | E62: 300 | G62: =E62*F62 -> 0 | H62: 300 | J62: =H62*I62 -> 0 | K62: =D62+G62+J62 -> 0 | L62: =C62+F62+I62 -> 0 | M62: 240 | N62: 28.8 | O62: 24 | P62: =((B62-M62)*C62)+((E62-M62)*F62)+((H62-M62)*I62) -> 0
A63: Eco Bag | B63: 80 | D63: =B63*C63 -> 0 | E63: 70 | G63: =E63*F63 -> 0 | H63: 60 | J63: =H63*I63 -> 0 | K63: =D63+G63+J63 -> 0 | L63: =C63+F63+I63 -> 0 | M63: 60 | P63: =((B63-M63)*C63)+((E63-M63)*F63)+((H63-M63)*I63) -> 0
A64: Eco Bag | B64: 130 | D64: =B64*C64 -> 0 | E64: 120 | G64: =E64*F64 -> 0 | H64: 110 | J64: =H64*I64 -> 0 | K64: =D64+G64+J64 -> 0 | L64: =C64+F64+I64 -> 0 | M64: 100 | P64: =((B64-M64)*C64)+((E64-M64)*F64)+((H64-M64)*I64) -> 0
A65: Main Building | B65: 430 | D65: =B65*C65 -> 0 | E65: 430 | G65: =E65*F65 -> 0 | H65: 430 | J65: =H65*I65 -> 0 | K65: =D65+G65+J65 -> 0 | L65: =C65+F65+I65 -> 0 | M65: 350 | N65: 42 | O65: 35 | P65: =((B65-M65)*C65)+((E65-M65)*F65)+((H65-M65)*I65) -> 0
A66: Mug | B66: 170 | D66: =B66*C66 -> 0 | E66: 160 | G66: =E66*F66 -> 0 | H66: 150 | J66: =H66*I66 -> 0 | K66: =D66+G66+J66 -> 0 | L66: =C66+F66+I66 -> 0 | M66: 125 | N66: 15 | O66: 12.5 | P66: =((B66-M66)*C66)+((E66-M66)*F66)+((H66-M66)*I66) -> 0
A67: Notebook | B67: 220 | D67: =B67*C67 -> 0 | G67: =E67*F67 -> 0 | J67: =H67*I67 -> 0 | K67: =D67+G67+J67 -> 0 | L67: =C67+F67+I67 -> 0 | P67: =((B67-M67)*C67)+((E67-M67)*F67)+((H67-M67)*I67) -> 0
A68: Pen | B68: 50 | D68: =B68*C68 -> 0 | G68: =E68*F68 -> 0 | J68: =H68*I68 -> 0 | K68: =D68+G68+J68 -> 0 | L68: =C68+F68+I68 -> 0 | M68: 42 | P68: =((B68-M68)*C68)+((E68-M68)*F68)+((H68-M68)*I68) -> 0
A69: Pen | B69: 25 | D69: =B69*C69 -> 0 | G69: =E69*F69 -> 0 | J69: =H69*I69 -> 0 | K69: =D69+G69+J69 -> 0 | L69: =C69+F69+I69 -> 0 | M69: 20 | P69: =((B69-M69)*C69)+((E69-M69)*F69)+((H69-M69)*I69) -> 0
A70: Sticker | B70: 115 | D70: =B70*C70 -> 0 | E70: 110 | G70: =E70*F70 -> 0 | H70: 105 | J70: =H70*I70 -> 0 | K70: =D70+G70+J70 -> 0 | L70: =C70+F70+I70 -> 0 | M70: 85 | P70: =((B70-M70)*C70)+((E70-M70)*F70)+((H70-M70)*I70) -> 0
A71: Sticker | B71: 20 | D71: =B71*C71 -> 0 | E71: 20 | G71: =E71*F71 -> 0 | H71: 20 | J71: =H71*I71 -> 0 | K71: =D71+G71+J71 -> 0 | L71: =C71+F71+I71 -> 0 | M71: 15 | P71: =((B71-M71)*C71)+((E71-M71)*F71)+((H71-M71)*I71) -> 0
A72: Tote | B72: 230 | D72: =B72*C72 -> 0 | G72: =E72*F72 -> 0 | J72: =H72*I72 -> 0 | K72: =D72+G72+J72 -> 0 | L72: =C72+F72+I72 -> 0 | P72: =((B72-M72)*C72)+((E72-M72)*F72)+((H72-M72)*I72) -> 0
C73: TOTAL | D73: =SUM(D62:D72) -> 0 | F73: TOTAL | G73: =SUM(G62:G72) -> 0 | I73: TOTAL | J73: =SUM(J62:J72) -> 0 | K73: =D73+G73+J73 -> 0 | M73: TOTAL | P73: =SUM(P62:P72) -> 0
A74: BLAZE | B74: RETAIL PRICE | C74: PCS SOLD | D74: SALES | E74: DISCOUNTED PRICE | F74: PCS SOLD | G74: SALES | H74: SPECIAL DISC. PRICE | I74: PCS SOLD | J74: SALES | K74: TOTAL SALES | L74: TOTALQTY SOLD | M74: PRODUCTION PRICE | N74: 12% Vat | O74: 10% Mark Up | P74: PROFIT
A75: Crew Neck Shirt | B75: 475 | D75: =B75*C75 -> 0 | E75: 450 | G75: =E75*F75 -> 0 | H75: 430 | J75: =H75*I75 -> 0 | K75: =D75+G75+J75 -> 0 | L75: =C75+F75+I75 -> 0 | M75: 350 | N75: 42 | O75: 35 | P75: =((B75-M75)*C75)+((E75-M75)*F75)+((H75-M75)*I75) -> 0
A76: Polo Shirt | B76: 800 | D76: =B76*C76 -> 0 | E76: 750 | G76: =E76*F76 -> 0 | H76: 700 | I76: 1 | J76: =H76*I76 -> 700 | K76: =D76+G76+J76 -> 700 | L76: =C76+F76+I76 -> 1 | M76: 550 | N76: 66 | O76: 55 | P76: =((B76-M76)*C76)+((E76-M76)*F76)+((H76-M76)*I76) -> 150
A77: Socks | B77: 375 | D77: =B77*C77 -> 0 | E77: 350 | G77: =E77*F77 -> 0 | H77: 325 | J77: =H77*I77 -> 0 | K77: =D77+G77+J77 -> 0 | L77: =C77+F77+I77 -> 0 | M77: 250 | N77: 30 | O77: 25 | P77: =((B77-M77)*C77)+((E77-M77)*F77)+((H77-M77)*I77) -> 0
A78: socks set of 3 | B78: 950 | D78: =B78*C78 -> 0 | E78: 900 | G78: =E78*F78 -> 0 | H78: 800 | J78: =H78*I78 -> 0 | K78: =D78+G78+J78 -> 0 | L78: =C78+F78+I78 -> 0 | M78: 750 | N78: 90 | O78: 75 | P78: =((B78-M78)*C78)+((E78-M78)*F78)+((H78-M78)*I78) -> 0
C79: TOTAL | D79: =SUM(D75:D78) -> 0 | F79: TOTAL | G79: =SUM(G75:G78) -> 0 | I79: TOTAL | J79: =SUM(J75:J78) -> 700 | K79: =D79+G79+J79 -> 700 | M79: TOTAL | P79: =SUM(P75:P78) -> 150
A80: VARSITY LIFE STYLE | B80: RETAIL PRICE | C80: PCS SOLD | D80: SALES | E80: DISCOUNTED PRICE | F80: PCS SOLD | G80: SALES | H80: SPECIAL DISC. PRICE | I80: PCS SOLD | J80: SALES | K80: TOTAL SALES | L80: TOTALQTY SOLD | M80: PRODUCTION PRICE | N80: 12% Vat | O80: 10% Mark Up | P80: PROFIT
A81: Baller | B81: 100 | C81: 1 | D81: =B81*C81 -> 100 | K81: =D81+G81+J81 -> 100 | L81: =C81+F81+I81 -> 1 | M81: 90
A82: Caps | B82: 800 | D82: =B82*C82 -> 0 | K82: =D82+G82+J82 -> 0 | L82: =C82+F82+I82 -> 0 | M82: 700
A83: Hoodie | B83: 1750 | D83: =B83*C83 -> 0 | K83: =D83+G83+J83 -> 0 | L83: =C83+F83+I83 -> 0 | M83: 1500
A84: Keychain | B84: 100 | C84: 4 | D84: =B84*C84 -> 400 | K84: =D84+G84+J84 -> 400 | L84: =C84+F84+I84 -> 4 | M84: 90
A85: Lanyard | B85: 250 | C85: 4 | D85: =B85*C85 -> 1000 | K85: =D85+G85+J85 -> 1000 | L85: =C85+F85+I85 -> 4 | M85: 200
A86: Long Sticker | B86: 100 | D86: =B86*C86 -> 0 | K86: =D86+G86+J86 -> 0 | L86: =C86+F86+I86 -> 0 | M86: 90
A87: Oversized Sweatshirt | B87: 1500 | C87: 1 | D87: =B87*C87 -> 1500 | K87: =D87+G87+J87 -> 1500 | L87: =C87+F87+I87 -> 1 | M87: 1300
A88: Scarves | B88: 400 | D88: =B88*C88 -> 0 | K88: =D88+G88+J88 -> 0 | L88: =C88+F88+I88 -> 0 | M88: 350
A89: Shirts | B89: 700 | C89: 3 | D89: =B89*C89 -> 2100 | K89: =D89+G89+J89 -> 2100 | L89: =C89+F89+I89 -> 3 | M89: 600
A90: Sticker Pack | B90: 150 | D90: =B90*C90 -> 0 | K90: =D90+G90+J90 -> 0 | L90: =C90+F90+I90 -> 0 | M90: 130
A91: Varsity Jacket | B91: 2100 | D91: =B91*C91 -> 0 | K91: =D91+G91+J91 -> 0 | L91: =C91+F91+I91 -> 0 | M91: 1900
C92: TOTAL | D92: =SUM(D81:D91) -> 5100 | F92: TOTAL | G92: =SUM(G81:G91) -> 0 | I92: TOTAL | J92: =SUM(J81:J91) -> 0 | K92: =D92+G92+J92 -> 5100 | M92: TOTAL | P92: =SUM(P81:P91) -> 0
A93: MITSUI | B93: RETAIL PRICE | C93: PCS SOLD | D93: SALES | E93: DISCOUNTED PRICE | F93: PCS SOLD | G93: SALES | H93: SPECIAL DISC. PRICE | I93: PCS SOLD | J93: SALES | K93: TOTAL SALES | L93: TOTALQTY SOLD | M93: PRODUCTION PRICE | N93: 12% Vat | O93: 10% Mark Up | P93: PROFIT
A94: Stylus pen | B94: 45 | D94: =B94*C94 -> 0 | E94: 40 | G94: =E94*F94 -> 0 | H94: 25 | J94: =H94*I94 -> 0 | K94: =D94+G94+J94 -> 0 | L94: =C94+F94+I94 -> 0 | M94: 17.36 | N94: 2.08 | O94: 1.74 | P94: =((B94-M94)*C94)+((E94-M94)*F94)+((H94-M94)*I94) -> 0
A95: Retractable | B95: 25 | D95: =B95*C95 -> 0 | E95: 15 | G95: =E95*F95 -> 0 | H95: 20 | J95: =H95*I95 -> 0 | K95: =D95+G95+J95 -> 0 | L95: =C95+F95+I95 -> 0 | M95: 10.08 | N95: 1.21 | O95: 1.01 | P95: =((B95-M95)*C95)+((E95-M95)*F95)+((H95-M95)*I95) -> 0
C96: TOTAL | D96: =SUM(D94+D95) -> 0 | F96: TOTAL | G96: =SUM(G94+G95) -> 0 | I96: TOTAL | J96: =SUM(J94+J95) -> 0 | K96: =D96+G96+J96 -> 0 | M96: TOTAL | P96: =SUM(P94) -> 0
A97: CENTRAL SEMINARY | B97: RETAIL PRICE | C97: PCS SOLD | D97: SALES | E97: DISCOUNTED PRICE | F97: PCS SOLD | G97: SALES | H97: SPECIAL DISC. PRICE | I97: PCS SOLD | J97: SALES | K97: TOTAL SALES | L97: TOTALQTY SOLD | M97: PRODUCTION PRICE | N97: 12% Vat | O97: 10% Mark Up | P97: PROFIT
A98: Subli. Shirt | B98: 550 | C98: 5 | D98: =B98*C98 -> 2750 | G98: =E98*F98 -> 0 | J98: =H98*I98 -> 0 | K98: =D98+G98+J98 -> 2750 | L98: =C98+F98+I98 -> 5 | M98: 500 | P98: =((B98-M98)*C98)+((E98-M98)*F98)+((H98-M98)*I98) -> 250
C99: GRAND TOTAL | D99: =D17+D27+D37+D60+D73+D79+D96+D98+D92 -> 57420 | F99: GRAND TOTAL | G99: =G17+G27+G37+G60+G73+G79+G96+G98+G92 -> 400 | I99: GRAND TOTAL | J99: =J17+J27+J37+J60+J73+J79+J96+J98 -> 3300 | K99: =D99+G99+J99 -> 61120 | M99: GRAND TOTAL | P99: =P17+P27+P37+P60+P73+P79+P96+P98 -> 22279
C100: TOTAL SALE | E100: =K99 -> 61120 | N100: TOTAL PROFIT | P100: =P99 -> 22279
...

Sheet May 10
A1: DAILY SALES REPORT
A2: 45422
A3: ITEMS | B3: RETAIL PRICE | C3: PCS SOLD | D3: SALES | E3: DISCOUNTED PRICE | F3: PCS SOLD | G3: SALES | H3: SPECIAL DISC. PRICE | I3: PCS SOLD | J3: SALES | K3: TOTAL SALES | L3: TOTALQTY SOLD | M3: PRODUCTION PRICE | N3: 12% Vat | O3: 10% Mark Up | P3: PROFIT
A4: NAPOLIZ
A5: Backpack Bag | B5: 1750 | D5: =B5*C5 -> 0 | E5: 1600 | G5: =E5*F5 -> 0 | H5: 1400 | J5: =H5*I5 -> 0 | K5: =D5+G5+J5 -> 0 | L5: =C5+F5+I5 -> 0 | M5: 840 | N5: 100.8 | O5: 84 | P5: =((B5-M5)*C5)+((E5-M5)*F5)+((H5-M5)*I5) -> 0
A6: Black Tote Bag (Phased Out) | B6: 280 | D6: =B6*C6 -> 0 | G6: =E6*F6 -> 0 | J6: =H6*I6 -> 0 | K6: =D6+G6+J6 -> 0 | L6: =C6+F6+I6 -> 0 | M6: 230 | P6: =((B6-M6)*C6)+((E6-M6)*F6)+((H6-M6)*I6) -> 0
A7: Double Canopy | B7: 639 | D7: =B7*C7 -> 0 | E7: 575 | G7: =E7*F7 -> 0 | H7: 500 | J7: =H7*I7 -> 0 | K7: =D7+G7+J7 -> 0 | L7: =C7+F7+I7 -> 0 | M7: 330 | N7: 39.6 | O7: 33 | P7: =((B7-M7)*C7)+((E7-M7)*F7)+((H7-M7)*I7) -> 0
A8: Laptop Bag | B8: 1450 | D8: =B8*C8 -> 0 | E8: 1400 | G8: =E8*F8 -> 0 | H8: 1250 | J8: =H8*I8 -> 0 | K8: =D8+G8+J8 -> 0 | L8: =C8+F8+I8 -> 0 | M8: 840 | N8: 100.8 | O8: 84 | P8: =((B8-M8)*C8)+((E8-M8)*F8)+((H8-M8)*I8) -> 0
A9: Script Santo Tomas with Tiger Back (B) | B9: 480 | C9: 2 | D9: =B9*C9 -> 960 | E9: 460 | G9: =E9*F9 -> 0 | H9: 450 | I9: 1 | J9: =H9*I9 -> 450 | K9: =D9+G9+J9 -> 1410 | L9: =C9+F9+I9 -> 3 | M9: 360 | N9: 43.2 | O9: 36 | P9: =((B9-M9)*C9)+((E9-M9)*F9)+((H9-M9)*I9) -> 330
A10: Side Tiger Hoodie | B10: 1480 | D10: =B10*C10 -> 0 | E10: 1400 | G10: =E10*F10 -> 0 | H10: 1375 | J10: =H10*I10 -> 0 | K10: =D10+G10+J10 -> 0 | L10: =C10+F10+I10 -> 0 | M10: 1125 | N10: 135 | O10: 112.5 | P10: =((B10-M10)*C10)+((E10-M10)*F10)+((H10-M10)*I10) -> 0
A11: Sling Bag | B11: 330 | D11: =B11*C11 -> 0 | E11: 320 | G11: =E11*F11 -> 0 | H11: 300 | J11: =H11*I11 -> 0 | K11: =D11+G11+J11 -> 0 | L11: =C11+F11+I11 -> 0 | M11: 260 | N11: 31.2 | O11: 26 | P11: =((B11-M11)*C11)+((E11-M11)*F11)+((H11-M11)*I11) -> 0
A12: Front Tiger Hoodie | B12: 1440 | D12: =B12*C12 -> 0 | E12: 1400 | G12: =E12*F12 -> 0 | H12: 1375 | J12: =H12*I12 -> 0 | K12: =D12+G12+J12 -> 0 | L12: =C12+F12+I12 -> 0 | M12: 1125 | N12: 135 | O12: 112.5 | P12: =((B12-M12)*C12)+((E12-M12)*F12)+((H12-M12)*I12) -> 0
A13: University of Santo Tomas (B) | B13: 450 | C13: 24 | D13: =B13*C13 -> 10800 | E13: 440 | G13: =E13*F13 -> 0 | H13: 425 | J13: =H13*I13 -> 0 | K13: =D13+G13+J13 -> 10800 | L13: =C13+F13+I13 -> 24 | M13: 360 | N13: 43.2 | O13: 36 | P13: =((B13-M13)*C13)+((E13-M13)*F13)+((H13-M13)*I13) -> 2160
A14: UST Tiger Front and Back Graphic (W) | B14: 500 | C14: 8 | D14: =B14*C14 -> 4000 | E14: 480 | G14: =E14*F14 -> 0 | H14: 450 | J14: =H14*I14 -> 0 | K14: =D14+G14+J14 -> 4000 | L14: =C14+F14+I14 -> 8 | M14: 360 | N14: 43.2 | O14: 36 | P14: =((B14-M14)*C14)+((E14-M14)*F14)+((H14-M14)*I14) -> 1120
A15: White Tote Bag | B15: 260 | D15: =B15*C15 -> 0 | E15: 250 | G15: =E15*F15 -> 0 | H15: 240 | J15: =H15*I15 -> 0 | K15: =D15+G15+J15 -> 0 | L15: =C15+F15+I15 -> 0 | M15: 200 | N15: 24 | O15: 20 | P15: =((B15-M15)*C15)+((E15-M15)*F15)+((H15-M15)*I15) -> 0
A16: Wind Breaker | B16: 1650 | C16: 7 | D16: =B16*C16 -> 11550 | E16: 1600 | G16: =E16*F16 -> 0 | H16: 1500 | J16: =H16*I16 -> 0 | K16: =D16+G16+J16 -> 11550 | L16: =C16+F16+I16 -> 7 | M16: 1125 | N16: 135 | O16: 112.5 | P16: =((B16-M16)*C16)+((E16-M16)*F16)+((H16-M16)*I16) -> 3675
C17: TOTAL | D17: =SUM(D5:D16) -> 27310 | F17: TOTAL | G17: =SUM(G5:G16) -> 0 | I17: TOTAL | J17: =SUM(J5:J16) -> 450 | K17: =D17+G17+J17 -> 27760 | M17: TOTAL | P17: =SUM(P5:P16) -> 7285
A18: JYL | B18: RETAIL PRICE | C18: PCS SOLD | D18: SALES | E18: DISCOUNTED PRICE | F18: PCS SOLD | G18: SALES | H18: SPECIAL DISC. PRICE | I18: PCS SOLD | J18: SALES | K18: TOTAL SALES | L18: TOTALQTY SOLD | M18: PRODUCTION PRICE | N18: 12% Vat | O18: 10% Mark Up | P18: PROFIT
A19: GT Shirt | B19: 375 | D19: =B19*C19 -> 0 | E19: 350 | G19: =E19*F19 -> 0 | H19: 325 | J19: =H19*I19 -> 0 | K19: =D19+G19+J19 -> 0 | L19: =C19+F19+I19 -> 0 | M19: 250 | N19: 30 | O19: 25 | P19: =((B19-M19)*C19)+((E19-M19)*F19)+((H19-M19)*I19) -> 0
A20: Jacket | B20: 1900 | C20: 5 | D20: =B20*C20 -> 9500 | E20: 1700 | G20: =E20*F20 -> 0 | H20: 1500 | J20: =H20*I20 -> 0 | K20: =D20+G20+J20 -> 9500 | L20: =C20+F20+I20 -> 5 | M20: 1200 | N20: 144 | O20: 120 | P20: =((B20-M20)*C20)+((E20-M20)*F20)+((H20-M20)*I20) -> 3500
A21: Poloshirt 123456 | B21: 860 | C21: 3 | D21: =B21*C21 -> 2580 | E21: 800 | G21: =E21*F21 -> 0 | H21: 750 | I21: 1 | J21: =H21*I21 -> 750 | K21: =D21+G21+J21 -> 3330 | L21: =C21+F21+I21 -> 4 | M21: 600 | N21: 72 | O21: 60 | P21: =((B21-M21)*C21)+((E21-M21)*F21)+((H21-M21)*I21) -> 930
A22: VB Jersey w/ sig. (Phased Out) | B22: 2800 | D22: =B22*C22 -> 0 | G22: =E22*F22 -> 0 | J22: =H22*I22 -> 0 | K22: =D22+G22+J22 -> 0 | L22: =C22+F22+I22 -> 0 | M22: 800 | N22: 96 | O22: 80 | P22: =((B22-M22)*C22)+((E22-M22)*F22)+((H22-M22)*I22) -> 0
A23: VB Jersey w/o sig. | B23: 2000 | D23: =B23*C23 -> 0 | E23: 1800 | G23: =E23*F23 -> 0 | H23: 1500 | J23: =H23*I23 -> 0 | K23: =D23+G23+J23 -> 0 | L23: =C23+F23+I23 -> 0 | M23: 800 | P23: =((B23-M23)*C23)+((E23-M23)*F23)+((H23-M23)*I23) -> 0
A24: VB Jersey w/o sig. | B24: 1500 | C24: 3 | D24: =B24*C24 -> 4500 | E24: 1400 | G24: =E24*F24 -> 0 | H24: 1300 | J24: =H24*I24 -> 0 | K24: =D24+G24+J24 -> 4500 | L24: =C24+F24+I24 -> 3 | M24: 800 | P24: =((B24-M24)*C24)+((E24-M24)*F24)+((H24-M24)*I24) -> 2100
A25: VB Jersey w/o sig. | B25: 1000 | D25: =B25*C25 -> 0 | E25: 980 | G25: =E25*F25 -> 0 | H25: 950 | J25: =H25*I25 -> 0 | K25: =D25+G25+J25 -> 0 | L25: =C25+F25+I25 -> 0 | M25: 800 | P25: =((B25-M25)*C25)+((E25-M25)*F25)+((H25-M25)*I25) -> 0
A26: VB Jersey with sig. (Phased Out) | B26: 1500 | D26: =B26*C26 -> 0 | G26: =E26*F26 -> 0 | J26: =H26*I26 -> 0 | K26: =D26+G26+J26 -> 0 | L26: =C26+F26+I26 -> 0 | M26: 800 | P26: =((B26-M26)*C26)+((E26-M26)*F26)+((H26-M26)*I26) -> 0
C27: TOTAL | D27: =SUM(D19:D26) -> 16580 | F27: TOTAL | G27: =SUM(G19:G26) -> 0 | I27: TOTAL | J27: =SUM(J19:J26) -> 750 | K27: =D27+G27+J27 -> 17330 | M27: TOTAL | P27: =SUM(P19:P26) -> 6530
A28: JUC | B28: RETAIL PRICE | C28: PCS SOLD | D28: SALES | E28: DISCOUNTED PRICE | F28: PCS SOLD | G28: SALES | H28: SPECIAL DISC. PRICE | I28: PCS SOLD | J28: SALES | K28: TOTAL SALES | L28: TOTALQTY SOLD | M28: PRODUCTION PRICE | N28: 12% Vat | O28: 10% Mark Up | P28: PROFIT
A29: UST OAT Hoodie Jacket | B29: 1450 | D29: =B29*C29 -> 0 | E29: 1400 | G29: =E29*F29 -> 0 | H29: 1300 | J29: =H29*I29 -> 0 | K29: =D29+G29+J29 -> 0 | L29: =C29+F29+I29 -> 0 | M29: 1000 | N29: 120 | O29: 100 | P29: =((B29-M29)*C29)+((E29-M29)*F29)+((H29-M29)*I29) -> 0
A30: UST OAT MUG | B30: 150 | C30: 10 | D30: =B30*C30 -> 1500 | E30: 140 | G30: =E30*F30 -> 0 | H30: 135 | J30: =H30*I30 -> 0 | K30: =D30+G30+J30 -> 1500 | L30: =C30+F30+I30 -> 10 | M30: 110 | N30: 12 | O30: 10 | P30: =((B30-M30)*C30)+((E30-M30)*F30)+((H30-M30)*I30) -> 400
A31: UST OAT MUG (WE) Inside | B31: 150 | C31: 2 | D31: =B31*C31 -> 300 | E31: 140 | G31: =E31*F31 -> 0 | H31: 135 | J31: =H31*I31 -> 0 | K31: =D31+G31+J31 -> 300 | L31: =C31+F31+I31 -> 2 | M31: 100 | N31: 12 | O31: 10 | P31: =((B31-M31)*C31)+((E31-M31)*F31)+((H31-M31)*I31) -> 100
A32: UST OAT T-Shirt | B32: 375 | C32: 3 | D32: =B32*C32 -> 1125 | E32: 360 | G32: =E32*F32 -> 0 | H32: 340 | J32: =H32*I32 -> 0 | K32: =D32+G32+J32 -> 1125 | L32: =C32+F32+I32 -> 3 | M32: 280 | N32: 33.6 | O32: 28 | P32: =((B32-M32)*C32)+((E32-M32)*F32)+((H32-M32)*I32) -> 285
A33: UST T-Shirt Sports | B33: 430 | C33: 23 | D33: =B33*C33 -> 9890 | E33: 400 | F33: 1 | G33: =E33*F33 -> 400 | H33: 350 | I33: 4 | J33: =H33*I33 -> 1400 | K33: =D33+G33+J33 -> 11690 | L33: =C33+F33+I33 -> 28 | M33: 260 | N33: 31.2 | O33: 26 | P33: =((B33-M33)*C33)+((E33-M33)*F33)+((H33-M33)*I33) -> 4410
A34: UST T-Shirt Tiger Pattern | B34: 450 | C34: 11 | D34: =B34*C34 -> 4950 | E34: 430 | G34: =E34*F34 -> 0 | H34: 400 | I34: 1 | J34: =H34*I34 -> 400 | K34: =D34+G34+J34 -> 5350 | L34: =C34+F34+I34 -> 12 | M34: 330 | N34: 39.6 | O34: 33 | P34: =((B34-M34)*C34)+((E34-M34)*F34)+((H34-M34)*I34) -> 1390
A35: UST Happy Tiger | B35: 450 | C35: 13 | D35: =B35*C35 -> 5850 | E35: 400 | G35: =E35*F35 -> 0 | H35: 350 | J35: =H35*I35 -> 0 | K35: =D35+G35+J35 -> 5850 | L35: =C35+F35+I35 -> 13 | M35: 280 | N35: 33.6 | O35: 28 | P35: =((B35-M35)*C35)+((E35-M35)*F35)+((H35-M35)*I35) -> 2210
A36: OAT Tote Bag (Phased Out) | B36: 220 | D36: =B36*C36 -> 0 | G36: =E36*F36 -> 0 | J36: =H36*I36 -> 0 | K36: =D36+G36+J36 -> 0 | L36: =C36+F36+I36 -> 0 | M36: 120 | P36: =((B36-M36)*C36)+((E36-M36)*F36)+((H36-M36)*I36) -> 0
C37: TOTAL | D37: =SUM(D29:D36) -> 23615 | F37: TOTAL | G37: =SUM(G29:G36) -> 400 | I37: TOTAL | J37: =SUM(J29:J36) -> 1800 | K37: =D37+G37+J37 -> 25815 | M37: TOTAL | P37: =SUM(P29:P36) -> 8795
A38: USTORE | B38: RETAIL PRICE | C38: PCS SOLD | D38: SALES | E38: DISCOUNTED PRICE | F38: PCS SOLD | G38: SALES | H38: SPECIAL DISC. PRICE | I38: PCS SOLD | J38: SALES | K38: TOTAL SALES | L38: TOTALQTY SOLD | M38: PRODUCTION PRICE | N38: 12% Vat | O38: 10% Mark Up | P38: PROFIT
A39: Auto Umbrella | B39: 250 | D39: =B39*C39 -> 0 | G39: =E39*F39 -> 0 | J39: =H39*I39 -> 0 | K39: =D39+G39+J39 -> 0 | L39: =C39+F39+I39 -> 0 | P39: =((B39-M39)*C39)+((E39-M39)*F39)+((H39-M39)*I39) -> 0
A40: Bag | B40: 250 | D40: =B40*C40 -> 0 | E40: 150 | G40: =E40*F40 -> 0 | J40: =H40*I40 -> 0 | K40: =D40+G40+J40 -> 0 | L40: =C40+F40+I40 -> 0 | P40: =((B40-M40)*C40)+((E40-M40)*F40)+((H40-M40)*I40) -> 0
A41: Eco Bag CGEEE! | B41: 50 | D41: =B41*C41 -> 0 | E41: 35 | G41: =E41*F41 -> 0 | J41: =H41*I41 -> 0 | K41: =D41+G41+J41 -> 0 | L41: =C41+F41+I41 -> 0 | P41: =((B41-M41)*C41)+((E41-M41)*F41)+((H41-M41)*I41) -> 0
A42: Keychain | B42: 150 | C42: 5 | D42: =B42*C42 -> 750 | E42: 120 | G42: =E42*F42 -> 0 | H42: 75 | J42: =H42*I42 -> 0 | K42: =D42+G42+J42 -> 750 | L42: =C42+F42+I42 -> 5 | P42: =((B42-M42)*C42)+((E42-M42)*F42)+((H42-M42)*I42) -> 750
A43: Kit Set | B43: 800 | D43: =B43*C43 -> 0 | E43: 750 | G43: =E43*F43 -> 0 | H43: 700 | J43: =H43*I43 -> 0 | K43: =D43+G43+J43 -> 0 | L43: =C43+F43+I43 -> 0 | P43: =((B43-M43)*C43)+((E43-M43)*F43)+((H43-M43)*I43) -> 0
A44: Lanyard | B44: 190 | C44: 1 | D44: =B44*C44 -> 190 | E44: 175 | G44: =E44*F44 -> 0 | H44: 150 | J44: =H44*I44 -> 0 | K44: =D44+G44+J44 -> 190 | L44: =C44+F44+I44 -> 1 | M44: 117 | N44: 14.04 | O44: 11.7 | P44: =((B44-M44)*C44)+((E44-M44)*F44)+((H44-M44)*I44) -> 73
A45: Lanyard | B45: 180 | C45: 5 | D45: =B45*C45 -> 900 | E45: 165 | G45: =E45*F45 -> 0 | H45: 140 | J45: =H45*I45 -> 0 | K45: =D45+G45+J45 -> 900 | L45: =C45+F45+I45 -> 5 | M45: 110 | N45: 13.2 | O45: 11 | P45: =((B45-M45)*C45)+((E45-M45)*F45)+((H45-M45)*I45) -> 350
A46: NB | B46: 75 | D46: =B46*C46 -> 0 | G46: =E46*F46 -> 0 | J46: =H46*I46 -> 0 | K46: =D46+G46+J46 -> 0 | L46: =C46+F46+I46 -> 0 | P46: =((B46-M46)*C46)+((E46-M46)*F46)+((H46-M46)*I46) -> 0
A47: NB | B47: 100 | D47: =B47*C47 -> 0 | E47: 80 | G47: =E47*F47 -> 0 | H47: 70 | J47: =H47*I47 -> 0 | K47: =D47+G47+J47 -> 0 | L47: =C47+F47+I47 -> 0 | P47: =((B47-M47)*C47)+((E47-M47)*F47)+((H47-M47)*I47) -> 0
A48: Sash Big | B48: 600 | D48: =B48*C48 -> 0 | E48: 500 | G48: =E48*F48 -> 0 | H48: 400 | J48: =H48*I48 -> 0 | K48: =D48+G48+J48 -> 0 | L48: =C48+F48+I48 -> 0 | P48: =((B48-M48)*C48)+((E48-M48)*F48)+((H48-M48)*I48) -> 0
A49: Sash Small | B49: 150 | D49: =B49*C49 -> 0 | E49: 125 | G49: =E49*F49 -> 0 | H49: 100 | J49: =H49*I49 -> 0 | K49: =D49+G49+J49 -> 0 | L49: =C49+F49+I49 -> 0 | P49: =((B49-M49)*C49)+((E49-M49)*F49)+((H49-M49)*I49) -> 0
A50: Shabby Hat | B50: 200 | C50: 1 | D50: =B50*C50 -> 200 | E50: 175 | G50: =E50*F50 -> 0 | H50: 150 | J50: =H50*I50 -> 0 | K50: =D50+G50+J50 -> 200 | L50: =C50+F50+I50 -> 1 | P50: =((B50-M50)*C50)+((E50-M50)*F50)+((H50-M50)*I50) -> 200
A51: Tiger Stuff Toy Small Grad | B51: 250 | C51: 1 | D51: =B51*C51 -> 250 | E51: 230 | G51: =E51*F51 -> 0 | H51: 200 | J51: =H51*I51 -> 0 | K51: =D51+G51+J51 -> 250 | L51: =C51+F51+I51 -> 1 | P51: =((B51-M51)*C51)+((E51-M51)*F51)+((H51-M51)*I51) -> 250
A52: Tote Bag CGEEE! | B52: 120 | D52: =B52*C52 -> 0 | E52: 100 | G52: =E52*F52 -> 0 | H52: 80 | J52: =H52*I52 -> 0 | K52: =D52+G52+J52 -> 0 | L52: =C52+F52+I52 -> 0 | P52: =((B52-M52)*C52)+((E52-M52)*F52)+((H52-M52)*I52) -> 0
A53: Tote Bag Canvas White | B53: 160 | C53: 2 | D53: =B53*C53 -> 320 | G53: =E53*F53 -> 0 | J53: =H53*I53 -> 0 | K53: =D53+G53+J53 -> 320 | L53: =C53+F53+I53 -> 2 | P53: =((B53-M53)*C53)+((E53-M53)*F53)+((H53-M53)*I53) -> 320
A54: Tote (One For UST) | B54: 300 | C54: 3 | D54: =B54*C54 -> 900 | E54: 275 | G54: =E54*F54 -> 0 | H54: 250 | J54: =H54*I54 -> 0 | K54: =D54+G54+J54 -> 900 | L54: =C54+F54+I54 -> 3 | P54: =((B54-M54)*C54)+((E54-M54)*F54)+((H54-M54)*I54) -> 900
A55: Tumbler | B55: 150 | C55: 6 | D55: =B55*C55 -> 900 | G55: =E55*F55 -> 0 | J55: =H55*I55 -> 0 | K55: =D55+G55+J55 -> 900 | L55: =C55+F55+I55 -> 6 | P55: =((B55-M55)*C55)+((E55-M55)*F55)+((H55-M55)*I55) -> 900
A56: Umb. Cane | B56: 500 | D56: =B56*C56 -> 0 | E56: 450 | G56: =E56*F56 -> 0 | H56: 400 | J56: =H56*I56 -> 0 | K56: =D56+G56+J56 -> 0 | L56: =C56+F56+I56 -> 0 | P56: =((B56-M56)*C56)+((E56-M56)*F56)+((H56-M56)*I56) -> 0
A57: Umb (One For UST) | B57: 350 | C57: 4 | D57: =B57*C57 -> 1400 | E57: 300 | G57: =E57*F57 -> 0 | H57: 250 | J57: =H57*I57 -> 0 | K57: =D57+G57+J57 -> 1400 | L57: =C57+F57+I57 -> 4 | P57: =((B57-M57)*C57)+((E57-M57)*F57)+((H57-M57)*I57) -> 1400
A58: Old Umbrella | B58: 250 | D58: =B58*C58 -> 0 | E58: 200 | G58: =E58*F58 -> 0 | H58: 180 | J58: =H58*I58 -> 0 | K58: =D58+G58+J58 -> 0 | L58: =C58+F58+I58 -> 0
A59: Utensil | B59: 250 | D59: =B59*C59 -> 0 | E59: 200 | G59: =E59*F59 -> 0 | H59: 180 | J59: =H59*I59 -> 0 | K59: =D59+G59+J59 -> 0 | L59: =C59+F59+I59 -> 0
C60: TOTAL | D60: =SUM(D39:D59) -> 5810 | F60: TOTAL | G60: =SUM(G39:G59) -> 0 | I60: TOTAL | J60: =SUM(J39:J59) -> 0 | K60: =D60+G60+J60 -> 5810 | M60: TOTAL | P60: =SUM(P39:P59) -> 5143
A61: TET AND DARS | B61: RETAIL PRICE | C61: PCS SOLD | D61: SALES | E61: DISCOUNTED PRICE | F61: PCS SOLD | G61: SALES | H61: SPECIAL DISC. PRICE | I61: PCS SOLD | J61: SALES | K61: TOTAL SALES | L61: TOTALQTY SOLD | M61: PRODUCTION PRICE | N61: 12% Vat | O61: 10% Mark Up | P61: PROFIT
A62: Arch | B62: 320 | D62: =B62*C62 -> 0 | E62: 300 | G62: =E62*F62 -> 0 | H62: 300 | J62: =H62*I62 -> 0 | K62: =D62+G62+J62 -> 0 | L62: =C62+F62+I62 -> 0 | M62: 240 | N62: 28.8 | O62: 24 | P62: =((B62-M62)*C62)+((E62-M62)*F62)+((H62-M62)*I62) -> 0
A63: Eco Bag | B63: 80 | D63: =B63*C63 -> 0 | E63: 70 | G63: =E63*F63 -> 0 | H63: 60 | J63: =H63*I63 -> 0 | K63: =D63+G63+J63 -> 0 | L63: =C63+F63+I63 -> 0 | M63: 60 | P63: =((B63-M63)*C63)+((E63-M63)*F63)+((H63-M63)*I63) -> 0
A64: Eco Bag | B64: 130 | D64: =B64*C64 -> 0 | E64: 120 | G64: =E64*F64 -> 0 | H64: 110 | J64: =H64*I64 -> 0 | K64: =D64+G64+J64 -> 0 | L64: =C64+F64+I64 -> 0 | M64: 100 | P64: =((B64-M64)*C64)+((E64-M64)*F64)+((H64-M64)*I64) -> 0
A65: Main Building | B65: 430 | D65: =B65*C65 -> 0 | E65: 430 | G65: =E65*F65 -> 0 | H65: 430 | J65: =H65*I65 -> 0 | K65: =D65+G65+J65 -> 0 | L65: =C65+F65+I65 -> 0 | M65: 350 | N65: 42 | O65: 35 | P65: =((B65-M65)*C65)+((E65-M65)*F65)+((H65-M65)*I65) -> 0
A66: Mug | B66: 170 | D66: =B66*C66 -> 0 | E66: 160 | G66: =E66*F66 -> 0 | H66: 150 | J66: =H66*I66 -> 0 | K66: =D66+G66+J66 -> 0 | L66: =C66+F66+I66 -> 0 | M66: 125 | N66: 15 | O66: 12.5 | P66: =((B66-M66)*C66)+((E66-M66)*F66)+((H66-M66)*I66) -> 0
A67: Notebook | B67: 220 | D67: =B67*C67 -> 0 | G67: =E67*F67 -> 0 | J67: =H67*I67 -> 0 | K67: =D67+G67+J67 -> 0 | L67: =C67+F67+I67 -> 0 | P67: =((B67-M67)*C67)+((E67-M67)*F67)+((H67-M67)*I67) -> 0
A68: Pen | B68: 50 | D68: =B68*C68 -> 0 | G68: =E68*F68 -> 0 | J68: =H68*I68 -> 0 | K68: =D68+G68+J68 -> 0 | L68: =C68+F68+I68 -> 0 | M68: 42 | P68: =((B68-M68)*C68)+((E68-M68)*F68)+((H68-M68)*I68) -> 0
A69: Pen | B69: 25 | D69: =B69*C69 -> 0 | G69: =E69*F69 -> 0 | J69: =H69*I69 -> 0 | K69: =D69+G69+J69 -> 0 | L69: =C69+F69+I69 -> 0 | M69: 20 | P69: =((B69-M69)*C69)+((E69-M69)*F69)+((H69-M69)*I69) -> 0
A70: Sticker | B70: 115 | C70: 1 | D70: =B70*C70 -> 115 | E70: 110 | G70: =E70*F70 -> 0 | H70: 105 | J70: =H70*I70 -> 0 | K70: =D70+G70+J70 -> 115 | L70: =C70+F70+I70 -> 1 | M70: 85 | P70: =((B70-M70)*C70)+((E70-M70)*F70)+((H70-M70)*I70) -> 30
A71: Sticker | B71: 20 | C71: 4 | D71: =B71*C71 -> 80 | E71: 20 | G71: =E71*F71 -> 0 | H71: 20 | J71: =H71*I71 -> 0 | K71: =D71+G71+J71 -> 80 | L71: =C71+F71+I71 -> 4 | M71: 15 | P71: =((B71-M71)*C71)+((E71-M71)*F71)+((H71-M71)*I71) -> 20
A72: Tote | B72: 230 | D72: =B72*C72 -> 0 | G72: =E72*F72 -> 0 | J72: =H72*I72 -> 0 | K72: =D72+G72+J72 -> 0 | L72: =C72+F72+I72 -> 0 | P72: =((B72-M72)*C72)+((E72-M72)*F72)+((H72-M72)*I72) -> 0
C73: TOTAL | D73: =SUM(D62:D72) -> 195 | F73: TOTAL | G73: =SUM(G62:G72) -> 0 | I73: TOTAL | J73: =SUM(J62:J72) -> 0 | K73: =D73+G73+J73 -> 195 | M73: TOTAL | P73: =SUM(P62:P72) -> 50
A74: BLAZE | B74: RETAIL PRICE | C74: PCS SOLD | D74: SALES | E74: DISCOUNTED PRICE | F74: PCS SOLD | G74: SALES | H74: SPECIAL DISC. PRICE | I74: PCS SOLD | J74: SALES | K74: TOTAL SALES | L74: TOTALQTY SOLD | M74: PRODUCTION PRICE | N74: 12% Vat | O74: 10% Mark Up | P74: PROFIT
A75: Crew Neck Shirt | B75: 475 | D75: =B75*C75 -> 0 | E75: 450 | G75: =E75*F75 -> 0 | H75: 430 | J75: =H75*I75 -> 0 | K75: =D75+G75+J75 -> 0 | L75: =C75+F75+I75 -> 0 | M75: 350 | N75: 42 | O75: 35 | P75: =((B75-M75)*C75)+((E75-M75)*F75)+((H75-M75)*I75) -> 0
A76: Polo Shirt | B76: 800 | C76: 1 | D76: =B76*C76 -> 800 | E76: 750 | G76: =E76*F76 -> 0 | H76: 700 | J76: =H76*I76 -> 0 | K76: =D76+G76+J76 -> 800 | L76: =C76+F76+I76 -> 1 | M76: 550 | N76: 66 | O76: 55 | P76: =((B76-M76)*C76)+((E76-M76)*F76)+((H76-M76)*I76) -> 250
A77: Socks | B77: 375 | D77: =B77*C77 -> 0 | E77: 350 | G77: =E77*F77 -> 0 | H77: 325 | J77: =H77*I77 -> 0 | K77: =D77+G77+J77 -> 0 | L77: =C77+F77+I77 -> 0 | M77: 250 | N77: 30 | O77: 25 | P77: =((B77-M77)*C77)+((E77-M77)*F77)+((H77-M77)*I77) -> 0
A78: socks set of 3 | B78: 950 | D78: =B78*C78 -> 0 | E78: 900 | G78: =E78*F78 -> 0 | H78: 800 | J78: =H78*I78 -> 0 | K78: =D78+G78+J78 -> 0 | L78: =C78+F78+I78 -> 0 | M78: 750 | N78: 90 | O78: 75 | P78: =((B78-M78)*C78)+((E78-M78)*F78)+((H78-M78)*I78) -> 0
C79: TOTAL | D79: =SUM(D75:D78) -> 800 | F79: TOTAL | G79: =SUM(G75:G78) -> 0 | I79: TOTAL | J79: =SUM(J75:J78) -> 0 | K79: =D79+G79+J79 -> 800 | M79: TOTAL | P79: =SUM(P75:P78) -> 250
A80: VARSITY LIFE STYLE | B80: RETAIL PRICE | C80: PCS SOLD | D80: SALES | E80: DISCOUNTED PRICE | F80: PCS SOLD | G80: SALES | H80: SPECIAL DISC. PRICE | I80: PCS SOLD | J80: SALES | K80: TOTAL SALES | L80: TOTALQTY SOLD | M80: PRODUCTION PRICE | N80: 12% Vat | O80: 10% Mark Up | P80: PROFIT
A81: Baller | B81: 100 | C81: 2 | D81: =B81*C81 -> 200 | K81: =D81+G81+J81 -> 200 | L81: =C81+F81+I81 -> 2 | M81: 90
A82: Caps | B82: 800 | C82: 1 | D82: =B82*C82 -> 800 | K82: =D82+G82+J82 -> 800 | L82: =C82+F82+I82 -> 1 | M82: 700
A83: Hoodie | B83: 1750 | D83: =B83*C83 -> 0 | K83: =D83+G83+J83 -> 0 | L83: =C83+F83+I83 -> 0 | M83: 1500
A84: Keychain | B84: 100 | D84: =B84*C84 -> 0 | K84: =D84+G84+J84 -> 0 | L84: =C84+F84+I84 -> 0 | M84: 90
A85: Lanyard | B85: 250 | D85: =B85*C85 -> 0 | K85: =D85+G85+J85 -> 0 | L85: =C85+F85+I85 -> 0 | M85: 200
A86: Long Sticker | B86: 100 | C86: 1 | D86: =B86*C86 -> 100 | K86: =D86+G86+J86 -> 100 | L86: =C86+F86+I86 -> 1 | M86: 90
A87: Oversized Sweatshirt | B87: 1500 | D87: =B87*C87 -> 0 | K87: =D87+G87+J87 -> 0 | L87: =C87+F87+I87 -> 0 | M87: 1300
A88: Scarves | B88: 400 | C88: 1 | D88: =B88*C88 -> 400 | K88: =D88+G88+J88 -> 400 | L88: =C88+F88+I88 -> 1 | M88: 350
A89: Shirts | B89: 700 | C89: 11 | D89: =B89*C89 -> 7700 | K89: =D89+G89+J89 -> 7700 | L89: =C89+F89+I89 -> 11 | M89: 600
A90: Sticker Pack | B90: 150 | C90: 1 | D90: =B90*C90 -> 150 | K90: =D90+G90+J90 -> 150 | L90: =C90+F90+I90 -> 1 | M90: 130
A91: Varsity Jacket | B91: 2100 | D91: =B91*C91 -> 0 | K91: =D91+G91+J91 -> 0 | L91: =C91+F91+I91 -> 0 | M91: 1900
C92: TOTAL | D92: =SUM(D81:D91) -> 9350 | F92: TOTAL | G92: =SUM(G81:G91) -> 0 | I92: TOTAL | J92: =SUM(J81:J91) -> 0 | K92: =D92+G92+J92 -> 9350 | M92: TOTAL | P92: =SUM(P81:P91) -> 0
A93: MITSUI | B93: RETAIL PRICE | C93: PCS SOLD | D93: SALES | E93: DISCOUNTED PRICE | F93: PCS SOLD | G93: SALES | H93: SPECIAL DISC. PRICE | I93: PCS SOLD | J93: SALES | K93: TOTAL SALES | L93: TOTALQTY SOLD | M93: PRODUCTION PRICE | N93: 12% Vat | O93: 10% Mark Up | P93: PROFIT
A94: Stylus pen | B94: 45 | D94: =B94*C94 -> 0 | E94: 40 | G94: =E94*F94 -> 0 | H94: 25 | J94: =H94*I94 -> 0 | K94: =D94+G94+J94 -> 0 | L94: =C94+F94+I94 -> 0 | M94: 17.36 | N94: 2.08 | O94: 1.74 | P94: =((B94-M94)*C94)+((E94-M94)*F94)+((H94-M94)*I94) -> 0
A95: Retractable | B95: 25 | D95: =B95*C95 -> 0 | E95: 15 | G95: =E95*F95 -> 0 | H95: 20 | J95: =H95*I95 -> 0 | K95: =D95+G95+J95 -> 0 | L95: =C95+F95+I95 -> 0 | M95: 10.08 | N95: 1.21 | O95: 1.01 | P95: =((B95-M95)*C95)+((E95-M95)*F95)+((H95-M95)*I95) -> 0
C96: TOTAL | D96: =SUM(D94+D95) -> 0 | F96: TOTAL | G96: =SUM(G94+G95) -> 0 | I96: TOTAL | J96: =SUM(J94+J95) -> 0 | K96: =D96+G96+J96 -> 0 | M96: TOTAL | P96: =SUM(P94) -> 0
A97: CENTRAL SEMINARY | B97: RETAIL PRICE | C97: PCS SOLD | D97: SALES | E97: DISCOUNTED PRICE | F97: PCS SOLD | G97: SALES | H97: SPECIAL DISC. PRICE | I97: PCS SOLD | J97: SALES | K97: TOTAL SALES | L97: TOTALQTY SOLD | M97: PRODUCTION PRICE | N97: 12% Vat | O97: 10% Mark Up | P97: PROFIT
A98: Subli. Shirt | B98: 550 | C98: 5 | D98: =B98*C98 -> 2750 | G98: =E98*F98 -> 0 | J98: =H98*I98 -> 0 | K98: =D98+G98+J98 -> 2750 | L98: =C98+F98+I98 -> 5 | M98: 500 | P98: =((B98-M98)*C98)+((E98-M98)*F98)+((H98-M98)*I98) -> 250
C99: GRAND TOTAL | D99: =D17+D27+D37+D60+D73+D79+D96+D98+D92 -> 86410 | F99: GRAND TOTAL | G99: =G17+G27+G37+G60+G73+G79+G96+G98+G92 -> 400 | I99: GRAND TOTAL | J99: =J17+J27+J37+J60+J73+J79+J96+J98 -> 3000 | K99: =D99+G99+J99 -> 89810 | M99: GRAND TOTAL | P99: =P17+P27+P37+P60+P73+P79+P96+P98 -> 28303
C100: TOTAL SALE | E100: =K99 -> 89810 | N100: TOTAL PROFIT | P100: =P99 -> 28303
...

Sheet May 13
A1: DAILY SALES REPORT
A2: 45425
A3: ITEMS | B3: RETAIL PRICE | C3: PCS SOLD | D3: SALES | E3: DISCOUNTED PRICE | F3: PCS SOLD | G3: SALES | H3: SPECIAL DISC. PRICE | I3: PCS SOLD | J3: SALES | K3: TOTAL SALES | L3: TOTALQTY SOLD | M3: PRODUCTION PRICE | N3: 12% Vat | O3: 10% Mark Up | P3: PROFIT
A4: NAPOLIZ
A5: Backpack Bag | B5: 1750 | D5: =B5*C5 -> 0 | E5: 1600 | G5: =E5*F5 -> 0 | H5: 1400 | J5: =H5*I5 -> 0 | K5: =D5+G5+J5 -> 0 | L5: =C5+F5+I5 -> 0 | M5: 840 | N5: 100.8 | O5: 84 | P5: =((B5-M5)*C5)+((E5-M5)*F5)+((H5-M5)*I5) -> 0
A6: Black Tote Bag (Phased Out) | B6: 280 | D6: =B6*C6 -> 0 | G6: =E6*F6 -> 0 | J6: =H6*I6 -> 0 | K6: =D6+G6+J6 -> 0 | L6: =C6+F6+I6 -> 0 | M6: 230 | P6: =((B6-M6)*C6)+((E6-M6)*F6)+((H6-M6)*I6) -> 0
A7: Double Canopy | B7: 639 | D7: =B7*C7 -> 0 | E7: 575 | G7: =E7*F7 -> 0 | H7: 500 | J7: =H7*I7 -> 0 | K7: =D7+G7+J7 -> 0 | L7: =C7+F7+I7 -> 0 | M7: 330 | N7: 39.6 | O7: 33 | P7: =((B7-M7)*C7)+((E7-M7)*F7)+((H7-M7)*I7) -> 0
A8: Laptop Bag | B8: 1450 | D8: =B8*C8 -> 0 | E8: 1400 | G8: =E8*F8 -> 0 | H8: 1250 | J8: =H8*I8 -> 0 | K8: =D8+G8+J8 -> 0 | L8: =C8+F8+I8 -> 0 | M8: 840 | N8: 100.8 | O8: 84 | P8: =((B8-M8)*C8)+((E8-M8)*F8)+((H8-M8)*I8) -> 0
A9: Script Santo Tomas with Tiger Back (B) | B9: 480 | D9: =B9*C9 -> 0 | E9: 460 | G9: =E9*F9 -> 0 | H9: 450 | J9: =H9*I9 -> 0 | K9: =D9+G9+J9 -> 0 | L9: =C9+F9+I9 -> 0 | M9: 360 | N9: 43.2 | O9: 36 | P9: =((B9-M9)*C9)+((E9-M9)*F9)+((H9-M9)*I9) -> 0
A10: Side Tiger Hoodie | B10: 1480 | D10: =B10*C10 -> 0 | E10: 1400 | G10: =E10*F10 -> 0 | H10: 1375 | J10: =H10*I10 -> 0 | K10: =D10+G10+J10 -> 0 | L10: =C10+F10+I10 -> 0 | M10: 1125 | N10: 135 | O10: 112.5 | P10: =((B10-M10)*C10)+((E10-M10)*F10)+((H10-M10)*I10) -> 0
A11: Sling Bag | B11: 330 | D11: =B11*C11 -> 0 | E11: 320 | G11: =E11*F11 -> 0 | H11: 300 | J11: =H11*I11 -> 0 | K11: =D11+G11+J11 -> 0 | L11: =C11+F11+I11 -> 0 | M11: 260 | N11: 31.2 | O11: 26 | P11: =((B11-M11)*C11)+((E11-M11)*F11)+((H11-M11)*I11) -> 0
A12: Front Tiger Hoodie | B12: 1440 | D12: =B12*C12 -> 0 | E12: 1400 | G12: =E12*F12 -> 0 | H12: 1375 | J12: =H12*I12 -> 0 | K12: =D12+G12+J12 -> 0 | L12: =C12+F12+I12 -> 0 | M12: 1125 | N12: 135 | O12: 112.5 | P12: =((B12-M12)*C12)+((E12-M12)*F12)+((H12-M12)*I12) -> 0
A13: University of Santo Tomas (B) | B13: 450 | C13: 7 | D13: =B13*C13 -> 3150 | E13: 440 | G13: =E13*F13 -> 0 | H13: 425 | J13: =H13*I13 -> 0 | K13: =D13+G13+J13 -> 3150 | L13: =C13+F13+I13 -> 7 | M13: 360 | N13: 43.2 | O13: 36 | P13: =((B13-M13)*C13)+((E13-M13)*F13)+((H13-M13)*I13) -> 630
A14: UST Tiger Front and Back Graphic (W) | B14: 500 | C14: 2 | D14: =B14*C14 -> 1000 | E14: 480 | G14: =E14*F14 -> 0 | H14: 450 | J14: =H14*I14 -> 0 | K14: =D14+G14+J14 -> 1000 | L14: =C14+F14+I14 -> 2 | M14: 360 | N14: 43.2 | O14: 36 | P14: =((B14-M14)*C14)+((E14-M14)*F14)+((H14-M14)*I14) -> 280
A15: White Tote Bag | B15: 260 | D15: =B15*C15 -> 0 | E15: 250 | G15: =E15*F15 -> 0 | H15: 240 | J15: =H15*I15 -> 0 | K15: =D15+G15+J15 -> 0 | L15: =C15+F15+I15 -> 0 | M15: 200 | N15: 24 | O15: 20 | P15: =((B15-M15)*C15)+((E15-M15)*F15)+((H15-M15)*I15) -> 0
A16: Wind Breaker | B16: 1650 | C16: 5 | D16: =B16*C16 -> 8250 | E16: 1600 | G16: =E16*F16 -> 0 | H16: 1500 | I16: 1 | J16: =H16*I16 -> 1500 | K16: =D16+G16+J16 -> 9750 | L16: =C16+F16+I16 -> 6 | M16: 1125 | N16: 135 | O16: 112.5 | P16: =((B16-M16)*C16)+((E16-M16)*F16)+((H16-M16)*I16) -> 3000
C17: TOTAL | D17: =SUM(D5:D16) -> 12400 | F17: TOTAL | G17: =SUM(G5:G16) -> 0 | I17: TOTAL | J17: =SUM(J5:J16) -> 1500 | K17: =D17+G17+J17 -> 13900 | M17: TOTAL | P17: =SUM(P5:P16) -> 3910
A18: JYL | B18: RETAIL PRICE | C18: PCS SOLD | D18: SALES | E18: DISCOUNTED PRICE | F18: PCS SOLD | G18: SALES | H18: SPECIAL DISC. PRICE | I18: PCS SOLD | J18: SALES | K18: TOTAL SALES | L18: TOTALQTY SOLD | M18: PRODUCTION PRICE | N18: 12% Vat | O18: 10% Mark Up | P18: PROFIT
A19: GT Shirt | B19: 375 | D19: =B19*C19 -> 0 | E19: 350 | G19: =E19*F19 -> 0 | H19: 325 | J19: =H19*I19 -> 0 | K19: =D19+G19+J19 -> 0 | L19: =C19+F19+I19 -> 0 | M19: 250 | N19: 30 | O19: 25 | P19: =((B19-M19)*C19)+((E19-M19)*F19)+((H19-M19)*I19) -> 0
A20: Jacket | B20: 1900 | C20: 1 | D20: =B20*C20 -> 1900 | E20: 1700 | G20: =E20*F20 -> 0 | H20: 1500 | J20: =H20*I20 -> 0 | K20: =D20+G20+J20 -> 1900 | L20: =C20+F20+I20 -> 1 | M20: 1200 | N20: 144 | O20: 120 | P20: =((B20-M20)*C20)+((E20-M20)*F20)+((H20-M20)*I20) -> 700
A21: Poloshirt 123456 | B21: 860 | D21: =B21*C21 -> 0 | E21: 800 | G21: =E21*F21 -> 0 | H21: 750 | J21: =H21*I21 -> 0 | K21: =D21+G21+J21 -> 0 | L21: =C21+F21+I21 -> 0 | M21: 600 | N21: 72 | O21: 60 | P21: =((B21-M21)*C21)+((E21-M21)*F21)+((H21-M21)*I21) -> 0
A22: VB Jersey w/ sig. (Phased Out) | B22: 2800 | D22: =B22*C22 -> 0 | G22: =E22*F22 -> 0 | J22: =H22*I22 -> 0 | K22: =D22+G22+J22 -> 0 | L22: =C22+F22+I22 -> 0 | M22: 800 | N22: 96 | O22: 80 | P22: =((B22-M22)*C22)+((E22-M22)*F22)+((H22-M22)*I22) -> 0
A23: VB Jersey w/o sig. | B23: 2000 | D23: =B23*C23 -> 0 | E23: 1800 | G23: =E23*F23 -> 0 | H23: 1500 | J23: =H23*I23 -> 0 | K23: =D23+G23+J23 -> 0 | L23: =C23+F23+I23 -> 0 | M23: 800 | P23: =((B23-M23)*C23)+((E23-M23)*F23)+((H23-M23)*I23) -> 0
A24: VB Jersey w/o sig. | B24: 1500 | D24: =B24*C24 -> 0 | E24: 1400 | G24: =E24*F24 -> 0 | H24: 1200 | I24: 1 | J24: =H24*I24 -> 1200 | K24: =D24+G24+J24 -> 1200 | L24: =C24+F24+I24 -> 1 | M24: 800 | P24: =((B24-M24)*C24)+((E24-M24)*F24)+((H24-M24)*I24) -> 400
A25: VB Jersey w/o sig. | B25: 1000 | D25: =B25*C25 -> 0 | E25: 980 | G25: =E25*F25 -> 0 | H25: 950 | J25: =H25*I25 -> 0 | K25: =D25+G25+J25 -> 0 | L25: =C25+F25+I25 -> 0 | M25: 800 | P25: =((B25-M25)*C25)+((E25-M25)*F25)+((H25-M25)*I25) -> 0
A26: VB Jersey with sig. (Phased Out) | B26: 1500 | D26: =B26*C26 -> 0 | G26: =E26*F26 -> 0 | J26: =H26*I26 -> 0 | K26: =D26+G26+J26 -> 0 | L26: =C26+F26+I26 -> 0 | M26: 800 | P26: =((B26-M26)*C26)+((E26-M26)*F26)+((H26-M26)*I26) -> 0
C27: TOTAL | D27: =SUM(D19:D26) -> 1900 | F27: TOTAL | G27: =SUM(G19:G26) -> 0 | I27: TOTAL | J27: =SUM(J19:J26) -> 1200 | K27: =D27+G27+J27 -> 3100 | M27: TOTAL | P27: =SUM(P19:P26) -> 1100
A28: JUC | B28: RETAIL PRICE | C28: PCS SOLD | D28: SALES | E28: DISCOUNTED PRICE | F28: PCS SOLD | G28: SALES | H28: SPECIAL DISC. PRICE | I28: PCS SOLD | J28: SALES | K28: TOTAL SALES | L28: TOTALQTY SOLD | M28: PRODUCTION PRICE | N28: 12% Vat | O28: 10% Mark Up | P28: PROFIT
A29: UST OAT Hoodie Jacket | B29: 1450 | C29: 1 | D29: =B29*C29 -> 1450 | E29: 1400 | G29: =E29*F29 -> 0 | H29: 1300 | J29: =H29*I29 -> 0 | K29: =D29+G29+J29 -> 1450 | L29: =C29+F29+I29 -> 1 | M29: 1000 | N29: 120 | O29: 100 | P29: =((B29-M29)*C29)+((E29-M29)*F29)+((H29-M29)*I29) -> 450
A30: UST OAT MUG | B30: 150 | C30: 5 | D30: =B30*C30 -> 750 | E30: 140 | G30: =E30*F30 -> 0 | H30: 135 | J30: =H30*I30 -> 0 | K30: =D30+G30+J30 -> 750 | L30: =C30+F30+I30 -> 5 | M30: 110 | N30: 12 | O30: 10 | P30: =((B30-M30)*C30)+((E30-M30)*F30)+((H30-M30)*I30) -> 200
A31: UST OAT MUG (WE) Inside | B31: 150 | D31: =B31*C31 -> 0 | E31: 140 | G31: =E31*F31 -> 0 | H31: 135 | J31: =H31*I31 -> 0 | K31: =D31+G31+J31 -> 0 | L31: =C31+F31+I31 -> 0 | M31: 100 | N31: 12 | O31: 10 | P31: =((B31-M31)*C31)+((E31-M31)*F31)+((H31-M31)*I31) -> 0
A32: UST OAT T-Shirt | B32: 375 | D32: =B32*C32 -> 0 | E32: 360 | G32: =E32*F32 -> 0 | H32: 340 | J32: =H32*I32 -> 0 | K32: =D32+G32+J32 -> 0 | L32: =C32+F32+I32 -> 0 | M32: 280 | N32: 33.6 | O32: 28 | P32: =((B32-M32)*C32)+((E32-M32)*F32)+((H32-M32)*I32) -> 0
A33: UST T-Shirt Sports | B33: 430 | C33: 12 | D33: =B33*C33 -> 5160 | E33: 400 | G33: =E33*F33 -> 0 | H33: 350 | J33: =H33*I33 -> 0 | K33: =D33+G33+J33 -> 5160 | L33: =C33+F33+I33 -> 12 | M33: 260 | N33: 31.2 | O33: 26 | P33: =((B33-M33)*C33)+((E33-M33)*F33)+((H33-M33)*I33) -> 2040
A34: UST T-Shirt Tiger Pattern | B34: 450 | C34: 8 | D34: =B34*C34 -> 3600 | E34: 430 | G34: =E34*F34 -> 0 | H34: 400 | J34: =H34*I34 -> 0 | K34: =D34+G34+J34 -> 3600 | L34: =C34+F34+I34 -> 8 | M34: 330 | N34: 39.6 | O34: 33 | P34: =((B34-M34)*C34)+((E34-M34)*F34)+((H34-M34)*I34) -> 960
A35: UST Happy Tiger | B35: 450 | C35: 2 | D35: =B35*C35 -> 900 | E35: 400 | G35: =E35*F35 -> 0 | H35: 350 | J35: =H35*I35 -> 0 | K35: =D35+G35+J35 -> 900 | L35: =C35+F35+I35 -> 2 | M35: 280 | N35: 33.6 | O35: 28 | P35: =((B35-M35)*C35)+((E35-M35)*F35)+((H35-M35)*I35) -> 340
A36: OAT Tote Bag (Phased Out) | B36: 220 | D36: =B36*C36 -> 0 | G36: =E36*F36 -> 0 | J36: =H36*I36 -> 0 | K36: =D36+G36+J36 -> 0 | L36: =C36+F36+I36 -> 0 | M36: 120 | P36: =((B36-M36)*C36)+((E36-M36)*F36)+((H36-M36)*I36) -> 0
C37: TOTAL | D37: =SUM(D29:D36) -> 11860 | F37: TOTAL | G37: =SUM(G29:G36) -> 0 | I37: TOTAL | J37: =SUM(J29:J36) -> 0 | K37: =D37+G37+J37 -> 11860 | M37: TOTAL | P37: =SUM(P29:P36) -> 3990
A38: USTORE | B38: RETAIL PRICE | C38: PCS SOLD | D38: SALES | E38: DISCOUNTED PRICE | F38: PCS SOLD | G38: SALES | H38: SPECIAL DISC. PRICE | I38: PCS SOLD | J38: SALES | K38: TOTAL SALES | L38: TOTALQTY SOLD | M38: PRODUCTION PRICE | N38: 12% Vat | O38: 10% Mark Up | P38: PROFIT
A39: Auto Umbrella | B39: 250 | D39: =B39*C39 -> 0 | G39: =E39*F39 -> 0 | J39: =H39*I39 -> 0 | K39: =D39+G39+J39 -> 0 | L39: =C39+F39+I39 -> 0 | P39: =((B39-M39)*C39)+((E39-M39)*F39)+((H39-M39)*I39) -> 0
A40: Bag | B40: 250 | D40: =B40*C40 -> 0 | E40: 150 | G40: =E40*F40 -> 0 | J40: =H40*I40 -> 0 | K40: =D40+G40+J40 -> 0 | L40: =C40+F40+I40 -> 0 | P40: =((B40-M40)*C40)+((E40-M40)*F40)+((H40-M40)*I40) -> 0
A41: Eco Bag CGEEE! | B41: 50 | C41: 1 | D41: =B41*C41 -> 50 | E41: 35 | G41: =E41*F41 -> 0 | J41: =H41*I41 -> 0 | K41: =D41+G41+J41 -> 50 | L41: =C41+F41+I41 -> 1 | P41: =((B41-M41)*C41)+((E41-M41)*F41)+((H41-M41)*I41) -> 50
A42: Keychain | B42: 150 | C42: 6 | D42: =B42*C42 -> 900 | E42: 120 | G42: =E42*F42 -> 0 | H42: 75 | J42: =H42*I42 -> 0 | K42: =D42+G42+J42 -> 900 | L42: =C42+F42+I42 -> 6 | P42: =((B42-M42)*C42)+((E42-M42)*F42)+((H42-M42)*I42) -> 900
A43: Kit Set | B43: 800 | D43: =B43*C43 -> 0 | E43: 750 | G43: =E43*F43 -> 0 | H43: 700 | J43: =H43*I43 -> 0 | K43: =D43+G43+J43 -> 0 | L43: =C43+F43+I43 -> 0 | P43: =((B43-M43)*C43)+((E43-M43)*F43)+((H43-M43)*I43) -> 0
A44: Lanyard | B44: 190 | C44: 3 | D44: =B44*C44 -> 570 | E44: 175 | G44: =E44*F44 -> 0 | H44: 150 | J44: =H44*I44 -> 0 | K44: =D44+G44+J44 -> 570 | L44: =C44+F44+I44 -> 3 | M44: 117 | N44: 14.04 | O44: 11.7 | P44: =((B44-M44)*C44)+((E44-M44)*F44)+((H44-M44)*I44) -> 219
A45: Lanyard | B45: 180 | C45: 1 | D45: =B45*C45 -> 180 | E45: 165 | G45: =E45*F45 -> 0 | H45: 140 | J45: =H45*I45 -> 0 | K45: =D45+G45+J45 -> 180 | L45: =C45+F45+I45 -> 1 | M45: 110 | N45: 13.2 | O45: 11 | P45: =((B45-M45)*C45)+((E45-M45)*F45)+((H45-M45)*I45) -> 70
A46: NB | B46: 75 | D46: =B46*C46 -> 0 | G46: =E46*F46 -> 0 | J46: =H46*I46 -> 0 | K46: =D46+G46+J46 -> 0 | L46: =C46+F46+I46 -> 0 | P46: =((B46-M46)*C46)+((E46-M46)*F46)+((H46-M46)*I46) -> 0
A47: NB | B47: 100 | D47: =B47*C47 -> 0 | E47: 80 | G47: =E47*F47 -> 0 | H47: 70 | J47: =H47*I47 -> 0 | K47: =D47+G47+J47 -> 0 | L47: =C47+F47+I47 -> 0 | P47: =((B47-M47)*C47)+((E47-M47)*F47)+((H47-M47)*I47) -> 0
A48: Sash Big | B48: 600 | C48: 1 | D48: =B48*C48 -> 600 | E48: 500 | G48: =E48*F48 -> 0 | H48: 400 | J48: =H48*I48 -> 0 | K48: =D48+G48+J48 -> 600 | L48: =C48+F48+I48 -> 1 | P48: =((B48-M48)*C48)+((E48-M48)*F48)+((H48-M48)*I48) -> 600
A49: Sash Small | B49: 150 | C49: 2 | D49: =B49*C49 -> 300 | E49: 125 | G49: =E49*F49 -> 0 | H49: 100 | J49: =H49*I49 -> 0 | K49: =D49+G49+J49 -> 300 | L49: =C49+F49+I49 -> 2 | P49: =((B49-M49)*C49)+((E49-M49)*F49)+((H49-M49)*I49) -> 300
A50: Shabby Hat | B50: 200 | C50: 1 | D50: =B50*C50 -> 200 | E50: 175 | G50: =E50*F50 -> 0 | H50: 150 | J50: =H50*I50 -> 0 | K50: =D50+G50+J50 -> 200 | L50: =C50+F50+I50 -> 1 | P50: =((B50-M50)*C50)+((E50-M50)*F50)+((H50-M50)*I50) -> 200
A51: Tiger Stuff Toy Small Grad | B51: 250 | C51: 7 | D51: =B51*C51 -> 1750 | E51: 230 | G51: =E51*F51 -> 0 | H51: 200 | J51: =H51*I51 -> 0 | K51: =D51+G51+J51 -> 1750 | L51: =C51+F51+I51 -> 7 | P51: =((B51-M51)*C51)+((E51-M51)*F51)+((H51-M51)*I51) -> 1750
A52: Tote Bag CGEEE! | B52: 120 | D52: =B52*C52 -> 0 | E52: 100 | G52: =E52*F52 -> 0 | H52: 80 | J52: =H52*I52 -> 0 | K52: =D52+G52+J52 -> 0 | L52: =C52+F52+I52 -> 0 | P52: =((B52-M52)*C52)+((E52-M52)*F52)+((H52-M52)*I52) -> 0
A53: Tote Bag Canvas White | B53: 160 | C53: 2 | D53: =B53*C53 -> 320 | G53: =E53*F53 -> 0 | J53: =H53*I53 -> 0 | K53: =D53+G53+J53 -> 320 | L53: =C53+F53+I53 -> 2 | P53: =((B53-M53)*C53)+((E53-M53)*F53)+((H53-M53)*I53) -> 320
A54: Tote (One For UST) | B54: 300 | C54: 1 | D54: =B54*C54 -> 300 | E54: 275 | G54: =E54*F54 -> 0 | H54: 250 | J54: =H54*I54 -> 0 | K54: =D54+G54+J54 -> 300 | L54: =C54+F54+I54 -> 1 | P54: =((B54-M54)*C54)+((E54-M54)*F54)+((H54-M54)*I54) -> 300
A55: Tumbler | B55: 150 | D55: =B55*C55 -> 0 | G55: =E55*F55 -> 0 | J55: =H55*I55 -> 0 | K55: =D55+G55+J55 -> 0 | L55: =C55+F55+I55 -> 0 | P55: =((B55-M55)*C55)+((E55-M55)*F55)+((H55-M55)*I55) -> 0
A56: Umb. Cane | B56: 500 | D56: =B56*C56 -> 0 | E56: 450 | G56: =E56*F56 -> 0 | H56: 400 | J56: =H56*I56 -> 0 | K56: =D56+G56+J56 -> 0 | L56: =C56+F56+I56 -> 0 | P56: =((B56-M56)*C56)+((E56-M56)*F56)+((H56-M56)*I56) -> 0
A57: Umb (One For UST) | B57: 350 | C57: 2 | D57: =B57*C57 -> 700 | E57: 300 | G57: =E57*F57 -> 0 | H57: 250 | J57: =H57*I57 -> 0 | K57: =D57+G57+J57 -> 700 | L57: =C57+F57+I57 -> 2 | P57: =((B57-M57)*C57)+((E57-M57)*F57)+((H57-M57)*I57) -> 700
A58: Old Umbrella | B58: 250 | D58: =B58*C58 -> 0 | E58: 200 | G58: =E58*F58 -> 0 | H58: 180 | J58: =H58*I58 -> 0 | K58: =D58+G58+J58 -> 0 | L58: =C58+F58+I58 -> 0
A59: Utensil | B59: 250 | D59: =B59*C59 -> 0 | E59: 200 | G59: =E59*F59 -> 0 | H59: 180 | J59: =H59*I59 -> 0 | K59: =D59+G59+J59 -> 0 | L59: =C59+F59+I59 -> 0
C60: TOTAL | D60: =SUM(D39:D59) -> 5870 | F60: TOTAL | G60: =SUM(G39:G59) -> 0 | I60: TOTAL | J60: =SUM(J39:J59) -> 0 | K60: =D60+G60+J60 -> 5870 | M60: TOTAL | P60: =SUM(P39:P59) -> 5409
A61: TET AND DARS | B61: RETAIL PRICE | C61: PCS SOLD | D61: SALES | E61: DISCOUNTED PRICE | F61: PCS SOLD | G61: SALES | H61: SPECIAL DISC. PRICE | I61: PCS SOLD | J61: SALES | K61: TOTAL SALES | L61: TOTALQTY SOLD | M61: PRODUCTION PRICE | N61: 12% Vat | O61: 10% Mark Up | P61: PROFIT
A62: Arch | B62: 320 | C62: 2 | D62: =B62*C62 -> 640 | E62: 300 | G62: =E62*F62 -> 0 | H62: 300 | J62: =H62*I62 -> 0 | K62: =D62+G62+J62 -> 640 | L62: =C62+F62+I62 -> 2 | M62: 240 | N62: 28.8 | O62: 24 | P62: =((B62-M62)*C62)+((E62-M62)*F62)+((H62-M62)*I62) -> 160
A63: Eco Bag | B63: 80 | C63: 1 | D63: =B63*C63 -> 80 | E63: 70 | G63: =E63*F63 -> 0 | H63: 60 | J63: =H63*I63 -> 0 | K63: =D63+G63+J63 -> 80 | L63: =C63+F63+I63 -> 1 | M63: 60 | P63: =((B63-M63)*C63)+((E63-M63)*F63)+((H63-M63)*I63) -> 20
A64: Eco Bag | B64: 130 | D64: =B64*C64 -> 0 | E64: 120 | G64: =E64*F64 -> 0 | H64: 110 | J64: =H64*I64 -> 0 | K64: =D64+G64+J64 -> 0 | L64: =C64+F64+I64 -> 0 | M64: 100 | P64: =((B64-M64)*C64)+((E64-M64)*F64)+((H64-M64)*I64) -> 0
A65: Main Building | B65: 430 | D65: =B65*C65 -> 0 | E65: 430 | G65: =E65*F65 -> 0 | H65: 430 | J65: =H65*I65 -> 0 | K65: =D65+G65+J65 -> 0 | L65: =C65+F65+I65 -> 0 | M65: 350 | N65: 42 | O65: 35 | P65: =((B65-M65)*C65)+((E65-M65)*F65)+((H65-M65)*I65) -> 0
A66: Mug | B66: 170 | D66: =B66*C66 -> 0 | E66: 160 | G66: =E66*F66 -> 0 | H66: 150 | J66: =H66*I66 -> 0 | K66: =D66+G66+J66 -> 0 | L66: =C66+F66+I66 -> 0 | M66: 125 | N66: 15 | O66: 12.5 | P66: =((B66-M66)*C66)+((E66-M66)*F66)+((H66-M66)*I66) -> 0
A67: Notebook | B67: 220 | D67: =B67*C67 -> 0 | G67: =E67*F67 -> 0 | J67: =H67*I67 -> 0 | K67: =D67+G67+J67 -> 0 | L67: =C67+F67+I67 -> 0 | P67: =((B67-M67)*C67)+((E67-M67)*F67)+((H67-M67)*I67) -> 0
A68: Pen | B68: 50 | D68: =B68*C68 -> 0 | G68: =E68*F68 -> 0 | J68: =H68*I68 -> 0 | K68: =D68+G68+J68 -> 0 | L68: =C68+F68+I68 -> 0 | M68: 42 | P68: =((B68-M68)*C68)+((E68-M68)*F68)+((H68-M68)*I68) -> 0
A69: Pen | B69: 25 | D69: =B69*C69 -> 0 | G69: =E69*F69 -> 0 | J69: =H69*I69 -> 0 | K69: =D69+G69+J69 -> 0 | L69: =C69+F69+I69 -> 0 | M69: 20 | P69: =((B69-M69)*C69)+((E69-M69)*F69)+((H69-M69)*I69) -> 0
A70: Sticker | B70: 115 | C70: 1 | D70: =B70*C70 -> 115 | E70: 110 | G70: =E70*F70 -> 0 | H70: 105 | J70: =H70*I70 -> 0 | K70: =D70+G70+J70 -> 115 | L70: =C70+F70+I70 -> 1 | M70: 85 | P70: =((B70-M70)*C70)+((E70-M70)*F70)+((H70-M70)*I70) -> 30
A71: Sticker | B71: 20 | D71: =B71*C71 -> 0 | E71: 20 | G71: =E71*F71 -> 0 | H71: 20 | J71: =H71*I71 -> 0 | K71: =D71+G71+J71 -> 0 | L71: =C71+F71+I71 -> 0 | M71: 15 | P71: =((B71-M71)*C71)+((E71-M71)*F71)+((H71-M71)*I71) -> 0
A72: Tote | B72: 230 | D72: =B72*C72 -> 0 | G72: =E72*F72 -> 0 | J72: =H72*I72 -> 0 | K72: =D72+G72+J72 -> 0 | L72: =C72+F72+I72 -> 0 | P72: =((B72-M72)*C72)+((E72-M72)*F72)+((H72-M72)*I72) -> 0
C73: TOTAL | D73: =SUM(D62:D72) -> 835 | F73: TOTAL | G73: =SUM(G62:G72) -> 0 | I73: TOTAL | J73: =SUM(J62:J72) -> 0 | K73: =D73+G73+J73 -> 835 | M73: TOTAL | P73: =SUM(P62:P72) -> 210
A74: BLAZE | B74: RETAIL PRICE | C74: PCS SOLD | D74: SALES | E74: DISCOUNTED PRICE | F74: PCS SOLD | G74: SALES | H74: SPECIAL DISC. PRICE | I74: PCS SOLD | J74: SALES | K74: TOTAL SALES | L74: TOTALQTY SOLD | M74: PRODUCTION PRICE | N74: 12% Vat | O74: 10% Mark Up | P74: PROFIT
A75: Crew Neck Shirt | B75: 475 | D75: =B75*C75 -> 0 | E75: 450 | G75: =E75*F75 -> 0 | H75: 430 | J75: =H75*I75 -> 0 | K75: =D75+G75+J75 -> 0 | L75: =C75+F75+I75 -> 0 | M75: 350 | N75: 42 | O75: 35 | P75: =((B75-M75)*C75)+((E75-M75)*F75)+((H75-M75)*I75) -> 0
A76: Polo Shirt | B76: 800 | C76: 1 | D76: =B76*C76 -> 800 | E76: 750 | G76: =E76*F76 -> 0 | H76: 700 | J76: =H76*I76 -> 0 | K76: =D76+G76+J76 -> 800 | L76: =C76+F76+I76 -> 1 | M76: 550 | N76: 66 | O76: 55 | P76: =((B76-M76)*C76)+((E76-M76)*F76)+((H76-M76)*I76) -> 250
A77: Socks | B77: 375 | D77: =B77*C77 -> 0 | E77: 350 | G77: =E77*F77 -> 0 | H77: 325 | J77: =H77*I77 -> 0 | K77: =D77+G77+J77 -> 0 | L77: =C77+F77+I77 -> 0 | M77: 250 | N77: 30 | O77: 25 | P77: =((B77-M77)*C77)+((E77-M77)*F77)+((H77-M77)*I77) -> 0
A78: socks set of 3 | B78: 950 | D78: =B78*C78 -> 0 | E78: 900 | G78: =E78*F78 -> 0 | H78: 800 | J78: =H78*I78 -> 0 | K78: =D78+G78+J78 -> 0 | L78: =C78+F78+I78 -> 0 | M78: 750 | N78: 90 | O78: 75 | P78: =((B78-M78)*C78)+((E78-M78)*F78)+((H78-M78)*I78) -> 0
C79: TOTAL | D79: =SUM(D75:D78) -> 800 | F79: TOTAL | G79: =SUM(G75:G78) -> 0 | I79: TOTAL | J79: =SUM(J75:J78) -> 0 | K79: =D79+G79+J79 -> 800 | M79: TOTAL | P79: =SUM(P75:P78) -> 250
A80: VARSITY LIFE STYLE | B80: RETAIL PRICE | C80: PCS SOLD | D80: SALES | E80: DISCOUNTED PRICE | F80: PCS SOLD | G80: SALES | H80: SPECIAL DISC. PRICE | I80: PCS SOLD | J80: SALES | K80: TOTAL SALES | L80: TOTALQTY SOLD | M80: PRODUCTION PRICE | N80: 12% Vat | O80: 10% Mark Up | P80: PROFIT
A81: Baller | B81: 100 | C81: 1 | D81: =B81*C81 -> 100 | K81: =D81+G81+J81 -> 100 | L81: =C81+F81+I81 -> 1 | M81: 90
A82: Caps | B82: 800 | C82: 1 | D82: =B82*C82 -> 800 | K82: =D82+G82+J82 -> 800 | L82: =C82+F82+I82 -> 1 | M82: 700
A83: Hoodie | B83: 1750 | D83: =B83*C83 -> 0 | K83: =D83+G83+J83 -> 0 | L83: =C83+F83+I83 -> 0 | M83: 1500
A84: Keychain | B84: 100 | D84: =B84*C84 -> 0 | K84: =D84+G84+J84 -> 0 | L84: =C84+F84+I84 -> 0 | M84: 90
A85: Lanyard | B85: 250 | C85: 1 | D85: =B85*C85 -> 250 | K85: =D85+G85+J85 -> 250 | L85: =C85+F85+I85 -> 1 | M85: 200
A86: Long Sticker | B86: 100 | D86: =B86*C86 -> 0 | K86: =D86+G86+J86 -> 0 | L86: =C86+F86+I86 -> 0 | M86: 90
A87: Oversized Sweatshirt | B87: 1500 | D87: =B87*C87 -> 0 | K87: =D87+G87+J87 -> 0 | L87: =C87+F87+I87 -> 0 | M87: 1300
A88: Scarves | B88: 400 | C88: 1 | D88: =B88*C88 -> 400 | K88: =D88+G88+J88 -> 400 | L88: =C88+F88+I88 -> 1 | M88: 350
A89: Shirts | B89: 700 | C89: 1 | D89: =B89*C89 -> 700 | K89: =D89+G89+J89 -> 700 | L89: =C89+F89+I89 -> 1 | M89: 600
A90: Sticker Pack | B90: 150 | D90: =B90*C90 -> 0 | K90: =D90+G90+J90 -> 0 | L90: =C90+F90+I90 -> 0 | M90: 130
A91: Varsity Jacket | B91: 2100 | D91: =B91*C91 -> 0 | K91: =D91+G91+J91 -> 0 | L91: =C91+F91+I91 -> 0 | M91: 1900
C92: TOTAL | D92: =SUM(D81:D91) -> 2250 | F92: TOTAL | G92: =SUM(G81:G91) -> 0 | I92: TOTAL | J92: =SUM(J81:J91) -> 0 | K92: =D92+G92+J92 -> 2250 | M92: TOTAL | P92: =SUM(P81:P91) -> 0
A93: MITSUI | B93: RETAIL PRICE | C93: PCS SOLD | D93: SALES | E93: DISCOUNTED PRICE | F93: PCS SOLD | G93: SALES | H93: SPECIAL DISC. PRICE | I93: PCS SOLD | J93: SALES | K93: TOTAL SALES | L93: TOTALQTY SOLD | M93: PRODUCTION PRICE | N93: 12% Vat | O93: 10% Mark Up | P93: PROFIT
A94: Stylus pen | B94: 45 | D94: =B94*C94 -> 0 | E94: 40 | G94: =E94*F94 -> 0 | H94: 25 | J94: =H94*I94 -> 0 | K94: =D94+G94+J94 -> 0 | L94: =C94+F94+I94 -> 0 | M94: 17.36 | N94: 2.08 | O94: 1.74 | P94: =((B94-M94)*C94)+((E94-M94)*F94)+((H94-M94)*I94) -> 0
A95: Retractable | B95: 25 | D95: =B95*C95 -> 0 | E95: 15 | G95: =E95*F95 -> 0 | H95: 20 | J95: =H95*I95 -> 0 | K95: =D95+G95+J95 -> 0 | L95: =C95+F95+I95 -> 0 | M95: 10.08 | N95: 1.21 | O95: 1.01 | P95: =((B95-M95)*C95)+((E95-M95)*F95)+((H95-M95)*I95) -> 0
C96: TOTAL | D96: =SUM(D94+D95) -> 0 | F96: TOTAL | G96: =SUM(G94+G95) -> 0 | I96: TOTAL | J96: =SUM(J94+J95) -> 0 | K96: =D96+G96+J96 -> 0 | M96: TOTAL | P96: =SUM(P94) -> 0
A97: CENTRAL SEMINARY | B97: RETAIL PRICE | C97: PCS SOLD | D97: SALES | E97: DISCOUNTED PRICE | F97: PCS SOLD | G97: SALES | H97: SPECIAL DISC. PRICE | I97: PCS SOLD | J97: SALES | K97: TOTAL SALES | L97: TOTALQTY SOLD | M97: PRODUCTION PRICE | N97: 12% Vat | O97: 10% Mark Up | P97: PROFIT
A98: Subli. Shirt | B98: 550 | C98: 1 | D98: =B98*C98 -> 550 | G98: =E98*F98 -> 0 | J98: =H98*I98 -> 0 | K98: =D98+G98+J98 -> 550 | L98: =C98+F98+I98 -> 1 | M98: 500 | P98: =((B98-M98)*C98)+((E98-M98)*F98)+((H98-M98)*I98) -> 50
C99: GRAND TOTAL | D99: =D17+D27+D37+D60+D73+D79+D96+D98+D92 -> 36465 | F99: GRAND TOTAL | G99: =G17+G27+G37+G60+G73+G79+G96+G98+G92 -> 0 | I99: GRAND TOTAL | J99: =J17+J27+J37+J60+J73+J79+J96+J98 -> 2700 | K99: =D99+G99+J99 -> 39165 | M99: GRAND TOTAL | P99: =P17+P27+P37+P60+P73+P79+P96+P98 -> 14919
C100: TOTAL SALE | E100: =K99 -> 39165 | N100: TOTAL PROFIT | P100: =P99 -> 14919
...

Sheet May 14
A1: DAILY SALES REPORT
A2: 45426
A3: ITEMS | B3: RETAIL PRICE | C3: PCS SOLD | D3: SALES | E3: DISCOUNTED PRICE | F3: PCS SOLD | G3: SALES | H3: SPECIAL DISC. PRICE | I3: PCS SOLD | J3: SALES | K3: TOTAL SALES | L3: TOTALQTY SOLD | M3: PRODUCTION PRICE | N3: 12% Vat | O3: 10% Mark Up | P3: PROFIT
A4: NAPOLIZ
A5: Backpack Bag | B5: 1750 | D5: =B5*C5 -> 0 | E5: 1600 | G5: =E5*F5 -> 0 | H5: 1400 | J5: =H5*I5 -> 0 | K5: =D5+G5+J5 -> 0 | L5: =C5+F5+I5 -> 0 | M5: 840 | N5: 100.8 | O5: 84 | P5: =((B5-M5)*C5)+((E5-M5)*F5)+((H5-M5)*I5) -> 0
A6: Black Tote Bag (Phased Out) | B6: 280 | D6: =B6*C6 -> 0 | G6: =E6*F6 -> 0 | J6: =H6*I6 -> 0 | K6: =D6+G6+J6 -> 0 | L6: =C6+F6+I6 -> 0 | M6: 230 | P6: =((B6-M6)*C6)+((E6-M6)*F6)+((H6-M6)*I6) -> 0
A7: Double Canopy | B7: 639 | D7: =B7*C7 -> 0 | E7: 575 | G7: =E7*F7 -> 0 | H7: 500 | J7: =H7*I7 -> 0 | K7: =D7+G7+J7 -> 0 | L7: =C7+F7+I7 -> 0 | M7: 330 | N7: 39.6 | O7: 33 | P7: =((B7-M7)*C7)+((E7-M7)*F7)+((H7-M7)*I7) -> 0
A8: Laptop Bag | B8: 1450 | C8: 1 | D8: =B8*C8 -> 1450 | E8: 1400 | G8: =E8*F8 -> 0 | H8: 1250 | J8: =H8*I8 -> 0 | K8: =D8+G8+J8 -> 1450 | L8: =C8+F8+I8 -> 1 | M8: 840 | N8: 100.8 | O8: 84 | P8: =((B8-M8)*C8)+((E8-M8)*F8)+((H8-M8)*I8) -> 610
A9: Script Santo Tomas with Tiger Back (B) | B9: 480 | C9: 1 | D9: =B9*C9 -> 480 | E9: 460 | G9: =E9*F9 -> 0 | H9: 450 | J9: =H9*I9 -> 0 | K9: =D9+G9+J9 -> 480 | L9: =C9+F9+I9 -> 1 | M9: 360 | N9: 43.2 | O9: 36 | P9: =((B9-M9)*C9)+((E9-M9)*F9)+((H9-M9)*I9) -> 120
A10: Side Tiger Hoodie | B10: 1480 | D10: =B10*C10 -> 0 | E10: 1400 | G10: =E10*F10 -> 0 | H10: 1375 | J10: =H10*I10 -> 0 | K10: =D10+G10+J10 -> 0 | L10: =C10+F10+I10 -> 0 | M10: 1125 | N10: 135 | O10: 112.5 | P10: =((B10-M10)*C10)+((E10-M10)*F10)+((H10-M10)*I10) -> 0
A11: Sling Bag | B11: 330 | D11: =B11*C11 -> 0 | E11: 320 | G11: =E11*F11 -> 0 | H11: 300 | J11: =H11*I11 -> 0 | K11: =D11+G11+J11 -> 0 | L11: =C11+F11+I11 -> 0 | M11: 260 | N11: 31.2 | O11: 26 | P11: =((B11-M11)*C11)+((E11-M11)*F11)+((H11-M11)*I11) -> 0
A12: Front Tiger Hoodie | B12: 1440 | D12: =B12*C12 -> 0 | E12: 1400 | G12: =E12*F12 -> 0 | H12: 1375 | J12: =H12*I12 -> 0 | K12: =D12+G12+J12 -> 0 | L12: =C12+F12+I12 -> 0 | M12: 1125 | N12: 135 | O12: 112.5 | P12: =((B12-M12)*C12)+((E12-M12)*F12)+((H12-M12)*I12) -> 0
A13: University of Santo Tomas (B) | B13: 450 | C13: 12 | D13: =B13*C13 -> 5400 | E13: 440 | G13: =E13*F13 -> 0 | H13: 425 | J13: =H13*I13 -> 0 | K13: =D13+G13+J13 -> 5400 | L13: =C13+F13+I13 -> 12 | M13: 360 | N13: 43.2 | O13: 36 | P13: =((B13-M13)*C13)+((E13-M13)*F13)+((H13-M13)*I13) -> 1080
A14: UST Tiger Front and Back Graphic (W) | B14: 500 | C14: 1 | D14: =B14*C14 -> 500 | E14: 480 | G14: =E14*F14 -> 0 | H14: 450 | J14: =H14*I14 -> 0 | K14: =D14+G14+J14 -> 500 | L14: =C14+F14+I14 -> 1 | M14: 360 | N14: 43.2 | O14: 36 | P14: =((B14-M14)*C14)+((E14-M14)*F14)+((H14-M14)*I14) -> 140
A15: White Tote Bag | B15: 260 | D15: =B15*C15 -> 0 | E15: 250 | G15: =E15*F15 -> 0 | H15: 240 | J15: =H15*I15 -> 0 | K15: =D15+G15+J15 -> 0 | L15: =C15+F15+I15 -> 0 | M15: 200 | N15: 24 | O15: 20 | P15: =((B15-M15)*C15)+((E15-M15)*F15)+((H15-M15)*I15) -> 0
A16: Wind Breaker | B16: 1650 | C16: 1 | D16: =B16*C16 -> 1650 | E16: 1600 | G16: =E16*F16 -> 0 | H16: 1500 | J16: =H16*I16 -> 0 | K16: =D16+G16+J16 -> 1650 | L16: =C16+F16+I16 -> 1 | M16: 1125 | N16: 135 | O16: 112.5 | P16: =((B16-M16)*C16)+((E16-M16)*F16)+((H16-M16)*I16) -> 525
C17: TOTAL | D17: =SUM(D5:D16) -> 9480 | F17: TOTAL | G17: =SUM(G5:G16) -> 0 | I17: TOTAL | J17: =SUM(J5:J16) -> 0 | K17: =D17+G17+J17 -> 9480 | M17: TOTAL | P17: =SUM(P5:P16) -> 2475
A18: JYL | B18: RETAIL PRICE | C18: PCS SOLD | D18: SALES | E18: DISCOUNTED PRICE | F18: PCS SOLD | G18: SALES | H18: SPECIAL DISC. PRICE | I18: PCS SOLD | J18: SALES | K18: TOTAL SALES | L18: TOTALQTY SOLD | M18: PRODUCTION PRICE | N18: 12% Vat | O18: 10% Mark Up | P18: PROFIT
A19: GT Shirt | B19: 375 | C19: 1 | D19: =B19*C19 -> 375 | E19: 350 | G19: =E19*F19 -> 0 | H19: 325 | J19: =H19*I19 -> 0 | K19: =D19+G19+J19 -> 375 | L19: =C19+F19+I19 -> 1 | M19: 250 | N19: 30 | O19: 25 | P19: =((B19-M19)*C19)+((E19-M19)*F19)+((H19-M19)*I19) -> 125
A20: Jacket | B20: 1900 | C20: 1 | D20: =B20*C20 -> 1900 | E20: 1700 | G20: =E20*F20 -> 0 | H20: 1500 | I20: 1 | J20: =H20*I20 -> 1500 | K20: =D20+G20+J20 -> 3400 | L20: =C20+F20+I20 -> 2 | M20: 1200 | N20: 144 | O20: 120 | P20: =((B20-M20)*C20)+((E20-M20)*F20)+((H20-M20)*I20) -> 1000
A21: Poloshirt 123456 | B21: 860 | D21: =B21*C21 -> 0 | E21: 800 | G21: =E21*F21 -> 0 | H21: 750 | J21: =H21*I21 -> 0 | K21: =D21+G21+J21 -> 0 | L21: =C21+F21+I21 -> 0 | M21: 600 | N21: 72 | O21: 60 | P21: =((B21-M21)*C21)+((E21-M21)*F21)+((H21-M21)*I21) -> 0
A22: VB Jersey w/ sig. (Phased Out) | B22: 2800 | D22: =B22*C22 -> 0 | G22: =E22*F22 -> 0 | J22: =H22*I22 -> 0 | K22: =D22+G22+J22 -> 0 | L22: =C22+F22+I22 -> 0 | M22: 800 | N22: 96 | O22: 80 | P22: =((B22-M22)*C22)+((E22-M22)*F22)+((H22-M22)*I22) -> 0
A23: VB Jersey w/o sig. | B23: 2000 | D23: =B23*C23 -> 0 | E23: 1800 | G23: =E23*F23 -> 0 | H23: 1500 | J23: =H23*I23 -> 0 | K23: =D23+G23+J23 -> 0 | L23: =C23+F23+I23 -> 0 | M23: 800 | P23: =((B23-M23)*C23)+((E23-M23)*F23)+((H23-M23)*I23) -> 0
A24: VB Jersey w/o sig. | B24: 1500 | D24: =B24*C24 -> 0 | E24: 1400 | G24: =E24*F24 -> 0 | H24: 1300 | J24: =H24*I24 -> 0 | K24: =D24+G24+J24 -> 0 | L24: =C24+F24+I24 -> 0 | M24: 800 | P24: =((B24-M24)*C24)+((E24-M24)*F24)+((H24-M24)*I24) -> 0
A25: VB Jersey w/o sig. | B25: 1000 | D25: =B25*C25 -> 0 | E25: 980 | G25: =E25*F25 -> 0 | H25: 950 | J25: =H25*I25 -> 0 | K25: =D25+G25+J25 -> 0 | L25: =C25+F25+I25 -> 0 | M25: 800 | P25: =((B25-M25)*C25)+((E25-M25)*F25)+((H25-M25)*I25) -> 0
A26: VB Jersey with sig. (Phased Out) | B26: 1500 | D26: =B26*C26 -> 0 | G26: =E26*F26 -> 0 | J26: =H26*I26 -> 0 | K26: =D26+G26+J26 -> 0 | L26: =C26+F26+I26 -> 0 | M26: 800 | P26: =((B26-M26)*C26)+((E26-M26)*F26)+((H26-M26)*I26) -> 0
C27: TOTAL | D27: =SUM(D19:D26) -> 2275 | F27: TOTAL | G27: =SUM(G19:G26) -> 0 | I27: TOTAL | J27: =SUM(J19:J26) -> 1500 | K27: =D27+G27+J27 -> 3775 | M27: TOTAL | P27: =SUM(P19:P26) -> 1125
A28: JUC | B28: RETAIL PRICE | C28: PCS SOLD | D28: SALES | E28: DISCOUNTED PRICE | F28: PCS SOLD | G28: SALES | H28: SPECIAL DISC. PRICE | I28: PCS SOLD | J28: SALES | K28: TOTAL SALES | L28: TOTALQTY SOLD | M28: PRODUCTION PRICE | N28: 12% Vat | O28: 10% Mark Up | P28: PROFIT
A29: UST OAT Hoodie Jacket | B29: 1450 | C29: 2 | D29: =B29*C29 -> 2900 | E29: 1400 | G29: =E29*F29 -> 0 | H29: 1300 | J29: =H29*I29 -> 0 | K29: =D29+G29+J29 -> 2900 | L29: =C29+F29+I29 -> 2 | M29: 1000 | N29: 120 | O29: 100 | P29: =((B29-M29)*C29)+((E29-M29)*F29)+((H29-M29)*I29) -> 900
A30: UST OAT MUG | B30: 150 | D30: =B30*C30 -> 0 | E30: 140 | G30: =E30*F30 -> 0 | H30: 135 | J30: =H30*I30 -> 0 | K30: =D30+G30+J30 -> 0 | L30: =C30+F30+I30 -> 0 | M30: 110 | N30: 12 | O30: 10 | P30: =((B30-M30)*C30)+((E30-M30)*F30)+((H30-M30)*I30) -> 0
A31: UST OAT MUG (WE) Inside | B31: 150 | D31: =B31*C31 -> 0 | E31: 140 | G31: =E31*F31 -> 0 | H31: 135 | J31: =H31*I31 -> 0 | K31: =D31+G31+J31 -> 0 | L31: =C31+F31+I31 -> 0 | M31: 100 | N31: 12 | O31: 10 | P31: =((B31-M31)*C31)+((E31-M31)*F31)+((H31-M31)*I31) -> 0
